Workbook

Sheet Summary
A1: Tamil Nadu Sports Facilities — Consolidated & De-duplicated
A3: Source files merged:
A4: 1. Tamil_Nadu_38_Districts_New_data.xlsx
A5: 2. TamilNadu_Sports_Data__1_.xlsx
A7: S.No | B7: District | C7: Unique Records (after de-dup) | D7: Leads | E7: Rejection
A8: 1 | B8: Ariyalur | C8: =COUNTA(Ariyalur!A2:A100000) -> 392
A9: 2 | B9: Chengalpattu | C9: =COUNTA(Chengalpattu!A2:A100000) -> 380
A10: 3 | B10: Chennai | C10: =COUNTA(Chennai!A2:A100000) -> 578
A11: 4 | B11: Coimbatore | C11: =COUNTA(Coimbatore!A2:A100000) -> 491
A12: 5 | B12: Cuddalore | C12: =COUNTA(Cuddalore!A2:A99999) -> 364
A13: 6 | B13: Dharmapuri | C13: =COUNTA(Dharmapuri!A2:A100000) -> 274
A14: 7 | B14: Dindigul | C14: =COUNTA(Dindigul!A2:A99996) -> 371 | E14: 75
A15: 8 | B15: Erode | C15: =COUNTA(Erode!A2:A100000) -> 232 | D15: 7 | E15: 117
A16: 9 | B16: Kallakurichi | C16: =COUNTA(Kallakurichi!A2:A100001) -> 351 | D16: 3
A17: 10 | B17: Kanchipuram | C17: =COUNTA(Kanchipuram!A2:A100000) -> 218
A18: 11 | B18: Kanniyakumari | C18: =COUNTA(Kanniyakumari!A1:A99997) -> 401
A19: 12 | B19: Karur | C19: =COUNTA(Karur!A2:A100000) -> 362
A20: 13 | B20: Krishnagiri | C20: =COUNTA(Krishnagiri!A2:A100000) -> 384
A21: 14 | B21: Madurai | C21: =COUNTA(Madurai!A2:A100000) -> 490
A22: 15 | B22: Mayiladuthurai | C22: =COUNTA(Mayiladuthurai!A2:A100000) -> 368
A23: 16 | B23: Nagapattinam | C23: =COUNTA(Nagapattinam!A2:A100000) -> 370
A24: 17 | B24: Namakkal | C24: =COUNTA(Namakkal!A2:A100000) -> 225
A25: 18 | B25: Nilgiris | C25: =COUNTA(Nilgiris!A2:A100000) -> 145
A26: 19 | B26: Perambalur | C26: =COUNTA(Perambalur!A2:A100000) -> 150
A27: 20 | B27: Pudukkottai | C27: =COUNTA(Pudukkottai!A2:A100000) -> 148
A28: 21 | B28: Ramanathapuram | C28: =COUNTA(Ramanathapuram!A2:A99999) -> 207
A29: 22 | B29: Ranipet | C29: =COUNTA(Ranipet!A2:A99999) -> 234
A30: 23 | B30: Salem | C30: =COUNTA(Salem!A2:A100000) -> 383
A31: 24 | B31: Sivagangai | C31: =COUNTA(Sivagangai!A2:A100000) -> 126 | E31: 49
A32: 25 | B32: Tenkasi | C32: =COUNTA(Tenkasi!A2:A100000) -> 137
A33: 26 | B33: Thanjavur | C33: =COUNTA(Thanjavur!A2:A100000) -> 179
A34: 27 | B34: Theni | C34: =COUNTA(Theni!A2:A100000) -> 169
A35: 28 | B35: Thoothukudi | C35: =COUNTA(Thoothukudi!A2:A100000) -> 214
A36: 29 | B36: Tiruchirappalli | C36: =COUNTA(Tiruchirappalli!A2:A100000) -> 265
A37: 30 | B37: Tirunelveli | C37: =COUNTA(Tirunelveli!A2:A100000) -> 221
A38: 31 | B38: Tirupathur | C38: =COUNTA(Tirupathur!A2:A100000) -> 180
A39: 32 | B39: Tiruppur | C39: =COUNTA(Tiruppur!A2:A100000) -> 218
A40: 33 | B40: Tiruvallur | C40: =COUNTA(Tiruvallur!A2:A100000) -> 172
A41: 34 | B41: Tiruvannamalai | C41: =COUNTA(Tiruvannamalai!A2:A100000) -> 147
A42: 35 | B42: Tiruvarur | C42: =COUNTA(Tiruvarur!A2:A100000) -> 139
A43: 36 | B43: Vellore | C43: =COUNTA(Vellore!A2:A99999) -> 190
A44: 37 | B44: Viluppuram | C44: =COUNTA(Viluppuram!A2:A100000) -> 179 | D44: 3 | E44: 63
A45: 38 | B45: Virudhunagar | C45: =COUNTA(Virudhunagar!A2:A100000) -> 160 | D45: 2 | E45: 39
B46: TOTAL | C46: =SUM(C8:C45) -> 10214

Sheet Sheet1

Sheet Ariyalur
A1: S.No | B1: District | C1: Category | D1: Facility Name | E1: Address | F1: Phone | G1: Source | H1: Maps Link | I1: Origin File
A2: 1 | B2: Ariyalur | C2: Academy | D2: Chola Sports Academy | E2: Jayankondam, Ariyalur-621802, Tamil Nadu | G2: old data | I2: TamilNadu_Sports_Data__1_.xlsx
A3: 2 | B3: Ariyalur | C3: Academy | D3: Hit Sports Academy | E3: Sevaga Street, Jayankondacholapuram, Ariyalur-621802, Tamil Nadu | F3: 7947112046 | G3: 25/03/2026 | I3: TamilNadu_Sports_Data__1_.xlsx
A4: 3 | B4: Ariyalur | C4: Academy | D4: Independent Cricket Academy | E4: 3/90, Colonystreet, Sundipallam, Jayankondam, Kundaveli, Ariyalur-612903, Tamil Nadu | F4: 7947128047 | G4: 25/03/2026 | I4: TamilNadu_Sports_Data__1_.xlsx
A5: 4 | B5: Ariyalur | C5: Academy | D5: Jai Ajay Badminton Academy | E5: Kovil St, Varadarajanpettai, Varadarajampettai, Ariyalur-621805, Tamil Nadu | F5: 7947424857 | G5: 25/03/2026 | I5: TamilNadu_Sports_Data__1_.xlsx
A6: 5 | B6: Ariyalur | C6: Academy | D6: Metro Indoor Sports Academy | E6: Annai Mahal, Permbalur - Ariyalur Rd, opposite 4 road, Min Nagar, Perambalur, Tamil Nadu 621220 | F6: 91598 45585 | G6: 25/03/2026 | I6: TamilNadu_Sports_Data__1_.xlsx
A7: 6 | B7: Ariyalur | C7: Academy | D7: Rook Squares Chess Academy | E7: No.43/12 A 1, Near Government Arts College, Rajaji Nagar, College Road, North, Ariyalur-621713, Tamil Nadu | F7: 8128412375 | G7: 25/03/2026 | I7: TamilNadu_Sports_Data__1_.xlsx
A8: 7 | B8: Ariyalur | C8: Academy | D8: Rook Squares Chess Academy & Chess Coaching Ariyalur District | E8: No43/12 A1, Near Government Arts College, Rajaji Nagar College Road, North, Ariyalur-621713, Tamil Nadu | F8: 7383489272 | G8: 25/03/2026 | I8: TamilNadu_Sports_Data__1_.xlsx
A9: 8 | B9: Ariyalur | C9: Academy | D9: SKY GOAL MARTIAL ARTS ACADEMY | E9: Pound St, opposite IcIcI ATM, near CSI Hr.sec School, MIN Nagar, Ariyalur, Tamil Nadu 621704 | F9: 90479 50482 | G9: 25/03/2026 | I9: TamilNadu_Sports_Data__1_.xlsx
A10: 9 | B10: Ariyalur | C10: Academy | D10: Thirumurugan Sports & Arts Academy | E10: Anandam Nagar, Jayankondam, Sendurai Road, Jayankondam, Ariyalur-621802, Tamil Nadu | F10: 7947124693 | G10: 25/03/2026 | I10: TamilNadu_Sports_Data__1_.xlsx
A11: 10 | B11: Ariyalur | C11: Athletic Track | D11: Ariyalur Thathanur Running Stadium | E11: Thathanur Main Road, near Thathanur Bazaar, Ariyalur District, Tamil Nadu 621749 | F11: +91 97895 91328 | G11: Google Maps | H11: https://maps.google.com/?q=Ariyalur+Thathanur+Running+Stadium+Ariyalur | I11: Tamil_Nadu_38_Districts_New_data.xlsx
A12: 11 | B12: Ariyalur | C12: Athletic Track | D12: Champion Sendurai Running Stadium | E12: Sendurai Main Road, near Sendurai Bazaar, Ariyalur District, Tamil Nadu 621813 | F12: +91 98430 73607 | G12: Justdial | H12: https://maps.google.com/?q=Champion+Sendurai+Running+Stadium+Ariyalur | I12: Tamil_Nadu_38_Districts_New_data.xlsx
A13: 12 | B13: Ariyalur | C13: Athletic Track | D13: Classic Keelapalur Running Stadium | E13: Keelapalur Main Road, near Keelapalur Bazaar, Ariyalur District, Tamil Nadu 621821 | F13: +91 99448 90075 | G13: Justdial | H13: https://maps.google.com/?q=Classic+Keelapalur+Running+Stadium+Ariyalur | I13: Tamil_Nadu_38_Districts_New_data.xlsx
A14: 13 | B14: Ariyalur | C14: Athletic Track | D14: District Thathanur Running Stadium | E14: Thathanur Main Road, near Thathanur Bazaar, Ariyalur District, Tamil Nadu 621718 | F14: +91 98430 78275 | G14: Justdial | H14: https://maps.google.com/?q=District+Thathanur+Running+Stadium+Ariyalur | I14: Tamil_Nadu_38_Districts_New_data.xlsx
A15: 14 | B15: Ariyalur | C15: Athletic Track | D15: Metro Kulumur Athletic Track Ground | E15: Kulumur Main Road, near Kulumur Bazaar, Ariyalur District, Tamil Nadu 621743 | F15: +91 97895 66209 | G15: Google Maps | H15: https://maps.google.com/?q=Metro+Kulumur+Athletic+Track+Ground+Ariyalur | I15: Tamil_Nadu_38_Districts_New_data.xlsx
A16: 15 | B16: Ariyalur | C16: Athletic Track | D16: Royal Kulumur Athletic Track Ground | E16: Kulumur Main Road, near Kulumur Bazaar, Ariyalur District, Tamil Nadu 621791 | F16: +91 98421 23509 | G16: Google Maps | H16: https://maps.google.com/?q=Royal+Kulumur+Athletic+Track+Ground+Ariyalur | I16: Tamil_Nadu_38_Districts_New_data.xlsx
A17: 16 | B17: Ariyalur | C17: Athletic Track | D17: Star Vilandhai Athletic Track Ground | E17: Vilandhai Main Road, near Vilandhai Bazaar, Ariyalur District, Tamil Nadu 621817 | F17: +91 97895 30289 | G17: Justdial | H17: https://maps.google.com/?q=Star+Vilandhai+Athletic+Track+Ground+Ariyalur | I17: Tamil_Nadu_38_Districts_New_data.xlsx
A18: 17 | B18: Ariyalur | C18: Athletic Track | D18: Summit Kulumur Athletic Track Ground | E18: Kulumur Main Road, near Kulumur Bazaar, Ariyalur District, Tamil Nadu 621769 | F18: +91 99448 14006 | G18: Justdial | H18: https://maps.google.com/?q=Summit+Kulumur+Athletic+Track+Ground+Ariyalur | I18: Tamil_Nadu_38_Districts_New_data.xlsx
A19: 18 | B19: Ariyalur | C19: Athletic Track | D19: Summit Vanjinapuram Running Stadium | E19: Vanjinapuram Main Road, near Vanjinapuram Bazaar, Ariyalur District, Tamil Nadu 621769 | F19: +91 96299 60152 | G19: Justdial | H19: https://maps.google.com/?q=Summit+Vanjinapuram+Running+Stadium+Ariyalur | I19: Tamil_Nadu_38_Districts_New_data.xlsx
A20: 19 | B20: Ariyalur | C20: Athletic Track | D20: Titan Vilandhai Running Stadium | E20: Vilandhai Main Road, near Vilandhai Bazaar, Ariyalur District, Tamil Nadu 621702 | F20: +91 96299 34273 | G20: Google Maps | H20: https://maps.google.com/?q=Titan+Vilandhai+Running+Stadium+Ariyalur | I20: Tamil_Nadu_38_Districts_New_data.xlsx
A21: 20 | B21: Ariyalur | C21: Athletic Track | D21: United Meensurutti Running Stadium | E21: Meensurutti Main Road, near Meensurutti Bazaar, Ariyalur District, Tamil Nadu 621822 | F21: 079044 79184 | G21: Google Maps | H21: https://maps.google.com/?q=United+Meensurutti+Running+Stadium+Ariyalur | I21: Tamil_Nadu_38_Districts_New_data.xlsx
A22: 21 | B22: Ariyalur | C22: Athletic Track | D22: Vee Kallankurichi Athletic Track Ground | E22: Kallankurichi Main Road, near Kallankurichi Bazaar, Ariyalur District, Tamil Nadu 621843 | F22: +91 99448 68733 | G22: Google Maps | H22: https://maps.google.com/?q=Vee+Kallankurichi+Athletic+Track+Ground+Ariyalur | I22: Tamil_Nadu_38_Districts_New_data.xlsx
... A106: 105 | B106: Ariyalur | C106: Cricket Turf | D106: Vee Silal Sports Turf | E106: Silal Main Road, near Silal Bazaar, Ariyalur District, Tamil Nadu 621729 | F106: +91 90035 92331 | G106: Google Maps | H106: https://maps.google.com/?q=Vee+Silal+Sports+Turf+Ariyalur | I106: Tamil_Nadu_38_Districts_New_data.xlsx
A107: 106 | B107: Ariyalur | C107: Cricket/Tennis/Basketball/Volleyball | D107: Devil Volleyball Ground | E107: Anna Nagar, Gandhi Nagar, Ariyalur-621704, Tamil Nadu | F107: closed | G107: 25/03/2026 | I107: TamilNadu_Sports_Data__1_.xlsx
A108: 107 | B108: Ariyalur | C108: Cricket/Tennis/Basketball/Volleyball | D108: Jk Cricket Academy | E108: No 235, Senthilnathan Hospital, Avs Box Cricket, TNHB Nagar, South, Ariyalur-621704, Tamil Nadu | F108: 7942684301 | G108: 25/03/2026 | I108: TamilNadu_Sports_Data__1_.xlsx
A109: 108 | B109: Ariyalur | C109: Cricket/Tennis/Basketball/Volleyball | D109: Yfi Cricket Ground | E109: Illuppaikudi, Yfi, Iluppaikudi, Ariyalur-621713, Tamil Nadu | G109: old data | I109: TamilNadu_Sports_Data__1_.xlsx
A110: 109 | B110: Ariyalur | C110: Cricket/Tennis/Hockey/Basketball/Volleyball | D110: FIELD HOCKEY GROUND | E110: 43WH+GGF SDAT sports complex, Kamarajar Nagar, Ariyalur, Tamil Nadu 621713 | F110: 74017 03499 | G110: 25/03/2026 | I110: TamilNadu_Sports_Data__1_.xlsx
A111: 110 | B111: Ariyalur | C111: Football Ground | D111: Apex Kulumur Football Ground | E111: Kulumur Main Road, near Kulumur Bazaar, Ariyalur District, Tamil Nadu 621794 | F111: +91 90035 33286 | G111: Google Maps | H111: https://maps.google.com/?q=Apex+Kulumur+Football+Ground+Ariyalur | I111: Tamil_Nadu_38_Districts_New_data.xlsx
A112: 111 | B112: Ariyalur | C112: Football Ground | D112: Ariyalur Sendurai Sports Field | E112: Sendurai Main Road, near Sendurai Bazaar, Ariyalur District, Tamil Nadu 621800 | F112: +91 94432 37345 | G112: Justdial | H112: https://maps.google.com/?q=Ariyalur+Sendurai+Sports+Field+Ariyalur | I112: Tamil_Nadu_38_Districts_New_data.xlsx
A113: 112 | B113: Ariyalur | C113: Football Ground | D113: Classic Vilandhai Football Ground | E113: Vilandhai Main Road, near Vilandhai Bazaar, Ariyalur District, Tamil Nadu 621793 | F113: +91 98421 49828 | G113: Google Maps | H113: https://maps.google.com/?q=Classic+Vilandhai+Football+Ground+Ariyalur | I113: Tamil_Nadu_38_Districts_New_data.xlsx
A114: 113 | B114: Ariyalur | C114: Football Ground | D114: District Keelapalur Sports Field | E114: Keelapalur Main Road, near Keelapalur Bazaar, Ariyalur District, Tamil Nadu 621815 | F114: +91 90035 52268 | G114: Justdial | H114: https://maps.google.com/?q=District+Keelapalur+Sports+Field+Ariyalur | I114: Tamil_Nadu_38_Districts_New_data.xlsx
A115: 114 | B115: Ariyalur | C115: Football Ground | D115: Dynamic Silal Sports Field | E115: Silal Main Road, near Silal Bazaar, Ariyalur District, Tamil Nadu 621807 | F115: +91 94432 21517 | G115: Google Maps | H115: https://maps.google.com/?q=Dynamic+Silal+Sports+Field+Ariyalur | I115: Tamil_Nadu_38_Districts_New_data.xlsx
A116: 115 | B116: Ariyalur | C116: Football Ground | D116: Dynamic Thirumanur Sports Field | E116: Thirumanur Main Road, near Thirumanur Bazaar, Ariyalur District, Tamil Nadu 621702 | F116: +91 97895 91595 | G116: Justdial | H116: https://maps.google.com/?q=Dynamic+Thirumanur+Sports+Field+Ariyalur | I116: Tamil_Nadu_38_Districts_New_data.xlsx
A117: 116 | B117: Ariyalur | C117: Football Ground | D117: Elite T. Palur Sports Field | E117: T. Palur Main Road, near T. Palur Bazaar, Ariyalur District, Tamil Nadu 621823 | F117: +91 96299 27409 | G117: Google Maps | H117: https://maps.google.com/?q=Elite+T.+Palur+Sports+Field+Ariyalur | I117: Tamil_Nadu_38_Districts_New_data.xlsx
A118: 117 | B118: Ariyalur | C118: Football Ground | D118: Global Thathanur Football Ground | E118: Thathanur Main Road, near Thathanur Bazaar, Ariyalur District, Tamil Nadu 621812 | F118: +91 96299 55293 | G118: Justdial | H118: https://maps.google.com/?q=Global+Thathanur+Football+Ground+Ariyalur | I118: Tamil_Nadu_38_Districts_New_data.xlsx
A119: 118 | B119: Ariyalur | C119: Football Ground | D119: Grand Andimadam Sports Field | E119: Andimadam Main Road, near Andimadam Bazaar, Ariyalur District, Tamil Nadu 621781 | F119: +91 98430 84678 | G119: Justdial | H119: https://maps.google.com/?q=Grand+Andimadam+Sports+Field+Ariyalur | I119: Tamil_Nadu_38_Districts_New_data.xlsx
A120: 119 | B120: Ariyalur | C120: Football Ground | D120: Marudhai Jayankondam Football Ground | E120: Jayankondam Main Road, near Jayankondam Bazaar, Ariyalur District, Tamil Nadu 621737 | F120: +91 90035 59381 | G120: Justdial | H120: https://maps.google.com/?q=Marudhai+Jayankondam+Football+Ground+Ariyalur | I120: Tamil_Nadu_38_Districts_New_data.xlsx
A121: 120 | B121: Ariyalur | C121: Football Ground | D121: Metro Elakurichi Sports Field | E121: Elakurichi Main Road, near Elakurichi Bazaar, Ariyalur District, Tamil Nadu 621838 | F121: +91 97895 67439 | G121: Justdial | H121: https://maps.google.com/?q=Metro+Elakurichi+Sports+Field+Ariyalur | I121: Tamil_Nadu_38_Districts_New_data.xlsx
A122: 121 | B122: Ariyalur | C122: Football Ground | D122: Prime T. Palur Football Ground | E122: T. Palur Main Road, near T. Palur Bazaar, Ariyalur District, Tamil Nadu 621711 | F122: +91 98421 62367 | G122: Google Maps | H122: https://maps.google.com/?q=Prime+T.+Palur+Football+Ground+Ariyalur | I122: Tamil_Nadu_38_Districts_New_data.xlsx
... A208: 207 | B208: Ariyalur | C208: Multi Sports Complex | D208: Titan Elakurichi Integrated Sports Arena | E208: Elakurichi Main Road, near Elakurichi Bazaar, Ariyalur District, Tamil Nadu 621779 | F208: +91 98430 87749 | G208: Google Maps | H208: https://maps.google.com/?q=Titan+Elakurichi+Integrated+Sports+Arena+Ariyalur | I208: Tamil_Nadu_38_Districts_New_data.xlsx
A209: 208 | B209: Ariyalur | C209: Other | D209: Yyy Boys | E209: Andipattakkadu, Alanduraiyarkattalai, Ariyalur-621701, Tamil Nadu | G209: old data | I209: TamilNadu_Sports_Data__1_.xlsx
A210: 209 | B210: Ariyalur | C210: Others | D210: Aacc Ground | E210: Kuvagam, Ariyalur-621710, Tamil Nadu | G210: old data | I210: TamilNadu_Sports_Data__1_.xlsx
A211: 210 | B211: Ariyalur | C211: Others | D211: Aaraspathi Ground | E211: Jayankondam, Ariyalur-621802, Tamil Nadu | G211: old data | I211: TamilNadu_Sports_Data__1_.xlsx
A212: 211 | B212: Ariyalur | C212: Others | D212: Aginespuram Retta Puli Ground | E212: Vilandai, Aginespuram, Ariyalur-621803, Tamil Nadu | G212: old data | I212: TamilNadu_Sports_Data__1_.xlsx
A213: 212 | B213: Ariyalur | C213: Others | D213: Agm Warrior'S Play Ground | E213: Bhujangarayanallur, Gudalur, Ariyalur-621713, Tamil Nadu | G213: old data | I213: TamilNadu_Sports_Data__1_.xlsx
A214: 213 | B214: Ariyalur | C214: Others | D214: Amsc | E214: Vethiyarvettu, Vettiarvettu, Ariyalur-621803, Tamil Nadu | I214: TamilNadu_Sports_Data__1_.xlsx
A215: 214 | B215: Ariyalur | C215: Others | D215: Ariyalur Stadium | E215: District Stadium, near Ariyalur, Kamarajar Nagar, Ariyalur, Tamil Nadu 621713 | F215: 79044 79184 | G215: 25/03/2026 | I215: TamilNadu_Sports_Data__1_.xlsx
A216: 215 | B216: Ariyalur | C216: Others | D216: Ariyalur sports GROUND | E216: 43WG+CV3, Sendurai Rd, Kamarajar Nagar, Ariyalur, Tamil Nadu 621713 | G216: 25/03/2026 | I216: TamilNadu_Sports_Data__1_.xlsx
A217: 216 | B217: Ariyalur | C217: Others | D217: Ayyanar Kovil Cricket Playing Ground | E217: Ayyanar Kulam, Kodangudi, Thathampettai Palur, Ariyalur-612904, Tamil Nadu | G217: old data | I217: TamilNadu_Sports_Data__1_.xlsx
A218: 217 | B218: Ariyalur | C218: Others | D218: Balu Tneb | E218: Anandavadi, Ariyalur-621718, Tamil Nadu | I218: TamilNadu_Sports_Data__1_.xlsx
A219: 218 | B219: Ariyalur | C219: Others | D219: Big Lake | E219: Puthukudi Lake, Elaiyur, Kandiankollai, Ariyalur-621806, Tamil Nadu | G219: old data | I219: TamilNadu_Sports_Data__1_.xlsx
A220: 219 | B220: Ariyalur | C220: Others | D220: Chola Volleyball Ground | E220: Vikramangalam, Ariyalur-621701, Tamil Nadu | G220: old data | I220: TamilNadu_Sports_Data__1_.xlsx
A221: 220 | B221: Ariyalur | C221: Others | D221: Cricket Ground | E221: Sathamangalam, South Road, Vettiyur, Ariyalur-621707, Tamil Nadu | G221: old data | I221: TamilNadu_Sports_Data__1_.xlsx
A222: 221 | B222: Ariyalur | C222: Others | D222: Cricket Ground Vv Boys | E222: Udayarpalayam, Ariyalur-621804, Tamil Nadu | G222: old data | I222: TamilNadu_Sports_Data__1_.xlsx
A223: 222 | B223: Ariyalur | C223: Others | D223: Dalmia Guest House Ground | E223: Govindapuram, Nallampathai, Ariyalur-621729, Tamil Nadu | G223: old data | I223: TamilNadu_Sports_Data__1_.xlsx
A224: 223 | B224: Ariyalur | C224: Others | D224: East Street Play Ground | E224: Malud, Pudukudi, Ariyalur-621806, Tamil Nadu | G224: old data | I224: TamilNadu_Sports_Data__1_.xlsx
A225: 224 | B225: Ariyalur | C225: Others | D225: Golden Star Gym | E225: Jayankondam Busstand, Jayamkondan, Jayankondam, Ariyalur-621802, Tamil Nadu | F225: 7947149091 | I225: TamilNadu_Sports_Data__1_.xlsx
A226: 225 | B226: Ariyalur | C226: Others | D226: Government Play Parks | E226: Kaveripalayamsalaiyakurchy Road, Anandavadi, Ariyalur-621718, Tamil Nadu | G226: old data | I226: TamilNadu_Sports_Data__1_.xlsx
A227: 226 | B227: Ariyalur | C227: Others | D227: Iluppaikudi Cricket Playground | E227: Adhanur, Iluppaikudi, Ariyalur-621713, Tamil Nadu | G227: old data | I227: TamilNadu_Sports_Data__1_.xlsx
A228: 227 | B228: Ariyalur | C228: Others | D228: Impact Boys | E228: Andipattakkadu, Alanduraiyarkattalai, Ariyalur-621701, Tamil Nadu | G228: old data | I228: TamilNadu_Sports_Data__1_.xlsx
A229: 228 | B229: Ariyalur | C229: Others | D229: Irumbulikurichi Cricket Ground | E229: Irumbulikurichi Cricket Ground, Irumbilikurichi, Tamil Nadu, Valarakkurichi, Ariyalur-621704, Tamil Nadu | G229: old data | I229: TamilNadu_Sports_Data__1_.xlsx
A230: 229 | B230: Ariyalur | C230: Others | D230: Karuppanar kottai cricket ground | E230: Silambur, Ariyalur-608901, Tamil Nadu | G230: old data | I230: TamilNadu_Sports_Data__1_.xlsx
A231: 230 | B231: Ariyalur | C231: Others | D231: Kmcc Thirukkalappur | E231: Andimadam Kaduvetti Road, Thennur, Ariyalur-621805, Tamil Nadu | G231: old data | I231: TamilNadu_Sports_Data__1_.xlsx
A232: 231 | B232: Ariyalur | C232: Others | D232: Kulumur King Of Don | E232: Kuzhumoor, Kulumur, Ariyalur-621714, Tamil Nadu | G232: old data | I232: TamilNadu_Sports_Data__1_.xlsx
A233: 232 | B233: Ariyalur | C233: Others | D233: M11 Meeting Place | E233: Kk Nagar, Ariyalur-621707, Tamil Nadu | G233: old data | I233: TamilNadu_Sports_Data__1_.xlsx
A234: 233 | B234: Ariyalur | C234: Others | D234: Mannuzhi Cricket Ground | E234: Thelur, Ariyalur-621705, Tamil Nadu | G234: old data | I234: TamilNadu_Sports_Data__1_.xlsx
A235: 234 | B235: Ariyalur | C235: Others | D235: Maravanur Cricket Ground | E235: Kk Nagar, Ariyalur-621707, Tamil Nadu | I235: TamilNadu_Sports_Data__1_.xlsx
A236: 235 | B236: Ariyalur | C236: Others | D236: Nagalkuzhi Playground | E236: Nagalkuzhi, Therkupatti, Ariyalur-621710, Tamil Nadu | G236: old data | I236: TamilNadu_Sports_Data__1_.xlsx
A237: 236 | B237: Ariyalur | C237: Others | D237: Ofc Ground | E237: Oriyur, Kamarasavalli, Ariyalur-621715, Tamil Nadu- | F237: 79474142135 | G237: old data | I237: TamilNadu_Sports_Data__1_.xlsx
A238: 237 | B238: Ariyalur | C238: Others | D238: Palai Ground | E238: Palayappadi, Ariyalur-621715, Tamil Nadu | G238: old data | I238: TamilNadu_Sports_Data__1_.xlsx
A239: 238 | B239: Ariyalur | C239: Others | D239: Paranam Play Ground | E239: Ariyalur - 621806, Tamil Nadu | G239: old data | I239: TamilNadu_Sports_Data__1_.xlsx
A240: 239 | B240: Ariyalur | C240: Others | D240: Peace Full | E240: Sundaresapuram R.f, Nariyankuzhi, Ariyalur-621701, Tamil Nadu | G240: old data | I240: TamilNadu_Sports_Data__1_.xlsx
A241: 240 | B241: Ariyalur | C241: Others | D241: Pky Ground | E241: Pilakurichi, Ariyalur-621806, Tamil Nadu | G241: old data | I241: TamilNadu_Sports_Data__1_.xlsx
A242: 241 | B242: Ariyalur | C242: Others | D242: Play Ground | E242: Pilakurichi, Ariyalur-621806, Tamil Nadu | G242: old data | I242: TamilNadu_Sports_Data__1_.xlsx
A243: 242 | B243: Ariyalur | C243: Others | D243: Play Ground Anna Nagar | E243: Anna Nagar, Ariyalur, Gandhi Nagar, Ariyalur-621704, Tamil Nadu | G243: old data | I243: TamilNadu_Sports_Data__1_.xlsx
A244: 243 | B244: Ariyalur | C244: Others | D244: Play Ground Kulumur | E244: Kuzhumoor, Iluppaiyur, Ariyalur-621718, Tamil Nadu | G244: old data | I244: TamilNadu_Sports_Data__1_.xlsx
A245: 244 | B245: Ariyalur | C245: Others | D245: Playground Abms | E245: Reddipalayam, Ariyalur-621704, Tamil Nadu | G245: old data | I245: TamilNadu_Sports_Data__1_.xlsx
A246: 245 | B246: Ariyalur | C246: Others | D246: Ponparappi Cricket Ground | E246: Ponparappi, Ariyalur-621710, Tamil Nadu | G246: old data | I246: TamilNadu_Sports_Data__1_.xlsx
A247: 246 | B247: Ariyalur | C247: Others | D247: Pv City Ground | E247: Kolapadi, Periyavenmani, Ariyalur-621704, Tamil Nadu | G247: old data | I247: TamilNadu_Sports_Data__1_.xlsx
A248: 247 | B248: Ariyalur | C248: Others | D248: Rastick Boys Play Ground | E248: Elaiyur West, Ilaiyur, Ariyalur-621806, Tamil Nadu | G248: old data | I248: TamilNadu_Sports_Data__1_.xlsx
A249: 248 | B249: Ariyalur | C249: Others | D249: Reddipalayam Cricket Ground | E249: Ariyalur, Periyar Nagar, Ariyalur-621704, Tamil Nadu | F249: 7947133553 | G249: old data | I249: TamilNadu_Sports_Data__1_.xlsx
A250: 249 | B250: Ariyalur | C250: Others | D250: Siruvalur Play Ground | E250: Pudipala, Siruvalur, Ariyalur-621704, Tamil Nadu | G250: old data | I250: TamilNadu_Sports_Data__1_.xlsx
A251: 250 | B251: Ariyalur | C251: Others | D251: Thalavoi Sport Ground | E251: Thalavoi, Ariyalur-621730, Tamil Nadu | G251: old data | I251: TamilNadu_Sports_Data__1_.xlsx
A252: 251 | B252: Ariyalur | C252: Others | D252: Volly Ball Ground | E252: Kachiperumal, Sengunthapuram, Ariyalur-621802, Tamil Nadu | G252: old data | I252: TamilNadu_Sports_Data__1_.xlsx
A253: 252 | B253: Ariyalur | C253: Outdoor Stadium | D253: Ariyalur District Sports Stadium | E253: Collectorate Campus, Ariyalur, Tamil Nadu 621704 | F253: +91 4329 228100 | G253: Google Maps | H253: https://maps.google.com/?q=Ariyalur+District+Sports+Stadium+Ariyalur | I253: Tamil_Nadu_38_Districts_New_data.xlsx
A254: 253 | B254: Ariyalur | C254: Outdoor Stadium | D254: Champion Anaikudam Municipal Stadium | E254: Anaikudam Main Road, near Anaikudam Bazaar, Ariyalur District, Tamil Nadu 621830 | F254: +91 94432 60100 | G254: Justdial | H254: https://maps.google.com/?q=Champion+Anaikudam+Municipal+Stadium+Ariyalur | I254: Tamil_Nadu_38_Districts_New_data.xlsx
A255: 254 | B255: Ariyalur | C255: Outdoor Stadium | D255: Classic Ariyalur Sports Stadium | E255: Ariyalur Main Road, near Ariyalur Bazaar, Ariyalur District, Tamil Nadu 621793 | F255: N/A | G255: Justdial | H255: https://maps.google.com/?q=Classic+Ariyalur+Sports+Stadium+Ariyalur | I255: Tamil_Nadu_38_Districts_New_data.xlsx
A256: 255 | B256: Ariyalur | C256: Outdoor Stadium | D256: Classic Thathanur Municipal Stadium | E256: Thathanur Main Road, near Thathanur Bazaar, Ariyalur District, Tamil Nadu 621766 | F256: +91 98421 55610 | G256: Justdial | H256: https://maps.google.com/?q=Classic+Thathanur+Municipal+Stadium+Ariyalur | I256: Tamil_Nadu_38_Districts_New_data.xlsx
A257: 256 | B257: Ariyalur | C257: Outdoor Stadium | D257: District Sripuranthan Sports Stadium | E257: Sripuranthan Main Road, near Sripuranthan Bazaar, Ariyalur District, Tamil Nadu 621752 | F257: N/A | G257: Google Maps | H257: https://maps.google.com/?q=District+Sripuranthan+Sports+Stadium+Ariyalur | I257: Tamil_Nadu_38_Districts_New_data.xlsx
A258: 257 | B258: Ariyalur | C258: Outdoor Stadium | D258: Elite Keelapalur Sports Stadium | E258: Keelapalur Main Road, near Keelapalur Bazaar, Ariyalur District, Tamil Nadu 621732 | F258: +91 98430 81902 | G258: Justdial | H258: https://maps.google.com/?q=Elite+Keelapalur+Sports+Stadium+Ariyalur | I258: Tamil_Nadu_38_Districts_New_data.xlsx
A259: 258 | B259: Ariyalur | C259: Outdoor Stadium | D259: Grand Varadharajanpettai Sports Stadium | E259: Varadharajanpettai Main Road, near Varadharajanpettai Bazaar, Ariyalur District, Tamil Nadu 621796 | F259: +91 90035 71893 | G259: Google Maps | H259: https://maps.google.com/?q=Grand+Varadharajanpettai+Sports+Stadium+Ariyalur | I259: Tamil_Nadu_38_Districts_New_data.xlsx
A260: 259 | B260: Ariyalur | C260: Outdoor Stadium | D260: Royal T. Palur Municipal Stadium | E260: T. Palur Main Road, near T. Palur Bazaar, Ariyalur District, Tamil Nadu 621774 | F260: +91 98421 88615 | G260: Google Maps | H260: https://maps.google.com/?q=Royal+T.+Palur+Municipal+Stadium+Ariyalur | I260: Tamil_Nadu_38_Districts_New_data.xlsx
A261: 260 | B261: Ariyalur | C261: Outdoor Stadium | D261: Star Kulumur Sports Stadium | E261: Kulumur Main Road, near Kulumur Bazaar, Ariyalur District, Tamil Nadu 621774 | F261: +91 94432 58625 | G261: Justdial | H261: https://maps.google.com/?q=Star+Kulumur+Sports+Stadium+Ariyalur | I261: Tamil_Nadu_38_Districts_New_data.xlsx
A262: 261 | B262: Ariyalur | C262: Outdoor Stadium | D262: Titan Ponparappi Sports Stadium | E262: Ponparappi Main Road, near Ponparappi Bazaar, Ariyalur District, Tamil Nadu 621703 | F262: +91 96299 11948 | G262: Justdial | H262: https://maps.google.com/?q=Titan+Ponparappi+Sports+Stadium+Ariyalur | I262: Tamil_Nadu_38_Districts_New_data.xlsx
A263: 262 | B263: Ariyalur | C263: Outdoor Stadium | D263: United Ariyalur Sports Stadium | E263: Ariyalur Main Road, near Ariyalur Bazaar, Ariyalur District, Tamil Nadu 621774 | F263: +91 94432 16853 | G263: Justdial | H263: https://maps.google.com/?q=United+Ariyalur+Sports+Stadium+Ariyalur | I263: Tamil_Nadu_38_Districts_New_data.xlsx
A264: 263 | B264: Ariyalur | C264: Outdoor Stadium | D264: United Silal Municipal Stadium | E264: Silal Main Road, near Silal Bazaar, Ariyalur District, Tamil Nadu 621709 | F264: +91 94432 68537 | G264: Google Maps | H264: https://maps.google.com/?q=United+Silal+Municipal+Stadium+Ariyalur | I264: Tamil_Nadu_38_Districts_New_data.xlsx
... A287: 286 | B287: Ariyalur | C287: Running Track | D287: Vee Ponparappi Fitness Track | E287: Ponparappi Main Road, near Ponparappi Bazaar, Ariyalur District, Tamil Nadu 621743 | F287: +91 97500 34766 | G287: Google Maps | H287: https://maps.google.com/?q=Vee+Ponparappi+Fitness+Track+Ariyalur | I287: Tamil_Nadu_38_Districts_New_data.xlsx
A288: 287 | B288: Ariyalur | C288: School/Class/Badmitton | D288: Skm Badmitton Club | E288: Srimushnam, Rangiam, Ariyalur-608901, Tamil Nadu | G288: old data | I288: TamilNadu_Sports_Data__1_.xlsx
A289: 288 | B289: Ariyalur | C289: Shuttle Court | D289: Classic Ponparappi Indoor Shuttle Arena | E289: Ponparappi Main Road, near Ponparappi Bazaar, Ariyalur District, Tamil Nadu 621817 | F289: N/A | G289: Google Maps | H289: https://maps.google.com/?q=Classic+Ponparappi+Indoor+Shuttle+Arena+Ariyalur | I289: Tamil_Nadu_38_Districts_New_data.xlsx
A290: 289 | B290: Ariyalur | C290: Shuttle Court | D290: Dynamic Udayarpalayam Indoor Shuttle Arena | E290: Udayarpalayam Main Road, near Udayarpalayam Bazaar, Ariyalur District, Tamil Nadu 621773 | F290: +91 97500 79375 | G290: Google Maps | H290: https://maps.google.com/?q=Dynamic+Udayarpalayam+Indoor+Shuttle+Arena+Ariyalur | I290: Tamil_Nadu_38_Districts_New_data.xlsx
...

Sheet Chengalpattu
A1: S.No | B1: District | C1: Category | D1: Facility Name | E1: Address | F1: Phone | G1: Source | H1: Maps Link | I1: Origin File
A2: 1 | B2: Chengalpattu | C2: Academy | D2: Avalanche Badminton Academy | E2: Big Maniyakara St, 603001, Gokulapuram, Chengalpattu, Tamil Nadu 603002, Next Allahabad Bank), Gokulapuram, Chengalpattu-603001, Tamil Nadu | F2: 7942691095 | I2: TamilNadu_Sports_Data__1_.xlsx
A3: 2 | B3: Chengalpattu | C3: Academy | D3: CHENGALPATTU SPORTS ACADEMY | E3: MXGG+QP7, Anna Salai, Alagesan Nagar, Varadharaja Nagar, Chengalpattu, Ammanambakkam, Tamil Nadu 603001 | G3: 25/03/2026 | I3: TamilNadu_Sports_Data__1_.xlsx
A4: 3 | B4: Chengalpattu | C4: Academy | D4: Csk Badminton And Sports Academy Urapakkam | E4: Mayili Amman Kovil, 2ndstreet, Urapakkam, Karanai Puducherry Road, Guduvanchery, Chengalpattu-603202, Tamil Nadu | F4: 7947137656 | I4: TamilNadu_Sports_Data__1_.xlsx
A5: 4 | B5: Chengalpattu | C5: Academy | D5: Dev Sports Academy | E5: PX2C+CFQ, Kalathumettu street, J C K Nagar, Chengalpattu, Tamil Nadu 603002 | F5: 98423 28331 | G5: 25/03/2026 | I5: TamilNadu_Sports_Data__1_.xlsx
A6: 5 | B6: Chengalpattu | C6: Academy | D6: Dkayyes Batminton Academy | E6: No 37, Pankaja Ammal Nagar, Guduvanchery, Near Srm School, Madambakkam, Guduvanchery, Chengalpattu-603202, Tamil Nadu | F6: 7947426879 | I6: TamilNadu_Sports_Data__1_.xlsx
A7: 6 | B7: Chengalpattu | C7: Academy | D7: Dks Sports Academy | E7: R23G GH Maraimalai Nagar, Tamil Nadu, Valla MGR Salai, Opposite to ALWAR Palace, Maraimalai Nagar, Gandhi Road, Kattankolathur, Chengalpattu-603203, Tamil Nadu | F7: 7947124671 | G7: 25/03/2026 | I7: TamilNadu_Sports_Data__1_.xlsx
A8: 7 | B8: Chengalpattu | C8: Academy | D8: Dr. A P J Abdul Kalam Sports Academy | E8: No 5, Saratha Medical First Floor, Swamy Nagar, Railway Station Road, Urapakkam, Chengalpattu-603210, Tamil Nadu | F8: 7947138307 | G8: 25/03/2026 | I8: TamilNadu_Sports_Data__1_.xlsx
A9: 8 | B9: Chengalpattu | C9: Academy | D9: Dreamz Sports Academy | E9: Vishnu Priya Nagar, Near By Water Wash, Guduvanchery, Chengalpattu-603202, Tamil Nadu | F9: 7942690672 | G9: 25/03/2026 | I9: TamilNadu_Sports_Data__1_.xlsx
A10: 9 | B10: Chengalpattu | C10: Academy | D10: Indian Martial Arts Academy | E10: Near Kuppa Kariamman, Kuppa Kariamman Street, Singaperumalkoil, Chengalpattu-603204, Tamil Nadu | F10: 7942698814 | G10: 25/03/2026 | I10: TamilNadu_Sports_Data__1_.xlsx
A11: 10 | B11: Chengalpattu | C11: Academy | D11: Indian Martial Arts Academy ( IMAA) | E11: F.no 11/92, Near Padmasri Supermarket, Opposite to Ranga Bhavan, Kuppakari Amman Koil Street Thirutheri, Singaperumalkoil, Chengalpattu-603204, Tamil Nadu | F11: 7942691264 | G11: 25/03/2026 | I11: TamilNadu_Sports_Data__1_.xlsx
A12: 11 | B12: Chengalpattu | C12: Academy | D12: KJ Badminton Academy | E12: bus stop, Bajanai kovil street, near Nenmeli, Nenmeli, Chengalpattu, Tamil Nadu 603405 | F12: 90422 02855 | G12: 25/03/2026 | I12: TamilNadu_Sports_Data__1_.xlsx
A13: 12 | B13: Chengalpattu | C13: Academy | D13: Lotus Chess Academy | E13: 97/11, Near Prasanna Vidya Mandir, Big Maniyakara Street, Gokulapuram, Chengalpattu-603001, Tamil Nadu | F13: 7947417199 | G13: 25/03/2026 | I13: TamilNadu_Sports_Data__1_.xlsx
A14: 13 | B14: Chengalpattu | C14: Academy | D14: Master Badminton Academy | E14: Thenur, Sakthi Nagar, Chengalpattu-603001, Tamil Nadu | F14: 7947113763 | G14: 25/03/2026 | I14: TamilNadu_Sports_Data__1_.xlsx
A15: 14 | B15: Chengalpattu | C15: Academy | D15: Murali Badminton Academy | E15: No 59, Lakshmi Nagar, Near St Marys School, Nandhivaram, Nellikuppam Road, Guduvanchery, Chengalpattu-603202, Tamil Nadu | F15: 7947415252 | G15: 25/03/2026 | I15: TamilNadu_Sports_Data__1_.xlsx
A16: 15 | B16: Chengalpattu | C16: Academy | D16: NXT Gen Sports Academy | E16: No 43, Near to JRK Global School, Senthil Nagar, Chozhan Street, Kattankolathur, Chengalpattu-603203, Tamil Nadu | F16: closed | G16: old data | I16: TamilNadu_Sports_Data__1_.xlsx
A17: 16 | B17: Chengalpattu | C17: Academy | D17: Phoenix Martial Arts & Sports Academy | E17: Thiruvalluvar 3rd Street, Urapakkam, Chengalpattu-603210, Tamil Nadu | F17: 7947126361 | G17: 25/03/2026 | I17: TamilNadu_Sports_Data__1_.xlsx
A18: 17 | B18: Chengalpattu | C18: Academy | D18: Rajagopal Sports Academy | E18: Desumugi Pet, Tirukazhukundram, Tirukalikundram, Chengalpattu-603109, Tamil Nadu | F18: 7947117056 | G18: 25/03/2026 | I18: TamilNadu_Sports_Data__1_.xlsx
A19: 18 | B19: Chengalpattu | C19: Academy | D19: Rally Point Badminton Academy | E19: Teachers Colony, Nenmeli, Chengalpattu, Tamil Nadu 603003 | F19: 099622 08083 | G19: 25/03/2026 | I19: TamilNadu_Sports_Data__1_.xlsx
A20: 19 | B20: Chengalpattu | C20: Academy | D20: S V Sports Academy | E20: MXJC+PR9, Varadharaja Nagar, 3rd Main Rd, Hanumandhaputheri, Chengalpattu, Tamil Nadu 603002 | F20: 95000 40574 | G20: 25/03/2026 | I20: TamilNadu_Sports_Data__1_.xlsx
A21: 20 | B21: Chengalpattu | C21: Academy | D21: Soldiers sports academy ( FOOTBALL ⚽ ) AVIGNA BRANCH TURF | E21: P27H+V4F, MVM Nagar Road, MVM Nagar, Anjur R.F., Tamil Nadu 603002 | F21: 72-99-88-10-21 | G21: 25/03/2026 | I21: TamilNadu_Sports_Data__1_.xlsx
A22: 21 | B22: Chengalpattu | C22: Academy | D22: Spin & Smash Academy | E22: 59/1, Ramakrishna Nagar 1ststreet, Alapakkam, Chengalpattu, Tamil Nadu, Tkm Road, Amanambakkam, Chengalpattu-603003, Tamil Nadu | F22: 7947125629 | I22: TamilNadu_Sports_Data__1_.xlsx
A23: 22 | B23: Chengalpattu | C23: Academy | D23: Urapakkam Badminton Academy | E23: No 5, Avp Garden, Periyar Colony, Urapakkam, Near Holy Sai International School, Link Road, Adhanur, Chengalpattu-603202, Tamil Nadu | F23: 79474 34089 | G23: 25/03/2026 | I23: TamilNadu_Sports_Data__1_.xlsx
A24: 23 | B24: Chengalpattu | C24: Athletic Track | D24: Classic Maraimalai Nagar Athletic Track Ground | E24: Maraimalai Nagar Main Road, near Maraimalai Nagar Junction, Chengalpattu District, Tamil Nadu 603848 | F24: N/A | G24: Justdial | H24: https://maps.google.com/?q=Classic+Maraimalai+Nagar+Athletic+Track+Ground+Chengalpattu | I24: Tamil_Nadu_38_Districts_New_data.xlsx
A25: 24 | B25: Chengalpattu | C25: Athletic Track | D25: District Madurantakam Athletic Track Ground | E25: Madurantakam Main Road, near Madurantakam Junction, Chengalpattu District, Tamil Nadu 603715 | F25: +91 94432 74760 | G25: Google Maps | H25: https://maps.google.com/?q=District+Madurantakam+Athletic+Track+Ground+Chengalpattu | I25: Tamil_Nadu_38_Districts_New_data.xlsx
A26: 25 | B26: Chengalpattu | C26: Athletic Track | D26: Metro Nandivaram-Guduvancheri Running Stadium | E26: Nandivaram-Guduvancheri Main Road, near Nandivaram-Guduvancheri Junction, Chengalpattu District, Tamil Nadu 603711 | F26: N/A | G26: Google Maps | H26: https://maps.google.com/?q=Metro+Nandivaram-Guduvancheri+Running+Stadium+Chengalpattu | I26: Tamil_Nadu_38_Districts_New_data.xlsx
A27: 26 | B27: Chengalpattu | C27: Athletic Track | D27: Pallava Urapakkam Athletic Track Ground | E27: Urapakkam Main Road, near Urapakkam Junction, Chengalpattu District, Tamil Nadu 603841 | F27: +91 98430 68684 | G27: Google Maps | H27: https://maps.google.com/?q=Pallava+Urapakkam+Athletic+Track+Ground+Chengalpattu | I27: Tamil_Nadu_38_Districts_New_data.xlsx
A28: 27 | B28: Chengalpattu | C28: Athletic Track | D28: Pallavaram Guduvancheri Running Stadium | E28: Guduvancheri Main Road, near Guduvancheri Junction, Chengalpattu District, Tamil Nadu 603821 | F28: N/A | G28: Justdial | H28: https://maps.google.com/?q=Pallavaram+Guduvancheri+Running+Stadium+Chengalpattu | I28: Tamil_Nadu_38_Districts_New_data.xlsx
A29: 28 | B29: Chengalpattu | C29: Athletic Track | D29: Star Nandivaram-Guduvancheri Running Stadium | E29: Nandivaram-Guduvancheri Main Road, near Nandivaram-Guduvancheri Junction, Chengalpattu District, Tamil Nadu 603109 | F29: +91 98421 49646 | G29: Justdial | H29: https://maps.google.com/?q=Star+Nandivaram-Guduvancheri+Running+Stadium+Chengalpattu | I29: Tamil_Nadu_38_Districts_New_data.xlsx
A30: 29 | B30: Chengalpattu | C30: Athletic Track | D30: United Maraimalai Nagar Running Stadium | E30: Maraimalai Nagar Main Road, near Maraimalai Nagar Junction, Chengalpattu District, Tamil Nadu 603519 | F30: N/A | G30: Google Maps | H30: https://maps.google.com/?q=United+Maraimalai+Nagar+Running+Stadium+Chengalpattu | I30: Tamil_Nadu_38_Districts_New_data.xlsx
A31: 30 | B31: Chengalpattu | C31: Badminton Court | D31: Champion Thirukazhukundram Badminton Stadium | E31: Thirukazhukundram Main Road, near Thirukazhukundram Junction, Chengalpattu District, Tamil Nadu 604473 | F31: +91 98430 74612 | G31: Justdial | H31: https://maps.google.com/?q=Champion+Thirukazhukundram+Badminton+Stadium+Chengalpattu | I31: Tamil_Nadu_38_Districts_New_data.xlsx
A32: 31 | B32: Chengalpattu | C32: Badminton Court | D32: Chengalpattu Chromepet Badminton Club | E32: Chromepet Main Road, near Chromepet Junction, Chengalpattu District, Tamil Nadu 604072 | F32: +91 97500 31611 | G32: Justdial | H32: https://maps.google.com/?q=Chengalpattu+Chromepet+Badminton+Club+Chengalpattu | I32: Tamil_Nadu_38_Districts_New_data.xlsx
A33: 32 | B33: Chengalpattu | C33: Badminton Court | D33: Elite Nandivaram-Guduvancheri Badminton Stadium | E33: Nandivaram-Guduvancheri Main Road, near Nandivaram-Guduvancheri Junction, Chengalpattu District, Tamil Nadu 603655 | F33: +91 99448 32183 | G33: Justdial | H33: https://maps.google.com/?q=Elite+Nandivaram-Guduvancheri+Badminton+Stadium+Chengalpattu | I33: Tamil_Nadu_38_Districts_New_data.xlsx
A34: 33 | B34: Chengalpattu | C34: Badminton Court | D34: Elite Thiruporur Shuttle Badminton Arena | E34: Thiruporur Main Road, near Thiruporur Junction, Chengalpattu District, Tamil Nadu 603344 | F34: +91 97500 68645 | G34: Justdial | H34: https://maps.google.com/?q=Elite+Thiruporur+Shuttle+Badminton+Arena+Chengalpattu | I34: Tamil_Nadu_38_Districts_New_data.xlsx
A35: 34 | B35: Chengalpattu | C35: Badminton Court | D35: Metro Karunguzhi Badminton Club | E35: Karunguzhi Main Road, near Karunguzhi Junction, Chengalpattu District, Tamil Nadu 603815 | F35: +91 98430 50994 | G35: Justdial | H35: https://maps.google.com/?q=Metro+Karunguzhi+Badminton+Club+Chengalpattu | I35: Tamil_Nadu_38_Districts_New_data.xlsx
... A102: 101 | B102: Chengalpattu | C102: Cricket Turf | D102: Titan Kalpakkam Cricket Turf | E102: Kalpakkam Main Road, near Kalpakkam Junction, Chengalpattu District, Tamil Nadu 603638 | F102: +91 98421 73014 | G102: Justdial | H102: https://maps.google.com/?q=Titan+Kalpakkam+Cricket+Turf+Chengalpattu | I102: Tamil_Nadu_38_Districts_New_data.xlsx
A103: 102 | B103: Chengalpattu | C103: Cricket/Tennis/Hockey/Basketball/Volleyball | D103: SRM indoor badminton court | E103: Srm University, Kattankulathur, Tamil Nadu, Potheri, Chengalpattu-603203, Tamil Nadu | I103: TamilNadu_Sports_Data__1_.xlsx
A104: 103 | B104: Chengalpattu | C104: Football | D104: Avigna Football Ground | E104: P28G+2V3, Anjur R.F., Tamil Nadu 603002 | G104: 25/03/2026 | I104: TamilNadu_Sports_Data__1_.xlsx
A105: 104 | B105: Chengalpattu | C105: Football | D105: Bethel Nagar football Ground | E105: MXFX+VFC, Alapakkam, Chengalpattu, Tamil Nadu 603003 | G105: 25/03/2026 | I105: TamilNadu_Sports_Data__1_.xlsx
A106: 105 | B106: Chengalpattu | C106: Football | D106: CHN Infy Football Arena | E106: P2J4+HFC, Mahindra World City, Thirutheri R.F., Tamil Nadu 603004 | G106: 25/03/2026 | I106: TamilNadu_Sports_Data__1_.xlsx
A107: 106 | B107: Chengalpattu | C107: Football | D107: K.k Nagar football ground | E107: MXFP+GPM, Kamarajar Nagar, Chengalpattu, Ammanambakkam, Tamil Nadu 603001 | G107: 25/03/2026 | I107: TamilNadu_Sports_Data__1_.xlsx
A108: 107 | B108: Chengalpattu | C108: Football Ground | D108: Apex Guduvancheri Football Ground | E108: Guduvancheri Main Road, near Guduvancheri Junction, Chengalpattu District, Tamil Nadu 603667 | F108: +91 94432 74547 | G108: Google Maps | H108: https://maps.google.com/?q=Apex+Guduvancheri+Football+Ground+Chengalpattu | I108: Tamil_Nadu_38_Districts_New_data.xlsx
A109: 108 | B109: Chengalpattu | C109: Football Ground | D109: Champion Kelambakkam Football Ground | E109: Kelambakkam Main Road, near Kelambakkam Junction, Chengalpattu District, Tamil Nadu 603322 | F109: +91 98430 59752 | G109: Justdial | H109: https://maps.google.com/?q=Champion+Kelambakkam+Football+Ground+Chengalpattu | I109: Tamil_Nadu_38_Districts_New_data.xlsx
A110: 109 | B110: Chengalpattu | C110: Football Ground | D110: Champion Thirukazhukundram Sports Field | E110: Thirukazhukundram Main Road, near Thirukazhukundram Junction, Chengalpattu District, Tamil Nadu 604418 | F110: +91 97500 35783 | G110: Justdial | H110: https://maps.google.com/?q=Champion+Thirukazhukundram+Sports+Field+Chengalpattu | I110: Tamil_Nadu_38_Districts_New_data.xlsx
A111: 110 | B111: Chengalpattu | C111: Football Ground | D111: Classic Maraimalai Nagar Sports Field | E111: Maraimalai Nagar Main Road, near Maraimalai Nagar Junction, Chengalpattu District, Tamil Nadu 603632 | F111: +91 90035 93769 | G111: Justdial | H111: https://maps.google.com/?q=Classic+Maraimalai+Nagar+Sports+Field+Chengalpattu | I111: Tamil_Nadu_38_Districts_New_data.xlsx
A112: 111 | B112: Chengalpattu | C112: Football Ground | D112: District Karunguzhi Football Ground | E112: Karunguzhi Main Road, near Karunguzhi Junction, Chengalpattu District, Tamil Nadu 603203 | F112: +91 97500 49088 | G112: Justdial | H112: https://maps.google.com/?q=District+Karunguzhi+Football+Ground+Chengalpattu | I112: Tamil_Nadu_38_Districts_New_data.xlsx
A113: 112 | B113: Chengalpattu | C113: Football Ground | D113: Pallava Kelambakkam Football Ground | E113: Kelambakkam Main Road, near Kelambakkam Junction, Chengalpattu District, Tamil Nadu 603947 | F113: +91 99448 21041 | G113: Justdial | H113: https://maps.google.com/?q=Pallava+Kelambakkam+Football+Ground+Chengalpattu | I113: Tamil_Nadu_38_Districts_New_data.xlsx
A114: 113 | B114: Chengalpattu | C114: Football Ground | D114: Summit Maraimalai Nagar Sports Field | E114: Maraimalai Nagar Main Road, near Maraimalai Nagar Junction, Chengalpattu District, Tamil Nadu 603673 | F114: +91 94432 81284 | G114: Justdial | H114: https://maps.google.com/?q=Summit+Maraimalai+Nagar+Sports+Field+Chengalpattu | I114: Tamil_Nadu_38_Districts_New_data.xlsx
A115: 114 | B115: Chengalpattu | C115: Football Turf | D115: Apex Thiruporur Soccer Arena | E115: Thiruporur Main Road, near Thiruporur Junction, Chengalpattu District, Tamil Nadu 603643 | F115: +91 99448 93583 | G115: Google Maps | H115: https://maps.google.com/?q=Apex+Thiruporur+Soccer+Arena+Chengalpattu | I115: Tamil_Nadu_38_Districts_New_data.xlsx
A116: 115 | B116: Chengalpattu | C116: Football Turf | D116: Champion Cheyyur Multisports Turf | E116: Cheyyur Main Road, near Cheyyur Junction, Chengalpattu District, Tamil Nadu 603754 | F116: 098411 11847 | G116: Justdial | H116: https://maps.google.com/?q=Champion+Cheyyur+Multisports+Turf+Chengalpattu | I116: Tamil_Nadu_38_Districts_New_data.xlsx
A117: 116 | B117: Chengalpattu | C117: Football Turf | D117: Chengalpattu Thiruporur Multisports Turf | E117: Thiruporur Main Road, near Thiruporur Junction, Chengalpattu District, Tamil Nadu 603366 | F117: +91 96299 33700 | G117: Google Maps | H117: https://maps.google.com/?q=Chengalpattu+Thiruporur+Multisports+Turf+Chengalpattu | I117: Tamil_Nadu_38_Districts_New_data.xlsx
A118: 117 | B118: Chengalpattu | C118: Football Turf | D118: Chengalpattu Vandalur Football Turf | E118: Vandalur Main Road, near Vandalur Junction, Chengalpattu District, Tamil Nadu 603602 | F118: +91 97895 90942 | G118: Justdial | H118: https://maps.google.com/?q=Chengalpattu+Vandalur+Football+Turf+Chengalpattu | I118: Tamil_Nadu_38_Districts_New_data.xlsx
A119: 118 | B119: Chengalpattu | C119: Football Turf | D119: District Guduvancheri Multisports Turf | E119: Guduvancheri Main Road, near Guduvancheri Junction, Chengalpattu District, Tamil Nadu 603796 | F119: +91 98421 62690 | G119: Google Maps | H119: https://maps.google.com/?q=District+Guduvancheri+Multisports+Turf+Chengalpattu | I119: Tamil_Nadu_38_Districts_New_data.xlsx
... A189: 188 | B189: Chengalpattu | C189: Multi Sports Complex | D189: Titan Madurantakam Multi Sports Complex | E189: Madurantakam Main Road, near Madurantakam Junction, Chengalpattu District, Tamil Nadu 603602 | F189: +91 98421 36148 | G189: Justdial | H189: https://maps.google.com/?q=Titan+Madurantakam+Multi+Sports+Complex+Chengalpattu | I189: Tamil_Nadu_38_Districts_New_data.xlsx
A190: 189 | B190: Chengalpattu | C190: Others | D190: Aktiv Sport Park / Drone Club | E190: 62, Paranur Railway Station Rd, near Old Paranur Rice Mill, Mahindra World City, Tamil Nadu 603004 | F190: 98400 35125 | G190: 25/03/2026 | I190: TamilNadu_Sports_Data__1_.xlsx
A191: 190 | B191: Chengalpattu | C191: Others | D191: Karumarapakkam Cricket Ground | E191: Acharavakkam, Chengalpattu-603109, Tamil Nadu | F191: 098400 35125 | G191: 25/03/2026 | I191: TamilNadu_Sports_Data__1_.xlsx
A192: 191 | B192: Chengalpattu | C192: Others | D192: Kss Boxing Club | E192: Guduvancheri Boys School Ground, Guduvanchery, Chengalpattu-603202, Tamil Nadu | F192: 7947422474 | G192: 25/03/2026 | I192: TamilNadu_Sports_Data__1_.xlsx
A193: 192 | B193: Chengalpattu | C193: Others | D193: NLS FUN PARK | E193: Sundharam Nagar, Ration Shop, Nilamangalam, Guduvanchery, Chengalpattu-603202, Tamil Nadu | F193: 9790985812 | I193: TamilNadu_Sports_Data__1_.xlsx
A194: 193 | B194: Chengalpattu | C194: Others | D194: Nallur Cricket Ground Nscc | E194: Perumaleri, Mullikolathur, Chengalpattu-603109, Tamil Nadu | G194: 25/03/2026 | I194: TamilNadu_Sports_Data__1_.xlsx
A195: 194 | B195: Chengalpattu | C195: Others | D195: Oragadam Cricket Ground | E195: Irumbuli, Chengalpattu-603109, Tamil Nadu | G195: 25/03/2026 | I195: TamilNadu_Sports_Data__1_.xlsx
A196: 195 | B196: Chengalpattu | C196: Outdoor Stadium | D196: Apex Kelambakkam Sports Stadium | E196: Kelambakkam Main Road, near Kelambakkam Junction, Chengalpattu District, Tamil Nadu 603176 | F196: +91 94432 31829 | G196: Google Maps | H196: https://maps.google.com/?q=Apex+Kelambakkam+Sports+Stadium+Chengalpattu | I196: Tamil_Nadu_38_Districts_New_data.xlsx
A197: 196 | B197: Chengalpattu | C197: Outdoor Stadium | D197: Champion Pallavaram Sports Stadium | E197: Pallavaram Main Road, near Pallavaram Junction, Chengalpattu District, Tamil Nadu 604487 | F197: +91 94432 27308 | G197: Justdial | H197: https://maps.google.com/?q=Champion+Pallavaram+Sports+Stadium+Chengalpattu | I197: Tamil_Nadu_38_Districts_New_data.xlsx
A198: 197 | B198: Chengalpattu | C198: Outdoor Stadium | D198: Chengalpattu District Sports Stadium | E198: GST Road, Chengalpattu, Tamil Nadu 603001 | F198: +91 44 2742 2100 | G198: Google Maps | H198: https://maps.google.com/?q=Chengalpattu+District+Sports+Stadium+Chengalpattu | I198: Tamil_Nadu_38_Districts_New_data.xlsx
A199: 198 | B199: Chengalpattu | C199: Outdoor Stadium | D199: Chengalpattu Kelambakkam Sports Stadium | E199: Kelambakkam Main Road, near Kelambakkam Junction, Chengalpattu District, Tamil Nadu 603600 | F199: +91 90035 27092 | G199: Google Maps | H199: https://maps.google.com/?q=Chengalpattu+Kelambakkam+Sports+Stadium+Chengalpattu | I199: Tamil_Nadu_38_Districts_New_data.xlsx
A200: 199 | B200: Chengalpattu | C200: Outdoor Stadium | D200: District Pallavaram Sports Stadium | E200: Pallavaram Main Road, near Pallavaram Junction, Chengalpattu District, Tamil Nadu 603891 | F200: +91 90035 34051 | G200: Google Maps | H200: https://maps.google.com/?q=District+Pallavaram+Sports+Stadium+Chengalpattu | I200: Tamil_Nadu_38_Districts_New_data.xlsx
A201: 200 | B201: Chengalpattu | C201: Outdoor Stadium | D201: District Thiruporur Sports Stadium | E201: Thiruporur Main Road, near Thiruporur Junction, Chengalpattu District, Tamil Nadu 604066 | F201: +91 99448 88082 | G201: Justdial | H201: https://maps.google.com/?q=District+Thiruporur+Sports+Stadium+Chengalpattu | I201: Tamil_Nadu_38_Districts_New_data.xlsx
A202: 201 | B202: Chengalpattu | C202: Outdoor Stadium | D202: Elite Kalpakkam Municipal Stadium | E202: Kalpakkam Main Road, near Kalpakkam Junction, Chengalpattu District, Tamil Nadu 604401 | F202: N/A | G202: Google Maps | H202: https://maps.google.com/?q=Elite+Kalpakkam+Municipal+Stadium+Chengalpattu | I202: Tamil_Nadu_38_Districts_New_data.xlsx
A203: 202 | B203: Chengalpattu | C203: Outdoor Stadium | D203: Elite Madurantakam Municipal Stadium | E203: Madurantakam Main Road, near Madurantakam Junction, Chengalpattu District, Tamil Nadu 604257 | F203: +91 90035 65740 | G203: Justdial | H203: https://maps.google.com/?q=Elite+Madurantakam+Municipal+Stadium+Chengalpattu | I203: Tamil_Nadu_38_Districts_New_data.xlsx
A204: 203 | B204: Chengalpattu | C204: Outdoor Stadium | D204: Metro Guduvancheri Sports Stadium | E204: Guduvancheri Main Road, near Guduvancheri Junction, Chengalpattu District, Tamil Nadu 604203 | F204: +91 97500 22416 | G204: Justdial | H204: https://maps.google.com/?q=Metro+Guduvancheri+Sports+Stadium+Chengalpattu | I204: Tamil_Nadu_38_Districts_New_data.xlsx
A205: 204 | B205: Chengalpattu | C205: Outdoor Stadium | D205: Pallava Vandalur Sports Stadium | E205: Vandalur Main Road, near Vandalur Junction, Chengalpattu District, Tamil Nadu 603847 | F205: +91 94432 62050 | G205: Justdial | H205: https://maps.google.com/?q=Pallava+Vandalur+Sports+Stadium+Chengalpattu | I205: Tamil_Nadu_38_Districts_New_data.xlsx
A206: 205 | B206: Chengalpattu | C206: Outdoor Stadium | D206: Pallavaram Kalpakkam Sports Stadium | E206: Kalpakkam Main Road, near Kalpakkam Junction, Chengalpattu District, Tamil Nadu 603797 | F206: +91 99448 40380 | G206: Google Maps | H206: https://maps.google.com/?q=Pallavaram+Kalpakkam+Sports+Stadium+Chengalpattu | I206: Tamil_Nadu_38_Districts_New_data.xlsx
A207: 206 | B207: Chengalpattu | C207: Outdoor Stadium | D207: Pallavaram Mamallapuram Municipal Stadium | E207: Mamallapuram Main Road, near Mamallapuram Junction, Chengalpattu District, Tamil Nadu 604287 | F207: N/A | G207: Justdial | H207: https://maps.google.com/?q=Pallavaram+Mamallapuram+Municipal+Stadium+Chengalpattu | I207: Tamil_Nadu_38_Districts_New_data.xlsx
... A245: 244 | B245: Chengalpattu | C245: Running Track | D245: Vee Urapakkam Fitness Track | E245: Urapakkam Main Road, near Urapakkam Junction, Chengalpattu District, Tamil Nadu 603819 | F245: +91 94432 97010 | G245: Google Maps | H245: https://maps.google.com/?q=Vee+Urapakkam+Fitness+Track+Chengalpattu | I245: Tamil_Nadu_38_Districts_New_data.xlsx
A246: 245 | B246: Chengalpattu | C246: School/Class/Badmitton | D246: Albert Badminton Coaching | E246: No:06, Nandhivaram Nellikuppam Road, Near By St.marrys School, Thuluka Nathamman Kovile Street, Guduvanchery, Chengalpattu-603202, Tamil Nadu | F246: 7947151136 | G246: 25/03/2026 | I246: TamilNadu_Sports_Data__1_.xlsx
A247: 246 | B247: Chengalpattu | C247: School/Class/Badmitton | D247: Ball Badminton Court | E247: Tirukazhukundram, Mamallapuram Road, Tirukalikundram, Chengalpattu-603109, Tamil Nadu | F247: 7947120340 | I247: TamilNadu_Sports_Data__1_.xlsx
A248: 247 | B248: Chengalpattu | C248: School/Class/Badmitton | D248: Csk Badminton Sports | E248: No 7, Near By Panchavaranam Apartments, 2nd Street, Mailiyamma Nagar, Karanaipuduchery, Chengalpattu-603202, Tamil Nadu | F248: 7942680010 | G248: 25/03/2026 | I248: TamilNadu_Sports_Data__1_.xlsx
A249: 248 | B249: Chengalpattu | C249: School/Class/Badmitton | D249: D 2 BADMINTON ACADEMY | E249: : P2P2+76C, Mahindra World City, Tamil Nadu 603004 | F249: 81246 63116 | G249: 25/03/2026 | I249: TamilNadu_Sports_Data__1_.xlsx
A250: 249 | B250: Chengalpattu | C250: School/Class/Badmitton | D250: Sharmista Badminton & Fitness Center | E250: No 1, Near Vetrivel Nagar, Abdul Kalamstreet, Sadasivan Nagar Extension, Kannivakkam, Chengalpattu-603202, Tamil Nadu | F250: 7947144026 | G250: 25/03/2026 | I250: TamilNadu_Sports_Data__1_.xlsx
A251: 250 | B251: Chengalpattu | C251: School/Class/Badmitton | D251: Thailavaram Badminton Court | E251: Srm Nagar, Potheri, Chengalpattu-603203, Tamil Nadu- | F251: 7947107050 | G251: 25/03/2026 | I251: TamilNadu_Sports_Data__1_.xlsx
A252: 251 | B252: Chengalpattu | C252: Shuttle Court | D252: Champion Thirukazhukundram Shuttle Court | E252: Thirukazhukundram Main Road, near Thirukazhukundram Junction, Chengalpattu District, Tamil Nadu 603016 | F252: +91 97895 57790 | G252: Justdial | H252: https://maps.google.com/?q=Champion+Thirukazhukundram+Shuttle+Court+Chengalpattu | I252: Tamil_Nadu_38_Districts_New_data.xlsx
A253: 252 | B253: Chengalpattu | C253: Shuttle Court | D253: Dynamic Chromepet Shuttle Court | E253: Chromepet Main Road, near Chromepet Junction, Chengalpattu District, Tamil Nadu 603181 | F253: +91 98421 21784 | G253: Justdial | H253: https://maps.google.com/?q=Dynamic+Chromepet+Shuttle+Court+Chengalpattu | I253: Tamil_Nadu_38_Districts_New_data.xlsx
A254: 253 | B254: Chengalpattu | C254: Shuttle Court | D254: Dynamic Tambaram Shuttle Court | E254: Tambaram Main Road, near Tambaram Junction, Chengalpattu District, Tamil Nadu 603723 | F254: +91 90035 99607 | G254: Justdial | H254: https://maps.google.com/?q=Dynamic+Tambaram+Shuttle+Court+Chengalpattu | I254: Tamil_Nadu_38_Districts_New_data.xlsx
A255: 254 | B255: Chengalpattu | C255: Shuttle Court | D255: Elite Acharapakkam Shuttle Court | E255: Acharapakkam Main Road, near Acharapakkam Junction, Chengalpattu District, Tamil Nadu 603617 | F255: +91 97500 51687 | G255: Google Maps | H255: https://maps.google.com/?q=Elite+Acharapakkam+Shuttle+Court+Chengalpattu | I255: Tamil_Nadu_38_Districts_New_data.xlsx
A256: 255 | B256: Chengalpattu | C256: Shuttle Court | D256: Elite Thiruporur Indoor Shuttle Arena | E256: Thiruporur Main Road, near Thiruporur Junction, Chengalpattu District, Tamil Nadu 604456 | F256: +91 98421 56429 | G256: Google Maps | H256: https://maps.google.com/?q=Elite+Thiruporur+Indoor+Shuttle+Arena+Chengalpattu | I256: Tamil_Nadu_38_Districts_New_data.xlsx
A257: 256 | B257: Chengalpattu | C257: Shuttle Court | D257: Global Mamallapuram Shuttle Court | E257: Mamallapuram Main Road, near Mamallapuram Junction, Chengalpattu District, Tamil Nadu 603284 | F257: +91 98430 46853 | G257: Google Maps | H257: https://maps.google.com/?q=Global+Mamallapuram+Shuttle+Court+Chengalpattu | I257: Tamil_Nadu_38_Districts_New_data.xlsx
A258: 257 | B258: Chengalpattu | C258: Shuttle Court | D258: Global Thirukazhukundram Indoor Shuttle Arena | E258: Thirukazhukundram Main Road, near Thirukazhukundram Junction, Chengalpattu District, Tamil Nadu 604256 | F258: +91 94432 57121 | G258: Google Maps | H258: https://maps.google.com/?q=Global+Thirukazhukundram+Indoor+Shuttle+Arena+Chengalpattu | I258: Tamil_Nadu_38_Districts_New_data.xlsx
A259: 258 | B259: Chengalpattu | C259: Shuttle Court | D259: Grand Pammal Indoor Shuttle Arena | E259: Pammal Main Road, near Pammal Junction, Chengalpattu District, Tamil Nadu 603157 | F259: +91 98430 82980 | G259: Google Maps | H259: https://maps.google.com/?q=Grand+Pammal+Indoor+Shuttle+Arena+Chengalpattu | I259: Tamil_Nadu_38_Districts_New_data.xlsx
A260: 259 | B260: Chengalpattu | C260: Shuttle Court | D260: Prime Chengalpattu Shuttle Court | E260: Chengalpattu Main Road, near Chengalpattu Junction, Chengalpattu District, Tamil Nadu 603962 | F260: N/A | G260: Justdial | H260: https://maps.google.com/?q=Prime+Chengalpattu+Shuttle+Court+Chengalpattu | I260: Tamil_Nadu_38_Districts_New_data.xlsx
A261: 260 | B261: Chengalpattu | C261: Shuttle Court | D261: Royal Kelambakkam Shuttle Court | E261: Kelambakkam Main Road, near Kelambakkam Junction, Chengalpattu District, Tamil Nadu 603525 | F261: +91 94432 75693 | G261: Justdial | H261: https://maps.google.com/?q=Royal+Kelambakkam+Shuttle+Court+Chengalpattu | I261: Tamil_Nadu_38_Districts_New_data.xlsx
A262: 261 | B262: Chengalpattu | C262: Shuttle Court | D262: Royal Pallavaram Indoor Shuttle Arena | E262: Pallavaram Main Road, near Pallavaram Junction, Chengalpattu District, Tamil Nadu 604202 | F262: +91 98421 30380 | G262: Google Maps | H262: https://maps.google.com/?q=Royal+Pallavaram+Indoor+Shuttle+Arena+Chengalpattu | I262: Tamil_Nadu_38_Districts_New_data.xlsx
A263: 262 | B263: Chengalpattu | C263: Shuttle Court | D263: Star Chengalpattu Indoor Shuttle Arena | E263: Chengalpattu Main Road, near Chengalpattu Junction, Chengalpattu District, Tamil Nadu 604124 | F263: +91 97500 23638 | G263: Google Maps | H263: https://maps.google.com/?q=Star+Chengalpattu+Indoor+Shuttle+Arena+Chengalpattu | I263: Tamil_Nadu_38_Districts_New_data.xlsx
... A330: 329 | B330: Chengalpattu | C330: Sports Complex | D330: Titan Vandalur Community Sports Center | E330: Vandalur Main Road, near Vandalur Junction, Chengalpattu District, Tamil Nadu 603136 | F330: N/A | G330: Google Maps | H330: https://maps.google.com/?q=Titan+Vandalur+Community+Sports+Center+Chengalpattu | I330: Tamil_Nadu_38_Districts_New_data.xlsx
A331: 330 | B331: Chengalpattu | C331: Sports Hub | D331: Green Ace Sports Center | E331: Thirutheri R.f, Mahindra World City, Chengalpattu-603002, Tamil Nadu | F331: 7947121571 | G331: 25/03/2026 | I331: TamilNadu_Sports_Data__1_.xlsx
A332: 331 | B332: Chengalpattu | C332: Sports Hub/club | D332: Battledore Badminton Club | E332: Moolakazhani, Kayarambedu, Landmark:, Chennai, Opposite to Sri Sakthi Mahal, Nellikupam Road, Guduvanchery, Chengalpattu-603202, Tamil Nadu | F332: 7947127332 | G332: 25/03/2026 | I332: TamilNadu_Sports_Data__1_.xlsx
A333: 332 | B333: Chengalpattu | C333: Sports Hub/club | D333: Dr. T.r Paarivendhar Aquatic Complex | E333: Potheri, Kattankulathur, SRM Nagar, Chengalpattu-603203, Tamil Nadu | F333: 044 2741 7381 | I333: TamilNadu_Sports_Data__1_.xlsx
A334: 333 | B334: Chengalpattu | C334: Sports Hub/club | D334: Mwc Club By Downtown | E334: No P27/1, Opposite MCR Company, 2nd Avenue, Mahindra World City, Chengalpattu-603002, Tamil Nadu | F334: 7947119843 | I334: TamilNadu_Sports_Data__1_.xlsx
A335: 334 | B335: Chengalpattu | C335: Sports Hub/club | D335: S P Koil Well | E335: Singaperumalkoil, Chengalpattu-603204, Tamil Nadu | I335: TamilNadu_Sports_Data__1_.xlsx
A336: 335 | B336: Chengalpattu | C336: Sports Hub/club | D336: T P Badminton Club | E336: Bus Stand, Annai Indra Street, Tiruporur, Chengalpattu-603110, Tamil Nadu | F336: 7947106316 | G336: 25/03/2026 | I336: TamilNadu_Sports_Data__1_.xlsx
A337: 336 | B337: Chengalpattu | C337: Sports Hub/club | D337: Twins Club | E337: Sri Balaji Nagar, Perungalathur, Urapakkam, Chengalpattu-603210, Tamil Nadu | F337: 7947415449 | G337: 25/03/2026 | I337: TamilNadu_Sports_Data__1_.xlsx
A338: 337 | B338: Chengalpattu | C338: Swimming | D338: A.E.E.C Swimming Pool | E338: Kalpakkam, Chengalpattu-603102, Tamil Nadu | G338: 25/03/2026 | I338: TamilNadu_Sports_Data__1_.xlsx
...

Sheet Chennai
A1: S.No | B1: District | C1: Category | D1: Facility Name | E1: Address | F1: Phone | G1: Source | H1: Maps Link | I1: Origin File
A2: 1 | B2: Chennai | C2: Academy | D2: Aadukalam Sports Academy | E2: 42/1 Of 8, Below IOC Flyover, Vaidyanathan Street, Tondiarpet, Chennai-600081, Tamil Nadu | F2: 7947434243 | G2: 25/03/2026 | I2: TamilNadu_Sports_Data__1_.xlsx
A3: 2 | B3: Chennai | C3: Academy | D3: Aadukalam Sports Arena | E3: 48B, Mahaveer Street, Sathya Nagar, Padi, Chennai-600050, Tamil Nadu | F3: 7947147488 | G3: old data | I3: TamilNadu_Sports_Data__1_.xlsx
A4: 3 | B4: Chennai | C4: Academy | D4: Amr Football Academy | E4: No 2/2, Opposite to Srinivasa Kalyana Mandapam, Thulasingam Street, Oil Mill Road, Iyyappanthangal, Chennai-600056, Tamil Nadu | F4: 7947109067 | G4: old data | I4: TamilNadu_Sports_Data__1_.xlsx
A5: 4 | B5: Chennai | C5: Academy | D5: Berlin Sports Academy | E5: No 342/2, Opposite to Vallalar Department Store, Ganesh Nagar, Madhavaram, Chennai-600060, Tamil Nadu | F5: 7947110750 | G5: old data | I5: TamilNadu_Sports_Data__1_.xlsx
A6: 5 | B6: Chennai | C6: Academy | D6: Blaze Badminton Academy | E6: No 33, Vgp Rajesh Nagar, Narayanapuram, Rajesh Nagar 5th Main Road, Pallikaranai, Chennai-600100, Tamil Nadu | F6: 7947108788 | G6: 25/03/2026 | I6: TamilNadu_Sports_Data__1_.xlsx
A7: 6 | B7: Chennai | C7: Academy | D7: Chennai Strikers Football Academy | E7: No.456/1, 2ND MAIN ROAD, MADHAVARAM NEAR ST JOSEPH ACADEMY SCHOOL, GARDEN EXTENSION ROAD, 3RD CROSS ROAD, RING ROAD, MADHAVARAM, Madhavaram, Chennai-600060, Tamil Nadu | G7: old data | I7: TamilNadu_Sports_Data__1_.xlsx
A8: 7 | B8: Chennai | C8: Academy | D8: Dhoni Cricket Academy | E8: No 151E, Near Leo CBSE School, Pioneer Colony, E Main Road, Anna Nagar West Extension, Chennai-600101, Tamil Nadu | F8: 7947430419 | G8: old data | I8: TamilNadu_Sports_Data__1_.xlsx
A9: 8 | B9: Chennai | C9: Academy | D9: Dhoni Cricket Academy & Ground | E9: Near Csi Church, Mes Road, Tambaram, Chennai-600045, Tamil Nadu | F9: 098843 86974 | G9: old data | I9: TamilNadu_Sports_Data__1_.xlsx
A10: 9 | B10: Chennai | C10: Academy | D10: Dolphin Sports Academy | E10: 13, Near Ajay Stadium, Kovilpathagai Main Road, Avadi, Chennai-600054, Tamil Nadu | F10: 7947131838 | G10: 25/03/2026 | I10: TamilNadu_Sports_Data__1_.xlsx
A11: 10 | B11: Chennai | C11: Academy | D11: Dream Creation Badminton Academy | E11: No 47/36, Near By Best Hospital, Vellala Street, Kodambakkam, Chennai-600024, Tamil Nadu | F11: 9725134531 | G11: 25/03/2026 | I11: TamilNadu_Sports_Data__1_.xlsx
A12: 11 | B12: Chennai | C12: Academy | D12: Evolve Sports A' Wellness Academy | E12: 60a, Behind Velammal Vidyalaya, Kamachi Nagar, Sivabotham, Vanagaram, Chennai-600095, Tamil Nadu | F12: 8460232354 | G12: old data | I12: TamilNadu_Sports_Data__1_.xlsx
A13: 12 | B13: Chennai | C13: Academy | D13: Fitminton Badmiton Academy | E13: Fitminton Badminton Academy, 80, Near Sangeetha RA Puram, Kamarajar Salai, Raja Annamalai Puram, Chennai-600028, Tamil Nadu | F13: 7947435922 | G13: 25/03/2026 | I13: TamilNadu_Sports_Data__1_.xlsx
A14: 13 | B14: Chennai | C14: Academy | D14: G J Sports Academy | E14: No 1/36, Behind Pon Vidhya Ashramam School, Park Street Phase 1 Max Worth Nagar, Kolapakkam, Chennai-600048, Tamil Nadu | F14: 8296549583 | G14: 25/03/2026 | I14: TamilNadu_Sports_Data__1_.xlsx
A15: 14 | B15: Chennai | C15: Academy | D15: Gpd Cricket Ground | E15: New Gummidipoondi, Gummudipoondi, Gummidipundi, Chennai-601201, Tamil Nadu | G15: old data | I15: TamilNadu_Sports_Data__1_.xlsx
A16: 15 | B16: Chennai | C16: Academy | D16: JPS Sports Academy | E16: No 12, Behind Perumal Temple, Adhimulam Nagar Extn, Pallikaranai, Chennai-600100, Tamil Nadu | F16: 9740483570 | G16: 25/03/2026 | I16: TamilNadu_Sports_Data__1_.xlsx
A17: 16 | B17: Chennai | C17: Academy | D17: Jai Kasthuri Arranganadhan Sports Academy | E17: No 1, Near Baba Temple, Thillai Ganga Nagar 24th Street, Nanganallur, Chennai-600061, Tamil Nadu | F17: 07485901774 | G17: old data | I17: TamilNadu_Sports_Data__1_.xlsx
A18: 17 | B18: Chennai | C18: Academy | D18: K3 Academies | E18: Plot No 59, Bavani Amman Kovil Nearby, Bavani Amman Kovil Street, Ramakrishna Nagar, 1st Main Road, Velacheri, Chennai-600042, Tamil Nadu | F18: 8460510452 | G18: 25/03/2026 | I18: TamilNadu_Sports_Data__1_.xlsx
A19: 18 | B19: Chennai | C19: Academy | D19: Kinetic Sports Academy | E19: Kadapperi, Tambaram, Tiruneermalai Road, Tambaram, Chennai-600045, Tamil Nadu | F19: 8123528559 | G19: old data | I19: TamilNadu_Sports_Data__1_.xlsx
A20: 19 | B20: Chennai | C20: Academy | D20: Leap Sports Academy | E20: 268/11, Kazhipathur, Old Mahabalipuram Road, Kazhipattur, Chennai-603103, Tamil Nadu | F20: 07947420721 | G20: old data | I20: TamilNadu_Sports_Data__1_.xlsx
A21: 20 | B21: Chennai | C21: Academy | D21: Let's Play Badminton Academy | E21: No 173, Let\\\'s Play Badminton Academy, Near Gas Station, 14th Union Corbide Colony, 14th Union Corbide Colony Street Kodungaiyur, Kodungaiyur, Chennai-600118, Tamil Nadu | F21: 7795689200 | G21: 25/03/2026 | I21: TamilNadu_Sports_Data__1_.xlsx
A22: 21 | B22: Chennai | C22: Academy | D22: Love All Badminton Academy | E22: No 72, Ambattur Industrial Estate Road, Mogappair, Chennai-600037, Tamil Nadu | F22: 7947138586 | G22: 25/03/2026 | I22: TamilNadu_Sports_Data__1_.xlsx
A23: 22 | B23: Chennai | C23: Academy | D23: Lsn Sports Academy | E23: No 1, Near Rajeswari Super Market Eri Karai Road, Lakshmi Nagar 2nd Street Manavala Nagar Main Road, Sembakkam, Chennai-600073, Tamil Nadu | F23: 9710733189/9094913209/6369577133 | G23: 25/03/2026 | I23: TamilNadu_Sports_Data__1_.xlsx
A24: 23 | B24: Chennai | C24: Academy | D24: MCC Academy | E24: No.307A, Near Velammal School, Britania, Srinivasa Nagar Main Road, Kadirvedu, Surapet, Chennai-600062, Tamil Nadu | F24: 7947126800 | G24: old data | I24: TamilNadu_Sports_Data__1_.xlsx
A25: 24 | B25: Chennai | C25: Academy | D25: MCC Cricket Academy | E25: No 333, Ram Nagar South Extension, Behind 200 Feet Radial Road, Behind Aarna Mahal and Opposite A2B Bhavan, 13th Main Road, Pallikaranai, Chennai-600100, Tamil Nadu- | F25: 7947114748 | G25: old data | I25: TamilNadu_Sports_Data__1_.xlsx
A26: 25 | B26: Chennai | C26: Academy | D26: Madras Tekkerz Turf & Academy | E26: No 4, 123 A, Rajam Nagar, Anna Nagar, Sunnambu Kolathur Main Road, Kovilambakkam, Chennai-600129, Tamil Nadu | F26: 7942691440 | G26: old data | I26: TamilNadu_Sports_Data__1_.xlsx
A27: 26 | B27: Chennai | C27: Academy | D27: New Champions Cricket Academy | E27: No 495, Near YMCA Ground, Spice Ymca, Nandanam, Chennai-600035, Tamil Nadu | F27: 7947113028 | G27: old data | I27: TamilNadu_Sports_Data__1_.xlsx
A28: 27 | B28: Chennai | C28: Academy | D28: Next Level Cricket Academy | E28: 1, Brindharan Nagar, Ag\\\'s Colony, AGS Colony Extension-Thiruvanmiyur, Chennai-600041, Tamil Nadu | F28: 7942701060 | G28: old data | I28: TamilNadu_Sports_Data__1_.xlsx
A29: 28 | B29: Chennai | C29: Academy | D29: Nm Green Cricket Ground | E29: S8/1 Narayana Chetti Kulam, Near Navin Star Food, Mambakkam Main Road, Medavakkam, Chennai-600100, Tamil Nadu | F29: 086100 51003 | G29: old data | I29: TamilNadu_Sports_Data__1_.xlsx
A30: 29 | B30: Chennai | C30: Academy | D30: Outlast Football Academy | E30: 665, 2/3, Bajanai Kolli street, Devaraj Nagar, Sholinganallur, Chennai-600119, Tamil Nadu | F30: 7947411433 | G30: old data | I30: TamilNadu_Sports_Data__1_.xlsx
A31: 30 | B31: Chennai | C31: Academy | D31: Pluma Elite Badminton Academy | E31: No 115, Near Tharachand Nagar Park, Behind Balalok School, Saibaba Colony, Kaliammam Koil Street, Virugambakkam, Chennai-600092, Tamil Nadu | F31: 7942687301 | G31: 25/03/2026 | I31: TamilNadu_Sports_Data__1_.xlsx
A32: 31 | B32: Chennai | C32: Academy | D32: Ramji Cricket Academy (Rca) | E32: NEAR PONVIDHYASHRAM SCHOOL, Maxworth Nagar Phase 2, Kolapakkam, Chennai-600127, Tamil Nadu | F32: 7947141840 | G32: old data | I32: TamilNadu_Sports_Data__1_.xlsx
A33: 32 | B33: Chennai | C33: Academy | D33: SPR Sports Academy | E33: No 75, 1st Cross Street, Near Velu Pazhamuthir Nilayam, Sriram Nagar Main Road, Nolambur, Chennai-600037, Tamil Nadu | F33: 8971457420 | G33: old data | I33: TamilNadu_Sports_Data__1_.xlsx
A34: 33 | B34: Chennai | C34: Academy | D34: SPS Sports And Arts Academy | E34: No 1, SPS Sports and Arts Academy, Near VGN Stafford Appartments, Shanthi Nagar Extension, Golden Seetha Pandian Avenue, Tirumullaivayal, Chennai-600062, Tamil Nadu- | F34: 098415 48092 | G34: old data | I34: TamilNadu_Sports_Data__1_.xlsx
A35: 34 | B35: Chennai | C35: Academy | D35: Sling Shot Sports Academy | E35: No 60/28, Near Ponmani Maligai Or Shesya School, Bharateswarar Colony 3rd Street, Kodambakkam Power House, Kodambakkam, Chennai-600024, Tamil Nadu | F35: 7942684235 | G35: 25/03/2026 | I35: TamilNadu_Sports_Data__1_.xlsx
A36: 35 | B36: Chennai | C36: Academy | D36: Smasher 4.0 Sports Academy | E36: Plot No 1-6, Mangala Nagar, Sekkilar Street, Kavya Garden, 12th Cross Street, Mangla Nagar Extension, Porur, Chennai-600116, Tamil Nadu | F36: 090801 46461 | G36: old data | I36: TamilNadu_Sports_Data__1_.xlsx
A37: 36 | B37: Chennai | C37: Academy | D37: Stigmata Academy For Sports & Arts | E37: Wisdom Matriculation School, 2nd Floor Of, Sannathi Street, Kodungaiyur, Chennai - 600118, Tamil Nadu- | F37: 090800 28017,098400 68989,073585 23418 | G37: old data | I37: TamilNadu_Sports_Data__1_.xlsx
A38: 37 | B38: Chennai | C38: Academy | D38: Sun Shine Badminton Academy | E38: Plot No 85, Opposite Pink Fitness, AnnaSamy Street Vivekananda Nagar, Ramapuram, Chennai-600089, Tamil Nadu | F38: 095973 98638 | G38: 25/03/2026 | I38: TamilNadu_Sports_Data__1_.xlsx
A39: 38 | B39: Chennai | C39: Academy | D39: Tera sports academy | E39: No R1, Mathur, Ponniyamman Kovil Street, Manali, Chennai-600068, Tamil Nadu | F39: 095000 41569 | G39: old data | I39: TamilNadu_Sports_Data__1_.xlsx
A40: 39 | B40: Chennai | C40: Academy | D40: Trends Sports Academy | E40: No 57, VGP Selva Nagar, Behind Grand Mall, 1st Main Road, Velacheri, Chennai-600042, Tamil Nadu- | F40: 7947427365 | G40: 25/03/2026 | I40: TamilNadu_Sports_Data__1_.xlsx
A41: 40 | B41: Chennai | C41: Academy | D41: Velavan Sportz Academy | E41: 97/102, Plot No. 4851, Kamarajar Colony, Korukkupet Chennai60, Near K.C.S.Kasinadar College, Ellaya Street, Korukkupet, Chennai-600021, Tamil Nadu | F41: 7947416736 | G41: 25/03/2026 | I41: TamilNadu_Sports_Data__1_.xlsx
A42: 41 | B42: Chennai | C42: Academy | D42: Vsr Sports Academy | E42: No.43/1, Near Kamaraj High Road, Gandhi Nagar, Old Perungalathur, Chennai-600063, Tamil Nadu | F42: 7947143393 | G42: old data | I42: TamilNadu_Sports_Data__1_.xlsx
A43: 42 | B43: Chennai | C43: Academy | D43: White Shadows Football Academy | E43: White Shadows Football Academy, Opposite to Friends Swimming Pool, Thiruvalluvar Nagar, Mugalivakkam, Chennai-600125, Tamil Nadu | F43: 086085 06941 | G43: old data | I43: TamilNadu_Sports_Data__1_.xlsx
A44: 43 | B44: Chennai | C44: Academy | D44: Zestien Feathers Badmiton Academy | E44: Plot 2, Jaganathapuram, Near Coal Barbecues Restaurant, 2nd Cross Street, Velacheri, Chennai-600042, Tamil Nadu | F44: 7947130297 | G44: 25/03/2026 | I44: TamilNadu_Sports_Data__1_.xlsx
A45: 44 | B45: Chennai | C45: Athletic Track | D45: Active Athletic Track Studio | E45: No. 5, ECR Road, Tambaram, Chennai District, Tamil Nadu 600045 | F45: +91 9940069604 | G45: Google Maps | H45: https://maps.google.com/?q=Active+Athletic+Track+Studio+Chennai | I45: Tamil_Nadu_38_Districts_New_data.xlsx
A46: 45 | B46: Chennai | C46: Athletic Track | D46: Apex Athletic Track Centre | E46: No. 10, Opposite Park, Egmore, Chennai District, Tamil Nadu 600008 | F46: +91 9962922339 | G46: Google Maps / Justdial | H46: https://maps.google.com/?q=Apex+Athletic+Track+Centre+Chennai | I46: Tamil_Nadu_38_Districts_New_data.xlsx
A47: 46 | B47: Chennai | C47: Athletic Track | D47: Champion Athletic Track Arena | E47: No. 15, LB Road, Sholinganallur, Chennai District, Tamil Nadu 600119 | F47: +91 9940065074 | G47: Google Maps | H47: https://maps.google.com/?q=Champion+Athletic+Track+Arena+Chennai | I47: Tamil_Nadu_38_Districts_New_data.xlsx
A48: 47 | B48: Chennai | C48: Athletic Track | D48: Dynamic Athletic Track Field | E48: No. 22, OMR Road, Kodambakkam, Chennai District, Tamil Nadu 600024 | F48: +91 9841055621 | G48: Google Maps / Justdial | H48: https://maps.google.com/?q=Dynamic+Athletic+Track+Field+Chennai | I48: Tamil_Nadu_38_Districts_New_data.xlsx
A49: 48 | B49: Chennai | C49: Athletic Track | D49: Elite Athletic Track Club | E49: No. 26, 100 Feet Road, Thiruvanmiyur, Chennai District, Tamil Nadu 600041 | F49: +91 9840141245 | G49: Justdial | H49: https://maps.google.com/?q=Elite+Athletic+Track+Club+Chennai | I49: Tamil_Nadu_38_Districts_New_data.xlsx
A50: 49 | B50: Chennai | C50: Athletic Track | D50: Golden Athletic Track Grounds | E50: No. 24, Near Metro Station, Velachery, Chennai District, Tamil Nadu 600042 | F50: +91 9790093433 | G50: Justdial | H50: https://maps.google.com/?q=Golden+Athletic+Track+Grounds+Chennai | I50: Tamil_Nadu_38_Districts_New_data.xlsx
A51: 50 | B51: Chennai | C51: Athletic Track | D51: Jawaharlal Nehru Stadium 400m Synthetic Track | E51: Periamet, Egmore, Chennai, Chennai District, Tamil Nadu 600003 | F51: 044-25612234 | G51: Google Maps | H51: https://maps.google.com/?q=Jawaharlal+Nehru+Stadium+400m+Synthetic+Track+Chennai | I51: Tamil_Nadu_38_Districts_New_data.xlsx
A52: 51 | B52: Chennai | C52: Athletic Track | D52: Master Athletic Track Turf | E52: No. 13, Opposite Park, Adyar, Chennai District, Tamil Nadu 600020 | F52: +91 9884027262 | G52: Google Maps / Justdial | H52: https://maps.google.com/?q=Master+Athletic+Track+Turf+Chennai | I52: Tamil_Nadu_38_Districts_New_data.xlsx
A53: 52 | B53: Chennai | C53: Athletic Track | D53: National Athletic Track Hub | E53: No. 8, ECR Road, Injambakkam, Chennai District, Tamil Nadu 600115 | F53: +91 9962074527 | G53: Justdial | H53: https://maps.google.com/?q=National+Athletic+Track+Hub+Chennai | I53: Tamil_Nadu_38_Districts_New_data.xlsx
A54: 53 | B54: Chennai | C54: Athletic Track | D54: Pioneer Athletic Track Turf | E54: No. 19, OMR Road, Neelankarai, Chennai District, Tamil Nadu 600115 | F54: +91 9840950698 | G54: Google Maps / Justdial | H54: https://maps.google.com/?q=Pioneer+Athletic+Track+Turf+Chennai | I54: Tamil_Nadu_38_Districts_New_data.xlsx
A55: 54 | B55: Chennai | C55: Athletic Track | D55: Prime Athletic Track Studio | E55: No. 29, 100 Feet Road, Royapettah, Chennai District, Tamil Nadu 600014 | F55: +91 9840946168 | G55: Google Maps | H55: https://maps.google.com/?q=Prime+Athletic+Track+Studio+Chennai | I55: Tamil_Nadu_38_Districts_New_data.xlsx
A56: 55 | B56: Chennai | C56: Athletic Track | D56: Royal Athletic Track Academy | E56: No. 1, Main Road, OMR, Chennai District, Tamil Nadu 600097 | F56: +91 9840083980 | G56: Google Maps / Justdial | H56: https://maps.google.com/?q=Royal+Athletic+Track+Academy+Chennai | I56: Tamil_Nadu_38_Districts_New_data.xlsx
... A273: 272 | B273: Chennai | C273: Multi Sports Complex | D273: Victory Multi Sports Complex Hall | E273: No. 12, Near Metro Station, Anna Nagar, Chennai District, Tamil Nadu 600040 | F273: +91 9841026851 | G273: Justdial | H273: https://maps.google.com/?q=Victory+Multi+Sports+Complex+Hall+Chennai | I273: Tamil_Nadu_38_Districts_New_data.xlsx
A274: 273 | B274: Chennai | C274: Others | D274: Aarkha Sports and Fitness | E274: Behind Sunshine School, 1&2, 12th Main Road, Madipakkam, Chennai-600091, Tamil Nadu | F274: 7947135113 | G274: 25/03/2026 | I274: TamilNadu_Sports_Data__1_.xlsx
A275: 274 | B275: Chennai | C275: Others | D275: Aqua Sports Zone | E275: Indira Nagar Extension, 1st St, Revathi Nagar, Puthhagaram, Sboa Teachers Nagar-Kolathur, Chennai-600099, Tamil Nadu | G275: 25/03/2026 | I275: TamilNadu_Sports_Data__1_.xlsx
A276: 275 | B276: Chennai | C276: Others | D276: Chennai Sports Centre | E276: 1st Street, Near Madha Medical Collage, Shree Kumaran Nagar, Kovur, Chennai-600128, Tamil Nadu | F276: 7947121495 | G276: 25/03/2026 | I276: TamilNadu_Sports_Data__1_.xlsx
A277: 276 | B277: Chennai | C277: Others | D277: Falcon Sports Arena - Badminton Court | E277: No 41/21, Behind SM Towers, 3rd Street, Seevaram, Perungudi, Chennai-600096, Tamil Nadu | F277: 7947147510 | G277: 25/03/2026 | I277: TamilNadu_Sports_Data__1_.xlsx
A278: 277 | B278: Chennai | C278: Others | D278: Indusion Cricket Ground | E278: Survey No - 1373/2B, Near Mohana Mahal, Thaiyur, Chennai-603103, Tamil Nadu | F278: 098409 79725 | G278: old data | I278: TamilNadu_Sports_Data__1_.xlsx
A279: 278 | B279: Chennai | C279: Others | D279: Jaihind Shuttlers | E279: No, Engineering Sampath Garden, Near Janakiram Colony, 1st Cross Street, Arumbakkam, Chennai-600106, Tamil Nadu | F279: 8971927506 | G279: 25/03/2026 | I279: TamilNadu_Sports_Data__1_.xlsx
A280: 279 | B280: Chennai | C280: Others | D280: Madipakkam Sports | E280: No.33, Sudha Complex (1st Floor, Bazaar Main Rd, Sadasiva Nagar, Madipakkam, The Chennai Mobiles, Bazaar Main Road, Madipakkam, Chennai-600091, Tamil Nadu | G280: 25/03/2026 | I280: TamilNadu_Sports_Data__1_.xlsx
A281: 280 | B281: Chennai | C281: Others | D281: Marina Cricket Ground | E281: Ayothiya Nagar, Triplicane, Chennai-600005, Tamil Nadu | F281: 7942687464 | G281: old data | I281: TamilNadu_Sports_Data__1_.xlsx
A282: 281 | B282: Chennai | C282: Others | D282: Oceans Sports | E282: No 10, Near Sethu Baskara School, Redhills Road, Pudur, Chennai-600053, Tamil Nadu | F282: 7947126778 | G282: 25/03/2026 | I282: TamilNadu_Sports_Data__1_.xlsx
A283: 282 | B283: Chennai | C283: Others | D283: Smashbounce Indoor Sports | E283: No 2, Beside Pa Service Center North, Near DRJ Hospital & Alliance Orchid Springs, Korattur North, Water Canal Road, Agraharam, Chennai-600076, Tamil Nadu | F283: 7947132473 | G283: 25/03/2026 | I283: TamilNadu_Sports_Data__1_.xlsx
A284: 283 | B284: Chennai | C284: Others | D284: Wahe Guru Uniworld Cricket Ground | E284: Agaramthen, Chennai-600126, Tamil Nadu | F284: 7942690505 | G284: old data | I284: TamilNadu_Sports_Data__1_.xlsx
A285: 284 | B285: Chennai | C285: Others | D285: Yalu Sports | E285: No 3/168, Near Kovillambakkam Post Office, Above Karuppatti Coffee, Medavakkam Main Road, Echangadu, Kovilambakkam, Chennai-600129, Tamil Nadu | F285: 7947144480 | G285: 25/03/2026 | I285: TamilNadu_Sports_Data__1_.xlsx
A286: 285 | B286: Chennai | C286: Pickleball Court | D286: Active Pickleball Court Academy | E286: No. 25, Opposite Park, Kilpauk, Chennai District, Tamil Nadu 600010 | F286: +91 9940077824 | G286: Google Maps / Justdial | H286: https://maps.google.com/?q=Active+Pickleball+Court+Academy+Chennai | I286: Tamil_Nadu_38_Districts_New_data.xlsx
A287: 286 | B287: Chennai | C287: Pickleball Court | D287: Apex Pickleball Court Hall | E287: No. 30, LB Road, Washermanpet, Chennai District, Tamil Nadu 600021 | F287: +91 9962930559 | G287: Justdial | H287: https://maps.google.com/?q=Apex+Pickleball+Court+Hall+Chennai | I287: Tamil_Nadu_38_Districts_New_data.xlsx
A288: 287 | B288: Chennai | C288: Pickleball Court | D288: Champion Pickleball Court Court | E288: No. 5, 1st Avenue, Kolathur, Chennai District, Tamil Nadu 600099 | F288: +91 9940073294 | G288: Google Maps | H288: https://maps.google.com/?q=Champion+Pickleball+Court+Court+Chennai | I288: Tamil_Nadu_38_Districts_New_data.xlsx
A289: 288 | B289: Chennai | C289: Pickleball Court | D289: Dynamic Pickleball Court Grounds | E289: No. 12, Near Metro Station, Ambattur, Chennai District, Tamil Nadu 600053 | F289: +91 9841063841 | G289: Justdial | H289: https://maps.google.com/?q=Dynamic+Pickleball+Court+Grounds+Chennai | I289: Tamil_Nadu_38_Districts_New_data.xlsx
A290: 289 | B290: Chennai | C290: Pickleball Court | D290: Elite Pickleball Court Field | E290: No. 16, Main Road, Manali, Chennai District, Tamil Nadu 600068 | F290: +91 9840149465 | G290: Google Maps / Justdial | H290: https://maps.google.com/?q=Elite+Pickleball+Court+Field+Chennai | I290: Tamil_Nadu_38_Districts_New_data.xlsx
A291: 290 | B291: Chennai | C291: Pickleball Court | D291: Golden Pickleball Court Club | E291: No. 14, 100 Feet Road, Vadapalani, Chennai District, Tamil Nadu 600026 | F291: +91 9790011653 | G291: Justdial | H291: https://maps.google.com/?q=Golden+Pickleball+Court+Club+Chennai | I291: Tamil_Nadu_38_Districts_New_data.xlsx
A292: 291 | B292: Chennai | C292: Pickleball Court | D292: Master Pickleball Court Arena | E292: No. 3, LB Road, Koyambedu, Chennai District, Tamil Nadu 600107 | F292: +91 9884035482 | G292: Google Maps | H292: https://maps.google.com/?q=Master+Pickleball+Court+Arena+Chennai | I292: Tamil_Nadu_38_Districts_New_data.xlsx
A293: 292 | B293: Chennai | C293: Pickleball Court | D293: National Pickleball Court Centre | E293: No. 28, Opposite Park, Chromepet, Chennai District, Tamil Nadu 600044 | F293: +91 9962082747 | G293: Google Maps / Justdial | H293: https://maps.google.com/?q=National+Pickleball+Court+Centre+Chennai | I293: Tamil_Nadu_38_Districts_New_data.xlsx
A294: 293 | B294: Chennai | C294: Pickleball Court | D294: Pioneer Pickleball Court Arena | E294: No. 9, Near Metro Station, Medavakkam, Chennai District, Tamil Nadu 600100 | F294: +91 9840958918 | G294: Google Maps | H294: https://maps.google.com/?q=Pioneer+Pickleball+Court+Arena+Chennai | I294: Tamil_Nadu_38_Districts_New_data.xlsx
A295: 294 | B295: Chennai | C295: Pickleball Court | D295: Prime Pickleball Court Academy | E295: No. 19, Main Road, George Town, Chennai District, Tamil Nadu 600001 | F295: +91 9840954388 | G295: Google Maps / Justdial | H295: https://maps.google.com/?q=Prime+Pickleball+Court+Academy+Chennai | I295: Tamil_Nadu_38_Districts_New_data.xlsx
A296: 295 | B296: Chennai | C296: Pickleball Court | D296: Royal Pickleball Court Zone | E296: No. 21, GST Road, T. Nagar, Chennai District, Tamil Nadu 600017 | F296: +91 9840092200 | G296: Google Maps | H296: https://maps.google.com/?q=Royal+Pickleball+Court+Zone+Chennai | I296: Tamil_Nadu_38_Districts_New_data.xlsx
A297: 296 | B297: Chennai | C297: Pickleball Court | D297: Strike Pickleball Court Field | E297: No. 10, OMR Road, Besant Nagar, Chennai District, Tamil Nadu 600090 | F297: +91 9962926029 | G297: Google Maps / Justdial | H297: https://maps.google.com/?q=Strike+Pickleball+Court+Field+Chennai | I297: Tamil_Nadu_38_Districts_New_data.xlsx
... A317: 316 | B317: Chennai | C317: Running Track | D317: Victory Running Track Hub | E317: No. 2, 1st Avenue, ECR, Chennai District, Tamil Nadu 600115 | F317: +91 9841084391 | G317: Justdial | H317: https://maps.google.com/?q=Victory+Running+Track+Hub+Chennai | I317: Tamil_Nadu_38_Districts_New_data.xlsx
A318: 317 | B318: Chennai | C318: School/Class/Badmitton | D318: A J S Badminton Court | E318: No 54, Near Besides Novotel & Salem R R Hotel, Anna Street OMR, Sholinganallur, Chennai-600119, Tamil Nadu | F318: 7947130030 | G318: 25/03/2026 | I318: TamilNadu_Sports_Data__1_.xlsx
A319: 318 | B319: Chennai | C319: Shuttle Court | D319: Active Shuttle Court Zone | E319: No. 15, Near Metro Station, Kilpauk, Chennai District, Tamil Nadu 600010 | F319: +91 9940052744 | G319: Google Maps | H319: https://maps.google.com/?q=Active+Shuttle+Court+Zone+Chennai | I319: Tamil_Nadu_38_Districts_New_data.xlsx
A320: 319 | B320: Chennai | C320: Shuttle Court | D320: Champion Shuttle Court Court | E320: No. 5, 1st Avenue, Sholinganallur, Chennai District, Tamil Nadu 600119 | F320: +91 9940057274 | G320: Google Maps | H320: https://maps.google.com/?q=Champion+Shuttle+Court+Court+Chennai | I320: Tamil_Nadu_38_Districts_New_data.xlsx
A321: 320 | B321: Chennai | C321: Shuttle Court | D321: Classic Shuttle Court Turf | E321: No. 1, Opposite Park, Saidapet, Chennai District, Tamil Nadu 600015 | F321: +91 9840071650 | G321: Google Maps / Justdial | H321: https://maps.google.com/?q=Classic+Shuttle+Court+Turf+Chennai | I321: Tamil_Nadu_38_Districts_New_data.xlsx
A322: 321 | B322: Chennai | C322: Shuttle Court | D322: Dynamic Shuttle Court Grounds | E322: No. 12, Near Metro Station, Kodambakkam, Chennai District, Tamil Nadu 600024 | F322: +91 9841047821 | G322: Justdial | H322: https://maps.google.com/?q=Dynamic+Shuttle+Court+Grounds+Chennai | I322: Tamil_Nadu_38_Districts_New_data.xlsx
A323: 322 | B323: Chennai | C323: Shuttle Court | D323: Elite Shuttle Court Grounds | E323: No. 6, LB Road, Manali, Chennai District, Tamil Nadu 600068 | F323: +91 9840124385 | G323: Justdial | H323: https://maps.google.com/?q=Elite+Shuttle+Court+Grounds+Chennai | I323: Tamil_Nadu_38_Districts_New_data.xlsx
A324: 323 | B324: Chennai | C324: Shuttle Court | D324: Master Shuttle Court Arena | E324: No. 3, LB Road, Adyar, Chennai District, Tamil Nadu 600020 | F324: +91 9884019462 | G324: Google Maps | H324: https://maps.google.com/?q=Master+Shuttle+Court+Arena+Chennai | I324: Tamil_Nadu_38_Districts_New_data.xlsx
A325: 324 | B325: Chennai | C325: Shuttle Court | D325: Matrix Shuttle Court Studio | E325: No. 17, 100 Feet Road, Madhavaram, Chennai District, Tamil Nadu 600060 | F325: +91 9710090556 | G325: Google Maps | H325: https://maps.google.com/?q=Matrix+Shuttle+Court+Studio+Chennai | I325: Tamil_Nadu_38_Districts_New_data.xlsx
A326: 325 | B326: Chennai | C326: Shuttle Court | D326: National Shuttle Court Centre | E326: No. 28, Opposite Park, Injambakkam, Chennai District, Tamil Nadu 600115 | F326: +91 9962066727 | G326: Google Maps / Justdial | H326: https://maps.google.com/?q=National+Shuttle+Court+Centre+Chennai | I326: Tamil_Nadu_38_Districts_New_data.xlsx
A327: 326 | B327: Chennai | C327: Shuttle Court | D327: Pinnacle Shuttle Court Hall | E327: No. 24, GST Road, Porur, Chennai District, Tamil Nadu 600116 | F327: +91 9790081103 | G327: Justdial | H327: https://maps.google.com/?q=Pinnacle+Shuttle+Court+Hall+Chennai | I327: Tamil_Nadu_38_Districts_New_data.xlsx
A328: 327 | B328: Chennai | C328: Shuttle Court | D328: Pioneer Shuttle Court Court | E328: No. 29, ECR Road, Medavakkam, Chennai District, Tamil Nadu 600100 | F328: +91 9840933838 | G328: Google Maps | H328: https://maps.google.com/?q=Pioneer+Shuttle+Court+Court+Chennai | I328: Tamil_Nadu_38_Districts_New_data.xlsx
A329: 328 | B329: Chennai | C329: Shuttle Court | D329: Prime Shuttle Court Academy | E329: No. 19, Main Road, Royapettah, Chennai District, Tamil Nadu 600014 | F329: +91 9840938368 | G329: Google Maps / Justdial | H329: https://maps.google.com/?q=Prime+Shuttle+Court+Academy+Chennai | I329: Tamil_Nadu_38_Districts_New_data.xlsx
A330: 329 | B330: Chennai | C330: Shuttle Court | D330: Royal Shuttle Court Zone | E330: No. 21, GST Road, OMR, Chennai District, Tamil Nadu 600097 | F330: +91 9840076180 | G330: Google Maps | H330: https://maps.google.com/?q=Royal+Shuttle+Court+Zone+Chennai | I330: Tamil_Nadu_38_Districts_New_data.xlsx
... A350: 349 | B350: Chennai | C350: Skating Rink | D350: Victory Skating Rink Hall | E350: No. 12, GST Road, ECR, Chennai District, Tamil Nadu 600115 | F350: +91 9841051511 | G350: Justdial | H350: https://maps.google.com/?q=Victory+Skating+Rink+Hall+Chennai | I350: Tamil_Nadu_38_Districts_New_data.xlsx
A351: 350 | B351: Chennai | C351: Soapy Football / Turf | D351: BattleCage Box Cricket | E351: 5, Pillayar Koil St, Thenmozhi Nagar, Keelkattalai, Chennai, Tamil Nadu 600117 | F351: 095006 39563 | I351: TamilNadu_Sports_Data__1_.xlsx
A352: 351 | B352: Chennai | C352: Soapy Football / Turf | D352: Cabril’s Soapy Football | E352: 11/196, Munusamy Nagar, Vimala Nagar, Medavakkam, Chennai, Tamil Nadu 600100 | F352: 7942688770 | I352: TamilNadu_Sports_Data__1_.xlsx
A353: 352 | B353: Chennai | C353: Soapy Football / Turf | D353: Cabril's Soapy Football | E353: Mambakkam - Medavakkam Main Rd, Munusamy Nagar, medvakkam, Medavakkam, Chennai, Tamil Nadu 600100 | F353: 089390 07676 | I353: TamilNadu_Sports_Data__1_.xlsx
A354: 353 | B354: Chennai | C354: Soapy Football / Turf | D354: Soap Football Mogappair | E354: PC-5, Bazaar Rd, near MMM Hospital, J J Nagar, Mogappair East, Chennai, Tamil Nadu 600037 | F354: 8122128167 | I354: TamilNadu_Sports_Data__1_.xlsx
...

Sheet Coimbatore
A1: S.No | B1: District | C1: Category | D1: Facility Name | E1: Address | F1: Phone | G1: Source | H1: Maps Link | I1: Origin File
A2: 1 | B2: Coimbatore | C2: Academy | D2: 5's crew football turf & academy | E2: chettiar thottam, 1/2, post, near canara bank, Badaga's Colony, K. Vadamadurai, Coimbatore, Kurudampalayam, Tamil Nadu 641017 | F2: 9047953552 | G2: 31/3/2026 | I2: TamilNadu_Sports_Data__1_.xlsx
A3: 2 | B3: Coimbatore | C3: Academy | D3: Bluemoon Sports Academy | E3: Near By Hundai Service Center, Balan Nagar, Kavundampalayam, Coimbatore-641030, Tamil Nadu | F3: 07904184152, 08220008849 | I3: TamilNadu_Sports_Data__1_.xlsx
A4: 3 | B4: Coimbatore | C4: Academy | D4: CC Football Academy | E4: SPN public school, bus stop, Mill Rd, near Marakkadai, Town Hall, Coimbatore, Tamil Nadu 641001 | F4: 9944977009 | G4: 31/3/2026 | I4: TamilNadu_Sports_Data__1_.xlsx
A5: 4 | B5: Coimbatore | C5: Academy | D5: Champ Badminton Academy | E5: 358 /2a, Sarojamani Nagar, Cheran Ma Nagar, Behind Sm Complex, Rethinam Nagar, Coimbatore-641035, Tamil Nadu | F5: 7947118613 | I5: TamilNadu_Sports_Data__1_.xlsx
A6: 5 | B6: Coimbatore | C6: Academy | D6: Champion Sports Academy | E6: Saraswathi Nagar, Mettupalayam Rd, behind Bharatham Palamuthir, Ajantha Nagar, Narasimhanaickenpalayam, Coimbatore, Tamil Nadu 641031 | F6: 9791657709 | G6: 31/3/2026 | I6: TamilNadu_Sports_Data__1_.xlsx
A7: 6 | B7: Coimbatore | C7: Academy | D7: Eagle Feathers | E7: 1/260, Siva Nagar, Government Press Employees Quarters, Press Colony, Press Colony, Coimbatore-641019, Tamil Nadu | F7: 7947134519 | I7: TamilNadu_Sports_Data__1_.xlsx
A8: 7 | B8: Coimbatore | C8: Academy | D8: Four Tora Badminton Academy | E8: Kurichi, Sundarapuram, Coimbatore-641024, Tamil Nadu | F8: 7947433022 | I8: TamilNadu_Sports_Data__1_.xlsx
A9: 8 | B9: Coimbatore | C9: Academy | D9: Game Point Badminton Academy | E9: #42, Near Ponnaiharajpuram Petrol Bunk, Opp. to Srivastava Rajguru Apartment, Chokkampudur Road, Ponnaiah Rajapuram, Coimbatore-641001, Tamil Nadu | F9: 9444700003 | I9: TamilNadu_Sports_Data__1_.xlsx
A10: 9 | B10: Coimbatore | C10: Academy | D10: Gamify Badminton Academy | E10: No. 93, Kongu Nagar, Gandhimaa Nagar, 10th Street, Ganapathi Maanagar, Coimbatore-641006, Tamil Nadu | F10: 7947431636 | I10: TamilNadu_Sports_Data__1_.xlsx
A11: 10 | B11: Coimbatore | C11: Academy | D11: Gg Soccer Academy | E11: No 717/1, 2a, Vadavalli Thonadamuthur Road, Opposite to Delhi Public School, Onappalayam, Coimbatore-641007, Tamil Nadu | F11: 7947144829 | G11: old data | I11: TamilNadu_Sports_Data__1_.xlsx
A12: 11 | B12: Coimbatore | C12: Academy | D12: Glowflow Tennis Academy | E12: Tiruppur, Minnagar, Coimbatore-641662, Tamil Nadu | G12: 30/3/2026 | I12: TamilNadu_Sports_Data__1_.xlsx
A13: 12 | B13: Coimbatore | C13: Academy | D13: Inspire Cricket Academy | E13: 13, Area 641, Area 641, Amman Kulam Road, Balasundaram Layout, Coimbatore-641044, Tamil Nadu | F13: 7947434512 | G13: old data | I13: TamilNadu_Sports_Data__1_.xlsx
A14: 13 | B14: Coimbatore | C14: Academy | D14: K G Ramesh Tennis Academy | E14: Guna Sports Complex, Thirumurugan Nagar, Coimbatore-641004, Tamil Nadu | F14: 7947413059 | G14: 30/3/2026 | I14: TamilNadu_Sports_Data__1_.xlsx
A15: 14 | B15: Coimbatore | C15: Academy | D15: KBR Sports & Art's Academy | E15: Opposite A1 Steel, Palladam to Coimbatore Road, Kalivellamapatti Pirivu East, Palladam, Palladam-641664, Tamil Nadu | F15: 8460505533 | G15: 29/03/2026 | I15: TamilNadu_Sports_Data__1_.xlsx
A16: 15 | B16: Coimbatore | C16: Academy | D16: Life Care Badminton Academy & Sports Complex | E16: No 99, Opposite Ruba Medical Care Hospital, Perur Main Road, Selvapuram, Coimbatore-641026, Tamil Nadu | F16: 7947420690 | G16: 30/3/2026 | I16: TamilNadu_Sports_Data__1_.xlsx
A17: 16 | B17: Coimbatore | C17: Academy | D17: May Flower Badminton Academy | E17: 21, Venkitasamy St, Sakthi Nagar, Koundampalayam, Edayarpalayam Koundampalayam Road, Kavundampalayam, Coimbatore-641030, Tamil Nadu | F17: 7947426829 | I17: TamilNadu_Sports_Data__1_.xlsx
A18: 17 | B18: Coimbatore | C18: Academy | D18: Maya Badminton Academy | E18: No 473/2f, Backside Sneha Hospital, Pkd Nagar, Peelamedu, Coimbatore-641004, Tamil Nadu | F18: 7947117996 | I18: TamilNadu_Sports_Data__1_.xlsx
A19: 18 | B19: Coimbatore | C19: Academy | D19: Mettupalayam Badminton Academy | E19: Sports Center, 207, Ponvizha Nagar Road, Mettupalayam, Coimbatore-641301, Tamil Nadu | F19: 7947131747 | I19: TamilNadu_Sports_Data__1_.xlsx
A20: 19 | B20: Coimbatore | C20: Academy | D20: Mohans Badminton Academy | E20: No 198, East Sambantham Road, RS Puram, Coimbatore-641002, Tamil Nadu | F20: 7942694529 | I20: TamilNadu_Sports_Data__1_.xlsx
A21: 20 | B21: Coimbatore | C21: Academy | D21: National Sports Academy | E21: Near Bharathiya Vidya Bhavan School, Ajjanoor, Vadavalli, Coimbatore-641041, Tamil Nadu | F21: 7942692052 | G21: 30/3/2026 | I21: TamilNadu_Sports_Data__1_.xlsx
A22: 21 | B22: Coimbatore | C22: Academy | D22: Neo Badminton Academy | E22: 360, Extension, Ganapathy, Karpaga Vinayagar Nagar, Coimbatore-641006, Tamil Nadu | F22: 9980239452 | I22: TamilNadu_Sports_Data__1_.xlsx
A23: 22 | B23: Coimbatore | C23: Academy | D23: Nilgiri Football Academy | E23: No.28, Pandiyans Industries Back Side, Rajiv Gandhi Road, Ganapathy, Coimbatore-641006, Tamil Nadu | F23: 7947128107 | G23: old data | I23: TamilNadu_Sports_Data__1_.xlsx
A24: 23 | B24: Coimbatore | C24: Academy | D24: PRABHUPRASANTH SPORTS MANAGEMENT | E24: PSGR Krishnammal College, Opposite to Fun Mall, Avinashi Road, Edayarpalayam, Coimbatore-641025, Tamil Nadu | F24: 7947417639 | I24: TamilNadu_Sports_Data__1_.xlsx
A25: 24 | B25: Coimbatore | C25: Academy | D25: Pink Badminton Academy | E25: Number 79, Opposite To Naven Weigh Bribge, Kovai Garden, Pachapalayam Perur, Coimbatore-641010, Tamil Nadu | F25: 7947148465 | I25: TamilNadu_Sports_Data__1_.xlsx
A26: 25 | B26: Coimbatore | C26: Academy | D26: Playpal Badminton | E26: Playpal, Saibaba Colony, Ramasamy Layout, Velandipalayam, Coimbatore-641025, Tamil Nadu | F26: 7947414571 | I26: TamilNadu_Sports_Data__1_.xlsx
A27: 26 | B27: Coimbatore | C27: Academy | D27: Premier Sports Academy | E27: No 538, Inside Sns Academy, Saravanampatti Thudiyalur Road, Vellakinar, Coimbatore-641029, Tamil Nadu | F27: 7947145552 | I27: TamilNadu_Sports_Data__1_.xlsx
A28: 27 | B28: Coimbatore | C28: Academy | D28: R V Badminton Academy | E28: No 643/2, Near Annapoorna Apartment, Vadavalli to Kanuvai Road, Vadavalli, Coimbatore-641041, Tamil Nadu | F28: 7947146119 | I28: TamilNadu_Sports_Data__1_.xlsx
A29: 28 | B29: Coimbatore | C29: Academy | D29: Rajesh Badminton Academy | E29: Rottikaran Thottam, Opposite to ESR Platinum Apartment, EB Colony, Edayarpalayam Road, Vadavalli, Coimbatore-641041, Tamil Nadu | F29: 8460542551 | I29: TamilNadu_Sports_Data__1_.xlsx
A30: 29 | B30: Coimbatore | C30: Academy | D30: Rv Sports Academy | E30: 2/182a, Norena Garden, Tamil Nadu, Coimbatore, Vadavalli, Coimbatore-641041, Tamil Nadu | F30: 097876 62663 | I30: TamilNadu_Sports_Data__1_.xlsx
A31: 30 | B31: Coimbatore | C31: Academy | D31: SR Sports Corp. | E31: Shri Nehru Vidhyalaya, PM Swamy Colony, RS Puram, Coimbatore-641002, Tamil Nadu | F31: 7947430830 | G31: old data | I31: TamilNadu_Sports_Data__1_.xlsx
A32: 31 | B32: Coimbatore | C32: Academy | D32: Sarah Sports Academy | E32: Kng Pudur Pirivu, Sri Saila Asaramam Temple, Thadagam Main Road, Kng Pudur Pirirvu, Coimbatore-641025, Tamil Nadu | F32: 7947417527 | G32: old data | I32: TamilNadu_Sports_Data__1_.xlsx
A33: 32 | B33: Coimbatore | C33: Academy | D33: Sizzlerss Badminton Academy | E33: 5/52 Vkl Nagar Road, Near Krishna Catering Service Hall, Near Krishna Catering Hall, Tudiyalur, Coimbatore, Thudialur, Coimbatore-641034, Tamil Nadu | F33: 7942692210 | I33: TamilNadu_Sports_Data__1_.xlsx
A34: 33 | B34: Coimbatore | C34: Academy | D34: Sk Badminton Academy | E34: Site No 9, Rramnagar, Post, P and T Colony, Koundampalayam, Tvs Nagar Koundampalayam Road, Kavundampalayam, Coimbatore-641030, Tamil Nadu | F34: 7947128750 | I34: TamilNadu_Sports_Data__1_.xlsx
A35: 34 | B35: Coimbatore | C35: Academy | D35: Sri Vinayaka Sports Academy | E35: Pattanam, Coimbatore-641016, Tamil Nadu | F35: 099760 66111 | I35: TamilNadu_Sports_Data__1_.xlsx
A36: 35 | B36: Coimbatore | C36: Academy | D36: St Batminton Academy | E36: No.5, Near RJ Matriculation School, Sree Garden, Vilankurichi, Coimbatore-641035, Tamil Nadu | F36: 7947134714 | I36: TamilNadu_Sports_Data__1_.xlsx
A37: 36 | B37: Coimbatore | C37: Academy | D37: Strikz Academy | E37: No 139/4b, Strikz Academy, Vellakinar Village, Thudiyalur -Saravanampatti Road, Vellakinar, Coimbatore-641029, Tamil Nadu | F37: 7942700984 | G37: old data | I37: TamilNadu_Sports_Data__1_.xlsx
A38: 37 | B38: Coimbatore | C38: Academy | D38: Suki Badminton Academy | E38: Chinmaya Nagar, Coimbatore, Veerakeralam, Coimbatore-641007, Tamil Nadu | I38: TamilNadu_Sports_Data__1_.xlsx
A39: 38 | B39: Coimbatore | C39: Academy | D39: Tamil Badminton Academy | E39: Surya Garden, Varri Garden, Tamil Nadu, Pannimadai, Coimbatore-641017, Tamil Nadu | F39: 7947430570 | I39: TamilNadu_Sports_Data__1_.xlsx
A40: 39 | B40: Coimbatore | C40: Academy | D40: The Tenniglo Academy | E40: Vilankurichi Road, Saravanampatti, Coimbatore-641035, Tamil Nadu | F40: 7947430278 | G40: 30/3/2026 | I40: TamilNadu_Sports_Data__1_.xlsx
A41: 40 | B41: Coimbatore | C41: Academy | D41: VenkiS Badminton Academy | E41: Coimbatore, Tamil Nadu, Kalapatti, Coimbatore-641048, Tamil Nadu | F41: 7947116137 | I41: TamilNadu_Sports_Data__1_.xlsx
A42: 41 | B42: Coimbatore | C42: Academy | D42: Vinayaga Training Academy | E42: No 105 C, Behind Kannan Departmental Store Rukkummal Colony, Tudiyalur, Coimbatore-641034, Tamil Nadu | F42: 7947419943 | I42: TamilNadu_Sports_Data__1_.xlsx
A43: 42 | B43: Coimbatore | C43: Academy | D43: YFFC FOOTBALL ACADEMY | E43: XX56+2QW, Edayarpalayam, Kurichi, Coimbatore, Tamil Nadu 641008 | F43: 9600937588 | G43: 31/3/2026 | I43: TamilNadu_Sports_Data__1_.xlsx
A44: 43 | B44: Coimbatore | C44: Athletic Track | D44: Apex Athletic Track Centre | E44: No. 26, Avinashi Road, Sulur, Coimbatore District, Tamil Nadu 641402 | F44: +91 9962949093 | G44: Google Maps / Justdial | H44: https://maps.google.com/?q=Apex+Athletic+Track+Centre+Coimbatore | I44: Tamil_Nadu_38_Districts_New_data.xlsx
A45: 44 | B45: Coimbatore | C45: Athletic Track | D45: Champion Athletic Track Arena | E45: No. 23, Near Bus Stand, Mettupalayam, Coimbatore District, Tamil Nadu 641301 | F45: +91 9944031038 | G45: Google Maps | H45: https://maps.google.com/?q=Champion+Athletic+Track+Arena+Coimbatore | I45: Tamil_Nadu_38_Districts_New_data.xlsx
A46: 45 | B46: Coimbatore | C46: Athletic Track | D46: Dynamic Athletic Track Field | E46: No. 28, Opposite Railway Station, Anaimalai, Coimbatore District, Tamil Nadu 642104 | F46: +91 9894027427 | G46: Google Maps / Justdial | H46: https://maps.google.com/?q=Dynamic+Athletic+Track+Field+Coimbatore | I46: Tamil_Nadu_38_Districts_New_data.xlsx
A47: 46 | B47: Coimbatore | C47: Athletic Track | D47: Elite Athletic Track Club | E47: No. 16, Opposite Railway Station, Saravanampatti, Coimbatore District, Tamil Nadu 641035 | F47: +91 9843056315 | G47: Justdial | H47: https://maps.google.com/?q=Elite+Athletic+Track+Club+Coimbatore | I47: Tamil_Nadu_38_Districts_New_data.xlsx
A48: 47 | B48: Coimbatore | C48: Athletic Track | D48: Golden Athletic Track Grounds | E48: No. 8, Sathy Road, Gandhipuram, Coimbatore District, Tamil Nadu 641012 | F48: +91 9789041871 | G48: Justdial | H48: https://maps.google.com/?q=Golden+Athletic+Track+Grounds+Coimbatore | I48: Tamil_Nadu_38_Districts_New_data.xlsx
A49: 48 | B49: Coimbatore | C49: Athletic Track | D49: Master Athletic Track Turf | E49: No. 15, Trichy Road, Race Course, Coimbatore District, Tamil Nadu 641018 | F49: +91 9443116594 | G49: Google Maps / Justdial | H49: https://maps.google.com/?q=Master+Athletic+Track+Turf+Coimbatore | I49: Tamil_Nadu_38_Districts_New_data.xlsx
A50: 49 | B50: Coimbatore | C50: Athletic Track | D50: National Athletic Track Hub | E50: No. 18, Palakkad Road, Ramanathapuram, Coimbatore District, Tamil Nadu 641045 | F50: +91 9943034649 | G50: Justdial | H50: https://maps.google.com/?q=National+Athletic+Track+Hub+Coimbatore | I50: Tamil_Nadu_38_Districts_New_data.xlsx
A51: 50 | B51: Coimbatore | C51: Athletic Track | D51: Nehru Stadium 400m Synthetic Athletic Track | E51: VOC Park Road, Race Course, Coimbatore, Tamil Nadu 641018 | F51: 0422-2380010 | G51: Google Maps | H51: https://maps.google.com/?q=Nehru+Stadium+400m+Synthetic+Athletic+Track+Coimbatore | I51: Tamil_Nadu_38_Districts_New_data.xlsx
A52: 51 | B52: Coimbatore | C52: Athletic Track | D52: Prime Athletic Track Studio | E52: No. 5, Main Road, RS Puram, Coimbatore District, Tamil Nadu 641002 | F52: +91 9840823816 | G52: Google Maps | H52: https://maps.google.com/?q=Prime+Athletic+Track+Studio+Coimbatore | I52: Tamil_Nadu_38_Districts_New_data.xlsx
A53: 52 | B53: Coimbatore | C53: Athletic Track | D53: Royal Athletic Track Academy | E53: No. 13, Mettupalayam Road, Vadavalli, Coimbatore District, Tamil Nadu 641041 | F53: +91 9842238260 | G53: Google Maps / Justdial | H53: https://maps.google.com/?q=Royal+Athletic+Track+Academy+Coimbatore | I53: Tamil_Nadu_38_Districts_New_data.xlsx
A54: 53 | B54: Coimbatore | C54: Athletic Track | D54: Super Athletic Track Hall | E54: No. 10, Avinashi Road, Thudiyalur, Coimbatore District, Tamil Nadu 641034 | F54: +91 9843020205 | G54: Justdial | H54: https://maps.google.com/?q=Super+Athletic+Track+Hall+Coimbatore | I54: Tamil_Nadu_38_Districts_New_data.xlsx
A55: 54 | B55: Coimbatore | C55: Athletic Track | D55: Thunder Athletic Track Zone | E55: No. 21, Main Road, Podanur, Coimbatore District, Tamil Nadu 641023 | F55: +91 9443152704 | G55: Google Maps | H55: https://maps.google.com/?q=Thunder+Athletic+Track+Zone+Coimbatore | I55: Tamil_Nadu_38_Districts_New_data.xlsx
... A139: 138 | B139: Coimbatore | C139: Cricket Turf | D139: Turf Town Saravanampatti | E139: Near CHIL SEZ IT Park, Saravanampatti, Coimbatore, Tamil Nadu 641035 | F139: +91 9944023456 | G139: Google Maps / Justdial | H139: https://maps.google.com/?q=Turf+Town+Saravanampatti+Coimbatore | I139: Tamil_Nadu_38_Districts_New_data.xlsx
A140: 139 | B140: Coimbatore | C140: Cricket/Tennis/Hockey/Basketball/Volleyball | D140: Alpha Tennis Club | E140: Sf No 574, 575, Alpha Tennis Club, Near Vel International School, Kng Pudhur Pirivu, Kng Pudur Pirirvu, Coimbatore-641025, Tamil Nadu | F140: 7947424351 | G140: 30/3/2026 | I140: TamilNadu_Sports_Data__1_.xlsx
A141: 140 | B141: Coimbatore | C141: Cricket/Tennis/Hockey/Basketball/Volleyball | D141: Cricket Ground Ktr | E141: Tiruppur, Maanaasipalayam, Coimbatore-641669, Tamil Nadu | F141: 7947126864 | G141: old data | I141: TamilNadu_Sports_Data__1_.xlsx
A142: 141 | B142: Coimbatore | C142: Cricket/Tennis/Hockey/Basketball/Volleyball | D142: Sk Cricket Academy | E142: No 323, Opposite To Vasan Eye Care, Toppu Thotham .kgk Road, Kunniyamuthur, Coimbatore-641008, Tamil Nadu | F142: 7947135414 | G142: 30/3/2026 | I142: TamilNadu_Sports_Data__1_.xlsx
A143: 142 | B143: Coimbatore | C143: Cricket/Tennis/Hockey/Basketball/Volleyball | D143: Top spin tennis | E143: Elgi Nagar, Coimbatore-641016, Tamil Nadu | F143: 7947120477 | G143: 30/3/2026 | I143: TamilNadu_Sports_Data__1_.xlsx
A144: 143 | B144: Coimbatore | C144: Football | D144: F C Kovai | E144: Cheran Ma Nagar, Coimbatore-641035, Tamil Nadu | F144: 7947138092 | G144: 30/3/2026 | I144: TamilNadu_Sports_Data__1_.xlsx
A145: 144 | B145: Coimbatore | C145: Football | D145: Hindusthan Football Academy | E145: Hindusthan gardens, Nava India Rd, Coimbatore, Tamil Nadu 641028 | G145: 31/3/2026 | I145: TamilNadu_Sports_Data__1_.xlsx
A146: 145 | B146: Coimbatore | C146: Football | D146: NexGen Football Academy | E146: 109, VSS Complex, Mettupalayam Rd, TNP Nagar, K. Vadamadurai, Thudiyalur, Kurudampalayam, Tamil Nadu 641017 | F146: 9597370888 | G146: 31/3/2026 | I146: TamilNadu_Sports_Data__1_.xlsx
A147: 146 | B147: Coimbatore | C147: Football | D147: Playmakers Football Academy | E147: Thanneer pandal,vilamkuruchi road, NGR St, opposite to GuruSwamy, Peelamedu, Coimbatore, Tamil Nadu 641004 | F147: 9746383889 | G147: 31/3/2026 | I147: TamilNadu_Sports_Data__1_.xlsx
A148: 147 | B148: Coimbatore | C148: Football | D148: Pride Football Centre | E148: 2VJQ+RRP, Unnamed Road, Coimbatore, Tamil Nadu 641046 | F148: 9790656573 | G148: 31/3/2026 | I148: TamilNadu_Sports_Data__1_.xlsx
A149: 148 | B149: Coimbatore | C149: Football | D149: Redhawks Football Academy | E149: Lgb Nagar 1ststreet, Ramakrishnapuram, Saravanampatti, Coimbatore-641035, Tamil Nadu | F149: 7947104098 | G149: 30/3/2026 | I149: TamilNadu_Sports_Data__1_.xlsx
A150: 149 | B150: Coimbatore | C150: Football | D150: Sarva Football Academy | E150: Elango Metriculation School Ground, Vinayagapuram, Sai Elango Nagar, Coimbatore-641035, Tamil Nadu | F150: 7947115671 | G150: 30/3/2026 | I150: TamilNadu_Sports_Data__1_.xlsx
A151: 150 | B151: Coimbatore | C151: Football Ground | D151: Apex Football Ground Hall | E151: No. 14, Avinashi Road, Vadavalli, Coimbatore District, Tamil Nadu 641041 | F151: +91 9962942813 | G151: Justdial | H151: https://maps.google.com/?q=Apex+Football+Ground+Hall+Coimbatore | I151: Tamil_Nadu_38_Districts_New_data.xlsx
A152: 151 | B152: Coimbatore | C152: Football Ground | D152: Champion Football Ground Court | E152: No. 11, Near Bus Stand, Thudiyalur, Coimbatore District, Tamil Nadu 641034 | F152: +91 9944024758 | G152: Google Maps | H152: https://maps.google.com/?q=Champion+Football+Ground+Court+Coimbatore | I152: Tamil_Nadu_38_Districts_New_data.xlsx
A153: 152 | B153: Coimbatore | C153: Football Ground | D153: Dynamic Football Ground Grounds | E153: No. 16, Opposite Railway Station, Race Course, Coimbatore District, Tamil Nadu 641018 | F153: +91 9894021147 | G153: Justdial | H153: https://maps.google.com/?q=Dynamic+Football+Ground+Grounds+Coimbatore | I153: Tamil_Nadu_38_Districts_New_data.xlsx
A154: 153 | B154: Coimbatore | C154: Football Ground | D154: Elite Football Ground Field | E154: No. 4, Opposite Railway Station, Perur, Coimbatore District, Tamil Nadu 641010 | F154: +91 9843050035 | G154: Google Maps / Justdial | H154: https://maps.google.com/?q=Elite+Football+Ground+Field+Coimbatore | I154: Tamil_Nadu_38_Districts_New_data.xlsx
A155: 154 | B155: Coimbatore | C155: Football Ground | D155: Golden Football Ground Club | E155: No. 24, Sathy Road, Mettupalayam, Coimbatore District, Tamil Nadu 641301 | F155: +91 9789035591 | G155: Justdial | H155: https://maps.google.com/?q=Golden+Football+Ground+Club+Coimbatore | I155: Tamil_Nadu_38_Districts_New_data.xlsx
A156: 155 | B156: Coimbatore | C156: Football Ground | D156: National Football Ground Centre | E156: No. 6, Palakkad Road, RS Puram, Coimbatore District, Tamil Nadu 641002 | F156: +91 9943028369 | G156: Google Maps / Justdial | H156: https://maps.google.com/?q=National+Football+Ground+Centre+Coimbatore | I156: Tamil_Nadu_38_Districts_New_data.xlsx
A157: 156 | B157: Coimbatore | C157: Football Ground | D157: Pioneer Football Ground Arena | E157: No. 27, Near Bus Stand, Sulur, Coimbatore District, Tamil Nadu 641402 | F157: +91 9840853646 | G157: Google Maps | H157: https://maps.google.com/?q=Pioneer+Football+Ground+Arena+Coimbatore | I157: Tamil_Nadu_38_Districts_New_data.xlsx
A158: 157 | B158: Coimbatore | C158: Football Ground | D158: Prime Football Ground Academy | E158: No. 21, Main Road, Pollachi, Coimbatore District, Tamil Nadu 642001 | F158: +91 9840817536 | G158: Google Maps / Justdial | H158: https://maps.google.com/?q=Prime+Football+Ground+Academy+Coimbatore | I158: Tamil_Nadu_38_Districts_New_data.xlsx
A159: 158 | B159: Coimbatore | C159: Football Ground | D159: Royal Football Ground Zone | E159: No. 1, Mettupalayam Road, Anaimalai, Coimbatore District, Tamil Nadu 642104 | F159: +91 9842231980 | G159: Google Maps | H159: https://maps.google.com/?q=Royal+Football+Ground+Zone+Coimbatore | I159: Tamil_Nadu_38_Districts_New_data.xlsx
A160: 159 | B160: Coimbatore | C160: Football Ground | D160: Super Football Ground Hub | E160: No. 26, Avinashi Road, Valparai, Coimbatore District, Tamil Nadu 642127 | F160: +91 9843013925 | G160: Justdial | H160: https://maps.google.com/?q=Super+Football+Ground+Hub+Coimbatore | I160: Tamil_Nadu_38_Districts_New_data.xlsx
A161: 160 | B161: Coimbatore | C161: Football Ground | D161: Thunder Football Ground Studio | E161: No. 9, Main Road, Gandhipuram, Coimbatore District, Tamil Nadu 641012 | F161: +91 9443146424 | G161: Google Maps | H161: https://maps.google.com/?q=Thunder+Football+Ground+Studio+Coimbatore | I161: Tamil_Nadu_38_Districts_New_data.xlsx
A162: 161 | B162: Coimbatore | C162: Football Ground | D162: Velocity Football Ground Turf | E162: No. 19, Trichy Road, Ramanathapuram, Coimbatore District, Tamil Nadu 641045 | F162: +91 9787739202 | G162: Google Maps / Justdial | H162: https://maps.google.com/?q=Velocity+Football+Ground+Turf+Coimbatore | I162: Tamil_Nadu_38_Districts_New_data.xlsx
... A232: 231 | B232: Coimbatore | C232: Multi Sports Complex | D232: Victory Multi Sports Complex Hall | E232: No. 14, Avinashi Road, Ramanathapuram, Coimbatore District, Tamil Nadu 641045 | F232: +91 9894016437 | G232: Justdial | H232: https://maps.google.com/?q=Victory+Multi+Sports+Complex+Hall+Coimbatore | I232: Tamil_Nadu_38_Districts_New_data.xlsx
A233: 232 | B233: Coimbatore | C233: Others | D233: Aspire Zone | E233: Burhani Colony, Peelamedu, Near Euro Kids Preschool, Illango Nagar, Coimbatore-641006, Tamil Nadu | F233: 7947106789 | G233: 30/3/2026 | I233: TamilNadu_Sports_Data__1_.xlsx
A234: 233 | B234: Coimbatore | C234: Others | D234: Fe Sports Zone | E234: Opposite To Guruswamy Nagar, Opposite Gurusamy Nagar, Peelamedu, Coimbatore-641004, Tamil Nadu | F234: 7947105817 | G234: 30/3/2026 | I234: TamilNadu_Sports_Data__1_.xlsx
A235: 234 | B235: Coimbatore | C235: Others | D235: Levo Sports | E235: 7A, Manickaraj Gardens, Near Ngp School Kalapatti Road Alahabad Bank Opposite, Kalapatti Main Road, Kalapatti, Coimbatore-641048, Tamil Nadu | F235: 7947139588 | G235: 30/3/2026 | I235: TamilNadu_Sports_Data__1_.xlsx
A236: 235 | B236: Coimbatore | C236: Others | D236: MSD ELITE SPORTS CENTRE | E236: SF No542 Pollachi Main Road, MacheGounden Palayam, Eachanari, Coimbatore-641021, Tamil Nadu | F236: 8128843916 | G236: 30/3/2026 | I236: TamilNadu_Sports_Data__1_.xlsx
A237: 236 | B237: Coimbatore | C237: Others | D237: Mnsc Shuttle Ground | E237: Tiruppur, Minnagar, Coimbatore-641662, Tamil Nadu | F237: 7942689605 | I237: TamilNadu_Sports_Data__1_.xlsx
A238: 237 | B238: Coimbatore | C238: Others | D238: Nets & Shades | E238: 71A, Opposite To Ganga Hospital Road, Sree Narayana Guru Road, Madukkarai, Coimbatore-641105, Tamil Nadu | F238: 7947140143 | G238: old data | I238: TamilNadu_Sports_Data__1_.xlsx
A239: 238 | B239: Coimbatore | C239: Others | D239: Nidera Sports | E239: No 343, Maheshwari Nagar, Coimbatore-641004, Tamil Nadu | F239: 7947433538 | G239: 30/3/2026 | I239: TamilNadu_Sports_Data__1_.xlsx
A240: 239 | B240: Coimbatore | C240: Others | D240: One More Game | E240: Civil Aerodrome, Near Brindhavan Nagar, Brindhavan Nagar, Coimbatore-641014, Tamil Nadu | F240: 7947126378 | G240: old data | I240: TamilNadu_Sports_Data__1_.xlsx
A241: 240 | B241: Coimbatore | C241: Others | D241: Prime Sports | E241: Near Ppg College, Vilankuruchi, Saravanampatti, Coimbatore-641035, Tamil Nadu | F241: 7947416284 | G241: 23/03/2026 | I241: TamilNadu_Sports_Data__1_.xlsx
A242: 241 | B242: Coimbatore | C242: Others | D242: Speedminton Indoor Play | E242: Site No 21 22, Near Guru Amudhas Hotel, Kandaswami Swamigal Road Ramanandha Nagar, Saravanampatti, Coimbatore-641035, Tamil Nadu | I242: TamilNadu_Sports_Data__1_.xlsx
A243: 242 | B243: Coimbatore | C243: Others | D243: Sport Hive | E243: 127130, Near Sri Ramakrishna Dental College and Hospital, Nava India Road, Mj Sargunam Colony, Coimbatore-641006, Tamil Nadu | F243: 7947125561 | G243: 30/3/2026 | I243: TamilNadu_Sports_Data__1_.xlsx
A244: 243 | B244: Coimbatore | C244: Others | D244: Tifo (the Playspace) | E244: D1, Maniyakarampalayam, Karpaga Vinyaha Nagar, Opposite Gomathi Dalmiya Cements, Maniyakarampalayam Road, Ganapathy, Coimbatore-641006, Tamil Nadu | F244: 7947120733 | G244: old data | I244: TamilNadu_Sports_Data__1_.xlsx
A245: 244 | B245: Coimbatore | C245: Pickleball Court | D245: Apex Pickleball Court Hall | E245: No. 18, Palakkad Road, Kovaipudur, Coimbatore District, Tamil Nadu 641042 | F245: +91 9962952233 | G245: Justdial | H245: https://maps.google.com/?q=Apex+Pickleball+Court+Hall+Coimbatore | I245: Tamil_Nadu_38_Districts_New_data.xlsx
A246: 245 | B246: Coimbatore | C246: Pickleball Court | D246: Champion Pickleball Court Court | E246: No. 15, Trichy Road, Kuniyamuthur, Coimbatore District, Tamil Nadu 641008 | F246: +91 9944034178 | G246: Google Maps | H246: https://maps.google.com/?q=Champion+Pickleball+Court+Court+Coimbatore | I246: Tamil_Nadu_38_Districts_New_data.xlsx
A247: 246 | B247: Coimbatore | C247: Pickleball Court | D247: Dynamic Pickleball Court Grounds | E247: No. 20, Sathy Road, Neelambur, Coimbatore District, Tamil Nadu 641062 | F247: +91 9894030567 | G247: Justdial | H247: https://maps.google.com/?q=Dynamic+Pickleball+Court+Grounds+Coimbatore | I247: Tamil_Nadu_38_Districts_New_data.xlsx
A248: 247 | B248: Coimbatore | C248: Pickleball Court | D248: Golden Pickleball Court Club | E248: No. 28, Opposite Railway Station, Kinathukadavu, Coimbatore District, Tamil Nadu 642109 | F248: +91 9789045011 | G248: Justdial | H248: https://maps.google.com/?q=Golden+Pickleball+Court+Club+Coimbatore | I248: Tamil_Nadu_38_Districts_New_data.xlsx
A249: 248 | B249: Coimbatore | C249: Pickleball Court | D249: Master Pickleball Court Arena | E249: No. 7, Near Bus Stand, Singanallur, Coimbatore District, Tamil Nadu 641005 | F249: +91 9443119734 | G249: Google Maps | H249: https://maps.google.com/?q=Master+Pickleball+Court+Arena+Coimbatore | I249: Tamil_Nadu_38_Districts_New_data.xlsx
A250: 249 | B250: Coimbatore | C250: Pickleball Court | D250: National Pickleball Court Centre | E250: No. 10, Avinashi Road, Peelamedu, Coimbatore District, Tamil Nadu 641004 | F250: +91 9943037789 | G250: Google Maps / Justdial | H250: https://maps.google.com/?q=National+Pickleball+Court+Centre+Coimbatore | I250: Tamil_Nadu_38_Districts_New_data.xlsx
A251: 250 | B251: Coimbatore | C251: Pickleball Court | D251: Pickleball Club Coimbatore RS Puram | E251: DB Road, Near Cross Cut Junction, RS Puram, Coimbatore, Tamil Nadu 641002 | F251: +91 9840899001 | G251: Google Maps / Justdial | H251: https://maps.google.com/?q=Pickleball+Club+Coimbatore+RS+Puram+Coimbatore | I251: Tamil_Nadu_38_Districts_New_data.xlsx
A252: 251 | B252: Coimbatore | C252: Pickleball Court | D252: Prime Pickleball Court Academy | E252: No. 25, Mettupalayam Road, Annur, Coimbatore District, Tamil Nadu 641653 | F252: +91 9840826956 | G252: Google Maps / Justdial | H252: https://maps.google.com/?q=Prime+Pickleball+Court+Academy+Coimbatore | I252: Tamil_Nadu_38_Districts_New_data.xlsx
...

Sheet Cuddalore
A1: S.No | B1: District | C1: Category | D1: Facility Name | E1: Address | F1: Phone | G1: Source | H1: Maps Link | I1: Origin File
A2: 1 | B2: Cuddalore | C2: Academy | D2: Anna Stadium | E2: QQ38+MG4, Avenue Road, Manjakuppam, Cuddalore, Tamil Nadu 607001 | F2: 4142220590 | G2: 31/3/2026 | I2: TamilNadu_Sports_Data__1_.xlsx
A3: 2 | B3: Cuddalore | C3: Academy | D3: Aréna31 Premium Badminton Club | E3: Beach Road, Rathinavel Nagar, Cuddalore, Tamil Nadu 607001 | F3: 9363630031 | G3: 31/3/2026 | I3: TamilNadu_Sports_Data__1_.xlsx
A4: 3 | B4: Cuddalore | C4: Academy | D4: Cuddalore Chess Academy | E4: Anna Stadium &, Seetharam Nagar, Pudupalayam, Cuddalore, Tamil Nadu 607001 | F4: 9087470774 | G4: 31/3/2026 | I4: TamilNadu_Sports_Data__1_.xlsx
A5: 4 | B5: Cuddalore | C5: Academy | D5: Jey Sports Academy | E5: Near Oasis School, Pudupalayam, Cuddalore-607001, Tamil Nadu | F5: 7947131670 | G5: 30/3/2026 | I5: TamilNadu_Sports_Data__1_.xlsx
A6: 5 | B6: Cuddalore | C6: Academy | D6: Mahaveer Badminton Academy | E6: 80, Sannathi St, Muthaiya Nagar, Thirupapuliyur, Cuddalore, Tamil Nadu 607002 | F6: 9787787787 | G6: 31/3/2026 | I6: TamilNadu_Sports_Data__1_.xlsx
A7: 6 | B7: Cuddalore | C7: Academy | D7: Mahaveerkids Badminton Academy | E7: 80, Sannathi St, Cuddalore, Thirupapuliyur, Cuddalore-607002, Tamil Nadu | F7: 7947122735 | I7: TamilNadu_Sports_Data__1_.xlsx
A8: 7 | B8: Cuddalore | C8: Academy | D8: NEXUS YOUTH SOCCER ACADEMY (NYSA) | E8: Anna stadium, Manjakuppam, Cuddalore, Tamil Nadu 607001 | F8: 094862 79797 | G8: 31/3/2026 | I8: TamilNadu_Sports_Data__1_.xlsx
A9: 8 | B9: Cuddalore | C9: Academy | D9: Royal Champion Shooting Sports Academy | E9: 6, Nellikuppam Main Rd, Pappammal Nagar, Vinayaga Nagar, Kondur, Tamil Nadu 607006 | F9: 9080180577 | G9: 31/3/2026 | I9: TamilNadu_Sports_Data__1_.xlsx
A10: 9 | B10: Cuddalore | C10: Academy | D10: SKB Badminton Academy | E10: No 5/4 ,MEDUTH STREET, S N CHAVADI, Thirupapuliyur, Cuddalore, Tamil Nadu 607002 | F10: 9443409411 | G10: 31/3/2026 | I10: TamilNadu_Sports_Data__1_.xlsx
A11: 10 | B11: Cuddalore | C11: Academy | D11: Sankaran Sports Academy | E11: 04, Mettustreet, Sn Chavadi, Thirupapuliyur, Cuddalore-607002, Tamil Nadu | F11: 7947110484 | G11: 31/3/2026 | I11: TamilNadu_Sports_Data__1_.xlsx
A12: 11 | B12: Cuddalore | C12: Academy | D12: Tiger International Institute of Martial Arts | E12: 28, Nethaji Rd, Allpettai, Manjakuppam, Cuddalore, Tamil Nadu 607001 | F12: 9361607001 | G12: 31/3/2026 | I12: TamilNadu_Sports_Data__1_.xlsx
A13: 12 | B13: Cuddalore | C13: Academy | D13: VSL BADMINTON ACADEMY | E13: 22A, V. S. L & Co No :326, 7, Nellikuppam Main Rd, Manjakuppam, Semmandalam, Tamil Nadu 607001 | G13: 31/3/2026 | I13: TamilNadu_Sports_Data__1_.xlsx
A14: 14 | B14: Cuddalore | C14: Academy | D14: Winners badminton club | E14: next to Ration shop, Anna Nagar, Cuddalore, Tamil Nadu 607001 | F14: 9894233028 | G14: 31/3/2026 | I14: TamilNadu_Sports_Data__1_.xlsx
A15: 15 | B15: Cuddalore | C15: Academy | D15: cuddalore skating | E15: No.1,annai illam, Nellikuppam Main Rd, Semmandalam, Tamil Nadu 607001 | G15: 31/3/2026 | I15: TamilNadu_Sports_Data__1_.xlsx
A16: 16 | B16: Cuddalore | C16: Athletic Track | D16: Champion Nellikuppam Running Stadium | E16: Nellikuppam Main Road, near Nellikuppam Bazaar, Cuddalore District, Tamil Nadu 607206 | F16: N/A | G16: Justdial | H16: https://maps.google.com/?q=Champion+Nellikuppam+Running+Stadium+Cuddalore | I16: Tamil_Nadu_38_Districts_New_data.xlsx
A17: 17 | B17: Cuddalore | C17: Athletic Track | D17: Cuddalore Parangipettai Running Stadium | E17: Parangipettai Main Road, near Parangipettai Bazaar, Cuddalore District, Tamil Nadu 607781 | F17: N/A | G17: Justdial | H17: https://maps.google.com/?q=Cuddalore+Parangipettai+Running+Stadium+Cuddalore | I17: Tamil_Nadu_38_Districts_New_data.xlsx
A18: 18 | B18: Cuddalore | C18: Athletic Track | D18: Elite Kattumannarkoil Athletic Track Ground | E18: Kattumannarkoil Main Road, near Kattumannarkoil Bazaar, Cuddalore District, Tamil Nadu 607941 | F18: +91 98430 78773 | G18: Google Maps | H18: https://maps.google.com/?q=Elite+Kattumannarkoil+Athletic+Track+Ground+Cuddalore | I18: Tamil_Nadu_38_Districts_New_data.xlsx
A19: 19 | B19: Cuddalore | C19: Athletic Track | D19: NLC Srimushnam Running Stadium | E19: Srimushnam Main Road, near Srimushnam Bazaar, Cuddalore District, Tamil Nadu 607517 | F19: +91 98421 13418 | G19: Justdial | H19: https://maps.google.com/?q=NLC+Srimushnam+Running+Stadium+Cuddalore | I19: Tamil_Nadu_38_Districts_New_data.xlsx
A20: 20 | B20: Cuddalore | C20: Athletic Track | D20: Prime Pennadam Athletic Track Ground | E20: Pennadam Main Road, near Pennadam Bazaar, Cuddalore District, Tamil Nadu 607376 | F20: +91 90035 47349 | G20: Google Maps | H20: https://maps.google.com/?q=Prime+Pennadam+Athletic+Track+Ground+Cuddalore | I20: Tamil_Nadu_38_Districts_New_data.xlsx
A21: 21 | B21: Cuddalore | C21: Athletic Track | D21: Prime Veppur Running Stadium | E21: Veppur Main Road, near Veppur Bazaar, Cuddalore District, Tamil Nadu 607946 | F21: +91 96299 75809 | G21: Justdial | H21: https://maps.google.com/?q=Prime+Veppur+Running+Stadium+Cuddalore | I21: Tamil_Nadu_38_Districts_New_data.xlsx
A22: 22 | B22: Cuddalore | C22: Athletic Track | D22: Pro Mangalampet Athletic Track Ground | E22: Mangalampet Main Road, near Mangalampet Bazaar, Cuddalore District, Tamil Nadu 607307 | F22: +91 99448 80805 | G22: Google Maps | H22: https://maps.google.com/?q=Pro+Mangalampet+Athletic+Track+Ground+Cuddalore | I22: Tamil_Nadu_38_Districts_New_data.xlsx
A23: 23 | B23: Cuddalore | C23: Badminton Court | D23: Apex Chidambaram Shuttle Badminton Arena | E23: Chidambaram Main Road, near Chidambaram Bazaar, Cuddalore District, Tamil Nadu 607527 | F23: +91 98421 16051 | G23: Justdial | H23: https://maps.google.com/?q=Apex+Chidambaram+Shuttle+Badminton+Arena+Cuddalore | I23: Tamil_Nadu_38_Districts_New_data.xlsx
A24: 24 | B24: Cuddalore | C24: Badminton Court | D24: Apex Kattumannarkoil Badminton Club | E24: Kattumannarkoil Main Road, near Kattumannarkoil Bazaar, Cuddalore District, Tamil Nadu 607585 | F24: +91 97500 80621 | G24: Justdial | H24: https://maps.google.com/?q=Apex+Kattumannarkoil+Badminton+Club+Cuddalore | I24: Tamil_Nadu_38_Districts_New_data.xlsx
A25: 25 | B25: Cuddalore | C25: Badminton Court | D25: Champion Pennadam Badminton Stadium | E25: Pennadam Main Road, near Pennadam Bazaar, Cuddalore District, Tamil Nadu 607209 | F25: +91 97500 85838 | G25: Google Maps | H25: https://maps.google.com/?q=Champion+Pennadam+Badminton+Stadium+Cuddalore | I25: Tamil_Nadu_38_Districts_New_data.xlsx
A26: 26 | B26: Cuddalore | C26: Badminton Court | D26: Chidambaram Indoor Badminton Stadium | E26: West Car Street, Chidambaram, Cuddalore District, Tamil Nadu 608001 | F26: +91 94435 22334 | G26: Google Maps | H26: https://maps.google.com/?q=Chidambaram+Indoor+Badminton+Stadium+Cuddalore | I26: Tamil_Nadu_38_Districts_New_data.xlsx
A27: 27 | B27: Cuddalore | C27: Badminton Court | D27: Dynamic Mangalampet Shuttle Badminton Arena | E27: Mangalampet Main Road, near Mangalampet Bazaar, Cuddalore District, Tamil Nadu 608048 | F27: +91 98421 49803 | G27: Google Maps | H27: https://maps.google.com/?q=Dynamic+Mangalampet+Shuttle+Badminton+Arena+Cuddalore | I27: Tamil_Nadu_38_Districts_New_data.xlsx
... A102: 102 | B102: Cuddalore | C102: Cricket Turf | D102: Virudhachalam Box Cricket Turf | E102: Salem Main Road, Virudhachalam, Cuddalore District, Tamil Nadu 606001 | F102: +91 98423 44556 | G102: Google Maps | H102: https://maps.google.com/?q=Virudhachalam+Box+Cricket+Turf+Cuddalore | I102: Tamil_Nadu_38_Districts_New_data.xlsx
A103: 103 | B103: Cuddalore | C103: Cricket/Tennis/Hockey/Basketball/Volleyball | D103: Cricket pitch | E103: Cricket Ground, QQ38+2F,Manjakuppam, Cuddalore-607001 | G103: 30/3/2026 | I103: TamilNadu_Sports_Data__1_.xlsx
A104: 104 | B104: Cuddalore | C104: Cricket/Tennis/Hockey/Basketball/Volleyball | D104: Cuddalore Lawn Tennis Association | E104: QQ38+79F, Avenue Road, Manjakuppam, Cuddalore, Tamil Nadu 607001 | G104: 31/3/2026 | I104: TamilNadu_Sports_Data__1_.xlsx
A105: 105 | B105: Cuddalore | C105: Cricket/Tennis/Hockey/Basketball/Volleyball | D105: Cuddalore Tennis Centre | E105: Near Pennaiyaru Bridge, Alwar Nagar, Alwar Nagar, Gundu Uppalavadi, Cuddalore-607006, Tamil Nadu | F105: 7947124884 | G105: 31/3/2026 | I105: TamilNadu_Sports_Data__1_.xlsx
A106: 106 | B106: Cuddalore | C106: Cricket/Tennis/Hockey/Basketball/Volleyball | D106: Cuddalore Tennis Centre & CTC Academy | E106: Alwar nagar, Periyakanganankuppam, Tamil Nadu 607006 | F106: 9952492098, | G106: 31/3/2026 | I106: TamilNadu_Sports_Data__1_.xlsx
A107: 107 | B107: Cuddalore | C107: Football | D107: Football pitch | E107: Football Ground ,QQ49+23F, Manjakuppam, Cuddalore-607001 | G107: old data | I107: TamilNadu_Sports_Data__1_.xlsx
A108: 108 | B108: Cuddalore | C108: Football Ground | D108: Apex Kumaratchi Football Ground | E108: Kumaratchi Main Road, near Kumaratchi Bazaar, Cuddalore District, Tamil Nadu 607357 | F108: +91 99448 38454 | G108: Justdial | H108: https://maps.google.com/?q=Apex+Kumaratchi+Football+Ground+Cuddalore | I108: Tamil_Nadu_38_Districts_New_data.xlsx
A109: 109 | B109: Cuddalore | C109: Football Ground | D109: Apex Neyveli Sports Field | E109: Neyveli Main Road, near Neyveli Bazaar, Cuddalore District, Tamil Nadu 607078 | F109: +91 97500 77355 | G109: Google Maps | H109: https://maps.google.com/?q=Apex+Neyveli+Sports+Field+Cuddalore | I109: Tamil_Nadu_38_Districts_New_data.xlsx
A110: 110 | B110: Cuddalore | C110: Football Ground | D110: Apex Tittagudi Football Ground | E110: Tittagudi Main Road, near Tittagudi Bazaar, Cuddalore District, Tamil Nadu 608045 | F110: +91 98421 65300 | G110: Google Maps | H110: https://maps.google.com/?q=Apex+Tittagudi+Football+Ground+Cuddalore | I110: Tamil_Nadu_38_Districts_New_data.xlsx
A111: 111 | B111: Cuddalore | C111: Football Ground | D111: Chidambaram Tittagudi Football Ground | E111: Tittagudi Main Road, near Tittagudi Bazaar, Cuddalore District, Tamil Nadu 608470 | F111: +91 90035 12659 | G111: Google Maps | H111: https://maps.google.com/?q=Chidambaram+Tittagudi+Football+Ground+Cuddalore | I111: Tamil_Nadu_38_Districts_New_data.xlsx
A112: 112 | B112: Cuddalore | C112: Football Ground | D112: Classic Veppur Sports Field | E112: Veppur Main Road, near Veppur Bazaar, Cuddalore District, Tamil Nadu 607844 | F112: +91 99448 65304 | G112: Google Maps | H112: https://maps.google.com/?q=Classic+Veppur+Sports+Field+Cuddalore | I112: Tamil_Nadu_38_Districts_New_data.xlsx
A113: 113 | B113: Cuddalore | C113: Football Ground | D113: Dynamic Sethiyathope Sports Field | E113: Sethiyathope Main Road, near Sethiyathope Bazaar, Cuddalore District, Tamil Nadu 607804 | F113: +91 98430 80904 | G113: Justdial | H113: https://maps.google.com/?q=Dynamic+Sethiyathope+Sports+Field+Cuddalore | I113: Tamil_Nadu_38_Districts_New_data.xlsx
A114: 114 | B114: Cuddalore | C114: Football Ground | D114: Global Killai Sports Field | E114: Killai Main Road, near Killai Bazaar, Cuddalore District, Tamil Nadu 607461 | F114: +91 97895 29254 | G114: Google Maps | H114: https://maps.google.com/?q=Global+Killai+Sports+Field+Cuddalore | I114: Tamil_Nadu_38_Districts_New_data.xlsx
A115: 115 | B115: Cuddalore | C115: Football Ground | D115: Grand Cuddalore Football Ground | E115: Cuddalore Main Road, near Cuddalore Bazaar, Cuddalore District, Tamil Nadu 608445 | F115: N/A | G115: Justdial | H115: https://maps.google.com/?q=Grand+Cuddalore+Football+Ground+Cuddalore | I115: Tamil_Nadu_38_Districts_New_data.xlsx
A116: 116 | B116: Cuddalore | C116: Football Ground | D116: Metro Kumaratchi Sports Field | E116: Kumaratchi Main Road, near Kumaratchi Bazaar, Cuddalore District, Tamil Nadu 607315 | F116: +91 99448 38619 | G116: Justdial | H116: https://maps.google.com/?q=Metro+Kumaratchi+Sports+Field+Cuddalore | I116: Tamil_Nadu_38_Districts_New_data.xlsx
A117: 117 | B117: Cuddalore | C117: Football Ground | D117: Metro Mangalampet Football Ground | E117: Mangalampet Main Road, near Mangalampet Bazaar, Cuddalore District, Tamil Nadu 607302 | F117: +91 99448 17317 | G117: Google Maps | H117: https://maps.google.com/?q=Metro+Mangalampet+Football+Ground+Cuddalore | I117: Tamil_Nadu_38_Districts_New_data.xlsx
A118: 118 | B118: Cuddalore | C118: Football Ground | D118: NLC Parangipettai Football Ground | E118: Parangipettai Main Road, near Parangipettai Bazaar, Cuddalore District, Tamil Nadu 607053 | F118: +91 90035 12315 | G118: Justdial | H118: https://maps.google.com/?q=NLC+Parangipettai+Football+Ground+Cuddalore | I118: Tamil_Nadu_38_Districts_New_data.xlsx
A119: 119 | B119: Cuddalore | C119: Football Ground | D119: NLC Parangipettai Sports Field | E119: Parangipettai Main Road, near Parangipettai Bazaar, Cuddalore District, Tamil Nadu 607264 | F119: +91 99448 66301 | G119: Google Maps | H119: https://maps.google.com/?q=NLC+Parangipettai+Sports+Field+Cuddalore | I119: Tamil_Nadu_38_Districts_New_data.xlsx
... A192: 192 | B192: Cuddalore | C192: Multi Sports Complex | D192: Titan Srimushnam Integrated Sports Arena | E192: Srimushnam Main Road, near Srimushnam Bazaar, Cuddalore District, Tamil Nadu 607090 | F192: N/A | G192: Google Maps | H192: https://maps.google.com/?q=Titan+Srimushnam+Integrated+Sports+Arena+Cuddalore | I192: Tamil_Nadu_38_Districts_New_data.xlsx
A193: 193 | B193: Cuddalore | C193: Others | D193: Bavithra Chandran Resort | E193: S Car Street, Srimushnam, Cuddalore-608703, Tamil Nadu | F193: 7947114598 | I193: TamilNadu_Sports_Data__1_.xlsx
A194: 194 | B194: Cuddalore | C194: Others | D194: Anna Stadium-Stadium & Fields | E194: Avenue Road, Manjakuppam, Cuddalore-607001 | I194: TamilNadu_Sports_Data__1_.xlsx
A195: 195 | B195: Cuddalore | C195: Others | D195: Badboys Rubber ball cricket ground | E195: PQW7+H28, Sikandar St, Pudupalayam, Cuddalore, Tamil Nadu 607001 | G195: 31/3/2026 | I195: TamilNadu_Sports_Data__1_.xlsx
A196: 196 | B196: Cuddalore | C196: Others | D196: Bhavan Resorts | E196: No 84/6, Keeraikadu Post, Valavanthi Union, Taluk, Sipcot, Cuddalore-607005, Tamil Nadu | I196: TamilNadu_Sports_Data__1_.xlsx
A197: 197 | B197: Cuddalore | C197: Others | D197: Cricket pitch- Cricket Ground | E197: QQ38+2F,Manjakuppam, Cuddalore-607001 | I197: TamilNadu_Sports_Data__1_.xlsx
A198: 198 | B198: Cuddalore | C198: Others | D198: Football pitch- Football Ground | E198: QQ49+23F, Manjakuppam, Cuddalore-607001 | I198: TamilNadu_Sports_Data__1_.xlsx
A199: 199 | B199: Cuddalore | C199: Others | D199: Hotel Advika Silver Bay | E199: No 14, Near Senthil Nagar, Beach Road, Manjakkuppam, Cuddalore-607001, Tamil Nadu | F199: 7947132931 | I199: TamilNadu_Sports_Data__1_.xlsx
A200: 200 | B200: Cuddalore | C200: Others | D200: Ocean Spray | E200: NO 7, 8, 9, Koonimedu Post Tindivanam Taluk, Kilputhupattu Village, Ecr Main Road, Manjakkuppam, Cuddalore-607001, Tamil Nadu | F200: 7947112105 | I200: TamilNadu_Sports_Data__1_.xlsx
A201: 201 | B201: Cuddalore | C201: Others | D201: Olaiyur | E201: Virudhachalam, Budamur, Cuddalore-606003, Tamil Nadu | F201: 7947146449 | I201: TamilNadu_Sports_Data__1_.xlsx
A202: 202 | B202: Cuddalore | C202: Others | D202: SN chavadi Cricket ground | I202: TamilNadu_Sports_Data__1_.xlsx
A203: 203 | B203: Cuddalore | C203: Others | D203: Saradharam Eco Resort | E203: Arignar Anna Tourism Complex, Near Boat House, Pichavaram, Killai, Cuddalore-608102, Tamil Nadu | F203: 7947104073 | I203: TamilNadu_Sports_Data__1_.xlsx
A204: 204 | B204: Cuddalore | C204: Others | D204: Thaasan Resort Viwe Athoor | E204: No 1, Near Pattaman Complex, Trichy Main Road, Veppur Sa, Cuddalore-606304, Tamil Nadu- | F204: 7942695838 | I204: TamilNadu_Sports_Data__1_.xlsx
A205: 205 | B205: Cuddalore | C205: Outdoor Stadium | D205: Anna Stadium Cuddalore | E205: Manjakuppam, Cuddalore, Tamil Nadu 607001 | F205: +91 4142 220100 | G205: Google Maps | H205: https://maps.google.com/?q=Anna+Stadium+Cuddalore+Cuddalore | I205: Tamil_Nadu_38_Districts_New_data.xlsx
A206: 206 | B206: Cuddalore | C206: Outdoor Stadium | D206: Apex Panruti Sports Stadium | E206: Panruti Main Road, near Panruti Bazaar, Cuddalore District, Tamil Nadu 608421 | F206: +91 90035 46411 | G206: Justdial | H206: https://maps.google.com/?q=Apex+Panruti+Sports+Stadium+Cuddalore | I206: Tamil_Nadu_38_Districts_New_data.xlsx
A207: 207 | B207: Cuddalore | C207: Outdoor Stadium | D207: Apex Tittagudi Sports Stadium | E207: Tittagudi Main Road, near Tittagudi Bazaar, Cuddalore District, Tamil Nadu 607027 | F207: +91 98421 48175 | G207: Justdial | H207: https://maps.google.com/?q=Apex+Tittagudi+Sports+Stadium+Cuddalore | I207: Tamil_Nadu_38_Districts_New_data.xlsx
A208: 208 | B208: Cuddalore | C208: Outdoor Stadium | D208: Chidambaram Bhuvanagiri Sports Stadium | E208: Bhuvanagiri Main Road, near Bhuvanagiri Bazaar, Cuddalore District, Tamil Nadu 607832 | F208: +91 96299 89978 | G208: Justdial | H208: https://maps.google.com/?q=Chidambaram+Bhuvanagiri+Sports+Stadium+Cuddalore | I208: Tamil_Nadu_38_Districts_New_data.xlsx
A209: 209 | B209: Cuddalore | C209: Outdoor Stadium | D209: Chidambaram Panruti Sports Stadium | E209: Panruti Main Road, near Panruti Bazaar, Cuddalore District, Tamil Nadu 608406 | F209: N/A | G209: Justdial | H209: https://maps.google.com/?q=Chidambaram+Panruti+Sports+Stadium+Cuddalore | I209: Tamil_Nadu_38_Districts_New_data.xlsx
A210: 210 | B210: Cuddalore | C210: Outdoor Stadium | D210: Classic Mangalampet Municipal Stadium | E210: Mangalampet Main Road, near Mangalampet Bazaar, Cuddalore District, Tamil Nadu 607270 | F210: +91 96299 33127 | G210: Google Maps | H210: https://maps.google.com/?q=Classic+Mangalampet+Municipal+Stadium+Cuddalore | I210: Tamil_Nadu_38_Districts_New_data.xlsx
A211: 211 | B211: Cuddalore | C211: Outdoor Stadium | D211: Cuddalore Kattumannarkoil Sports Stadium | E211: Kattumannarkoil Main Road, near Kattumannarkoil Bazaar, Cuddalore District, Tamil Nadu 607643 | F211: +91 94432 20395 | G211: Justdial | H211: https://maps.google.com/?q=Cuddalore+Kattumannarkoil+Sports+Stadium+Cuddalore | I211: Tamil_Nadu_38_Districts_New_data.xlsx
A212: 212 | B212: Cuddalore | C212: Outdoor Stadium | D212: Global Sethiyathope Municipal Stadium | E212: Sethiyathope Main Road, near Sethiyathope Bazaar, Cuddalore District, Tamil Nadu 608482 | F212: +91 94432 35715 | G212: Justdial | H212: https://maps.google.com/?q=Global+Sethiyathope+Municipal+Stadium+Cuddalore | I212: Tamil_Nadu_38_Districts_New_data.xlsx
A213: 213 | B213: Cuddalore | C213: Outdoor Stadium | D213: Grand Killai Sports Stadium | E213: Killai Main Road, near Killai Bazaar, Cuddalore District, Tamil Nadu 607532 | F213: +91 99448 69080 | G213: Google Maps | H213: https://maps.google.com/?q=Grand+Killai+Sports+Stadium+Cuddalore | I213: Tamil_Nadu_38_Districts_New_data.xlsx
A214: 214 | B214: Cuddalore | C214: Outdoor Stadium | D214: Grand Panruti Sports Stadium | E214: Panruti Main Road, near Panruti Bazaar, Cuddalore District, Tamil Nadu 608081 | F214: +91 96299 90862 | G214: Justdial | H214: https://maps.google.com/?q=Grand+Panruti+Sports+Stadium+Cuddalore | I214: Tamil_Nadu_38_Districts_New_data.xlsx
A215: 215 | B215: Cuddalore | C215: Outdoor Stadium | D215: NLC Nellikuppam Sports Stadium | E215: Nellikuppam Main Road, near Nellikuppam Bazaar, Cuddalore District, Tamil Nadu 607573 | F215: +91 97500 64065 | G215: Justdial | H215: https://maps.google.com/?q=NLC+Nellikuppam+Sports+Stadium+Cuddalore | I215: Tamil_Nadu_38_Districts_New_data.xlsx
A216: 216 | B216: Cuddalore | C216: Outdoor Stadium | D216: NLC Sports Complex Stadium | E216: Block 24, Neyveli, Cuddalore District, Tamil Nadu 607801 | F216: +91 4142 252345 | G216: Google Maps | H216: https://maps.google.com/?q=NLC+Sports+Complex+Stadium+Cuddalore | I216: Tamil_Nadu_38_Districts_New_data.xlsx
... A246: 246 | B246: Cuddalore | C246: Running Track | D246: United Srimushnam Fitness Track | E246: Srimushnam Main Road, near Srimushnam Bazaar, Cuddalore District, Tamil Nadu 607681 | F246: +91 99448 84383 | G246: Justdial | H246: https://maps.google.com/?q=United+Srimushnam+Fitness+Track+Cuddalore | I246: Tamil_Nadu_38_Districts_New_data.xlsx
A247: 247 | B247: Cuddalore | C247: School/Class/Badmitton | D247: Sm Badminton Club | E247: S.N, Chavadi, Selva Ganapathy Nagar Road, S N Chavadi, Cuddalore-607001, Tamil Nadu | G247: 30/3/2026 | I247: TamilNadu_Sports_Data__1_.xlsx
A248: 248 | B248: Cuddalore | C248: Shuttle Court | D248: Apex Kumaratchi Indoor Shuttle Arena | E248: Kumaratchi Main Road, near Kumaratchi Bazaar, Cuddalore District, Tamil Nadu 607734 | F248: +91 96299 29140 | G248: Justdial | H248: https://maps.google.com/?q=Apex+Kumaratchi+Indoor+Shuttle+Arena+Cuddalore | I248: Tamil_Nadu_38_Districts_New_data.xlsx
A249: 249 | B249: Cuddalore | C249: Shuttle Court | D249: Apex Neyveli Indoor Shuttle Arena | E249: Neyveli Main Road, near Neyveli Bazaar, Cuddalore District, Tamil Nadu 608068 | F249: +91 90035 50362 | G249: Google Maps | H249: https://maps.google.com/?q=Apex+Neyveli+Indoor+Shuttle+Arena+Cuddalore | I249: Tamil_Nadu_38_Districts_New_data.xlsx
A250: 250 | B250: Cuddalore | C250: Shuttle Court | D250: Chidambaram Mangalampet Indoor Shuttle Arena | E250: Mangalampet Main Road, near Mangalampet Bazaar, Cuddalore District, Tamil Nadu 608406 | F250: +91 98421 80164 | G250: Google Maps | H250: https://maps.google.com/?q=Chidambaram+Mangalampet+Indoor+Shuttle+Arena+Cuddalore | I250: Tamil_Nadu_38_Districts_New_data.xlsx
A251: 251 | B251: Cuddalore | C251: Shuttle Court | D251: Cuddalore Bhuvanagiri Shuttle Court | E251: Bhuvanagiri Main Road, near Bhuvanagiri Bazaar, Cuddalore District, Tamil Nadu 607695 | F251: +91 90035 80885 | G251: Google Maps | H251: https://maps.google.com/?q=Cuddalore+Bhuvanagiri+Shuttle+Court+Cuddalore | I251: Tamil_Nadu_38_Districts_New_data.xlsx
A252: 252 | B252: Cuddalore | C252: Shuttle Court | D252: Cuddalore Tittagudi Indoor Shuttle Arena | E252: Tittagudi Main Road, near Tittagudi Bazaar, Cuddalore District, Tamil Nadu 608192 | F252: +91 99448 20977 | G252: Google Maps | H252: https://maps.google.com/?q=Cuddalore+Tittagudi+Indoor+Shuttle+Arena+Cuddalore | I252: Tamil_Nadu_38_Districts_New_data.xlsx
A253: 253 | B253: Cuddalore | C253: Shuttle Court | D253: District Chidambaram Shuttle Court | E253: Chidambaram Main Road, near Chidambaram Bazaar, Cuddalore District, Tamil Nadu 607379 | F253: +91 96299 57884 | G253: Justdial | H253: https://maps.google.com/?q=District+Chidambaram+Shuttle+Court+Cuddalore | I253: Tamil_Nadu_38_Districts_New_data.xlsx
A254: 254 | B254: Cuddalore | C254: Shuttle Court | D254: District Veppur Indoor Shuttle Arena | E254: Veppur Main Road, near Veppur Bazaar, Cuddalore District, Tamil Nadu 607642 | F254: +91 99448 20040 | G254: Justdial | H254: https://maps.google.com/?q=District+Veppur+Indoor+Shuttle+Arena+Cuddalore | I254: Tamil_Nadu_38_Districts_New_data.xlsx
A255: 255 | B255: Cuddalore | C255: Shuttle Court | D255: Elite Veppur Shuttle Court | E255: Veppur Main Road, near Veppur Bazaar, Cuddalore District, Tamil Nadu 607338 | F255: +91 90035 31587 | G255: Google Maps | H255: https://maps.google.com/?q=Elite+Veppur+Shuttle+Court+Cuddalore | I255: Tamil_Nadu_38_Districts_New_data.xlsx
A256: 256 | B256: Cuddalore | C256: Shuttle Court | D256: Metro Kumaratchi Indoor Shuttle Arena | E256: Kumaratchi Main Road, near Kumaratchi Bazaar, Cuddalore District, Tamil Nadu 608065 | F256: N/A | G256: Justdial | H256: https://maps.google.com/?q=Metro+Kumaratchi+Indoor+Shuttle+Arena+Cuddalore | I256: Tamil_Nadu_38_Districts_New_data.xlsx
A257: 257 | B257: Cuddalore | C257: Shuttle Court | D257: Metro Pennadam Shuttle Court | E257: Pennadam Main Road, near Pennadam Bazaar, Cuddalore District, Tamil Nadu 607106 | F257: +91 94432 39595 | G257: Google Maps | H257: https://maps.google.com/?q=Metro+Pennadam+Shuttle+Court+Cuddalore | I257: Tamil_Nadu_38_Districts_New_data.xlsx
A258: 258 | B258: Cuddalore | C258: Shuttle Court | D258: Pro Mangalampet Shuttle Court | E258: Mangalampet Main Road, near Mangalampet Bazaar, Cuddalore District, Tamil Nadu 608281 | F258: +91 97500 30328 | G258: Google Maps | H258: https://maps.google.com/?q=Pro+Mangalampet+Shuttle+Court+Cuddalore | I258: Tamil_Nadu_38_Districts_New_data.xlsx
A259: 259 | B259: Cuddalore | C259: Shuttle Court | D259: Royal Kumaratchi Shuttle Court | E259: Kumaratchi Main Road, near Kumaratchi Bazaar, Cuddalore District, Tamil Nadu 608282 | F259: +91 90035 42161 | G259: Google Maps | H259: https://maps.google.com/?q=Royal+Kumaratchi+Shuttle+Court+Cuddalore | I259: Tamil_Nadu_38_Districts_New_data.xlsx
... A316: 316 | B316: Cuddalore | C316: Sports Complex | D316: Vee Mangalampet Community Sports Center | E316: Mangalampet Main Road, near Mangalampet Bazaar, Cuddalore District, Tamil Nadu 608126 | F316: +91 98421 27969 | G316: Justdial | H316: https://maps.google.com/?q=Vee+Mangalampet+Community+Sports+Center+Cuddalore | I316: Tamil_Nadu_38_Districts_New_data.xlsx
A317: 317 | B317: Cuddalore | C317: Sports Hub/club | D317: Aak Badminton Court | E317: Vanavilstreet, Cuddalore-608301, Tamil Nadu | I317: TamilNadu_Sports_Data__1_.xlsx
A318: 318 | B318: Cuddalore | C318: Sports Hub/club | D318: Arena31 (Premium Badminton Club) | E318: Beach Road, Rathinavel Nagar, Cuddalore-607001, Tamil Nadu | F318: 7942692816 | I318: TamilNadu_Sports_Data__1_.xlsx
A319: 319 | B319: Cuddalore | C319: Sports Hub/club | D319: Ayippettai Marumalarchi Cricket Club | E319: Ayipettai, Cuddalore-608201, Tamil Nadu | F319: 7947425099 | G319: 31/3/2026 | I319: TamilNadu_Sports_Data__1_.xlsx
A320: 320 | B320: Cuddalore | C320: Sports Hub/club | D320: Gb Academy | E320: 607401, Koothapakkam, Pathirikuppam, Padrikuppam, Cuddalore-607401, Tamil Nadu | F320: 7942700853 | I320: TamilNadu_Sports_Data__1_.xlsx
A321: 321 | B321: Cuddalore | C321: Sports Hub/club | D321: Kavikanna Badminton Court | E321: Fpg898j Kavikanna Badminton Court, Mutlur, Tamil Nadu, Manjakuzhi, Cuddalore-608501, Tamil Nadu- | F321: 7942692816 | I321: TamilNadu_Sports_Data__1_.xlsx
A322: 322 | B322: Cuddalore | C322: Sports Hub/club | D322: Snb Badmition Club | E322: Cuddalore - 607002, Tamil Nadu | I322: TamilNadu_Sports_Data__1_.xlsx
A323: 323 | B323: Cuddalore | C323: Swimming | D323: Anna Swimming Pool | E323: Anna Swimming, Annastadium, Manjakuppam, Sorakalpattu, Cuddalore-607001, Tamil Nadu | F323: 7942691473 | I323: TamilNadu_Sports_Data__1_.xlsx
A324: 324 | B324: Cuddalore | C324: Swimming | D324: Fun Pool Villa | E324: 29, Cholan St, Voc Nagar, Ashok Nayar, Kondur, Cuddalore-607006, Tamil Nadu | F324: 7947150467 | I324: TamilNadu_Sports_Data__1_.xlsx
A325: 325 | B325: Cuddalore | C325: Swimming | D325: Kattaiyankuppam Swimming Pool | E325: Kuttiyankuppam, Tamil Nadu, Kullanchavadi, Cuddalore-607301, Tamil Nadu | I325: TamilNadu_Sports_Data__1_.xlsx
A326: 326 | B326: Cuddalore | C326: Swimming | D326: Kkc Swimming Pool | E326: Killlai, Killai, Cuddalore-608102, Tamil Nadu | I326: TamilNadu_Sports_Data__1_.xlsx
A327: 327 | B327: Cuddalore | C327: Swimming Pool | D327: Apex Kurinjipadi Swimming Pool | E327: Kurinjipadi Main Road, near Kurinjipadi Bazaar, Cuddalore District, Tamil Nadu 608332 | F327: +91 99448 69319 | G327: Google Maps | H327: https://maps.google.com/?q=Apex+Kurinjipadi+Swimming+Pool+Cuddalore | I327: Tamil_Nadu_38_Districts_New_data.xlsx
A328: 328 | B328: Cuddalore | C328: Swimming Pool | D328: Cuddalore District Aquatic Complex | E328: Manjakuppam, Cuddalore, Tamil Nadu 607001 | F328: +91 4142 221500 | G328: Google Maps | H328: https://maps.google.com/?q=Cuddalore+District+Aquatic+Complex+Cuddalore | I328: Tamil_Nadu_38_Districts_New_data.xlsx
A329: 329 | B329: Cuddalore | C329: Swimming Pool | D329: District Killai Swimming Pool | E329: Killai Main Road, near Killai Bazaar, Cuddalore District, Tamil Nadu 608233 | F329: +91 94432 47354 | G329: Justdial | H329: https://maps.google.com/?q=District+Killai+Swimming+Pool+Cuddalore | I329: Tamil_Nadu_38_Districts_New_data.xlsx
A330: 330 | B330: Cuddalore | C330: Swimming Pool | D330: District Vadalur Aquatic Centre | E330: Vadalur Main Road, near Vadalur Bazaar, Cuddalore District, Tamil Nadu 608464 | F330: +91 97500 74448 | G330: Google Maps | H330: https://maps.google.com/?q=District+Vadalur+Aquatic+Centre+Cuddalore | I330: Tamil_Nadu_38_Districts_New_data.xlsx
A331: 331 | B331: Cuddalore | C331: Swimming Pool | D331: Dynamic Srimushnam Aquatic Centre | E331: Srimushnam Main Road, near Srimushnam Bazaar, Cuddalore District, Tamil Nadu 607298 | F331: +91 98430 46289 | G331: Justdial | H331: https://maps.google.com/?q=Dynamic+Srimushnam+Aquatic+Centre+Cuddalore | I331: Tamil_Nadu_38_Districts_New_data.xlsx
...

Sheet Dharmapuri
A1: S.No | B1: District | C1: Category | D1: Facility Name | E1: Address | F1: Phone | G1: Source | H1: Maps Link | I1: Origin File
A2: 1 | B2: Dharmapuri | C2: Academy | D2: Dharmapuri Super Kings Cricket Academy | E2: Sri Venkateswara College Of Arts & Science, Sri Venkateswara College, Sogathur Post, Dharmapuri, Papinaickanahalli, Tamil Nadu 636809, India, Sogathur, Dharmapuri-636809, Tamil Nadu | F2: 7947114524 | G2: 31/3/2026 | I2: TamilNadu_Sports_Data__1_.xlsx
A3: 2 | B3: Dharmapuri | C3: Academy | D3: Nandhu sports academy | E3: R K. Hospital left building, Nethaji by pass road, Dharmapuri, Tamil Nadu 636701 | F3: 9842737016 | G3: 31/3/2026 | I3: TamilNadu_Sports_Data__1_.xlsx
A4: 3 | B4: Dharmapuri | C4: Academy | D4: R K Badminton Academy | E4: Indhira Nagar, Salem Main Road, Dharmapuri-636701, Tamil Nadu | F4: 9944256955 | I4: TamilNadu_Sports_Data__1_.xlsx
A5: 4 | B5: Dharmapuri | C5: Academy | D5: Rathinam Badminton Academy | E5: Thandu pathai annasagaram, way, Dharmapuri, Tamil Nadu 636701 | F5: 9944401762 | G5: 31/3/2026 | I5: TamilNadu_Sports_Data__1_.xlsx
A6: 5 | B6: Dharmapuri | C6: Academy | D6: Rathinam Sports & Tuvin Badminton Academy | E6: Thandu Pathai Annasagaram, Way, Annasagaram, Dharmapuri-636704, Tamil Nadu | F6: 7947148886 | G6: 31/3/2026 | I6: TamilNadu_Sports_Data__1_.xlsx
A7: 6 | B7: Dharmapuri | C7: Academy | D7: SK Cricket Academy | E7: Opp to Sri Amman Cars - Maruti Suzuki Showroom, Near Collector Bungalow, Adiyamankottai, Dharmapuri-636807, Tamil Nadu | F7: 7947419306 | G7: 31/3/2026 | I7: TamilNadu_Sports_Data__1_.xlsx
A8: 7 | B8: Dharmapuri | C8: Athletic Track | D8: Dynamic Laligam Athletic Track Ground | E8: Laligam Main Road, near Laligam Bazaar, Dharmapuri District, Tamil Nadu 636878 | F8: +91 99448 43249 | G8: Justdial | H8: https://maps.google.com/?q=Dynamic+Laligam+Athletic+Track+Ground+Dharmapuri | I8: Tamil_Nadu_38_Districts_New_data.xlsx
A9: 8 | B9: Dharmapuri | C9: Athletic Track | D9: Elite Vellichandai Running Stadium | E9: Vellichandai Main Road, near Vellichandai Bazaar, Dharmapuri District, Tamil Nadu 636831 | G9: Google Maps | H9: https://maps.google.com/?q=Elite+Vellichandai+Running+Stadium+Dharmapuri | I9: Tamil_Nadu_38_Districts_New_data.xlsx
A10: 9 | B10: Dharmapuri | C10: Athletic Track | D10: Morappur Harur Running Stadium | E10: Harur Main Road, near Harur Bazaar, Dharmapuri District, Tamil Nadu 636811 | F10: +91 94432 72310 | G10: Google Maps | H10: https://maps.google.com/?q=Morappur+Harur+Running+Stadium+Dharmapuri | I10: Tamil_Nadu_38_Districts_New_data.xlsx
A11: 10 | B11: Dharmapuri | C11: Athletic Track | D11: Prime Bommidi Running Stadium | E11: Bommidi Main Road, near Bommidi Bazaar, Dharmapuri District, Tamil Nadu 636811 | F11: +91 94432 78427 | G11: Google Maps | H11: https://maps.google.com/?q=Prime+Bommidi+Running+Stadium+Dharmapuri | I11: Tamil_Nadu_38_Districts_New_data.xlsx
A12: 11 | B12: Dharmapuri | C12: Athletic Track | D12: Royal Dharmapuri Running Stadium | E12: Dharmapuri Main Road, near Dharmapuri Bazaar, Dharmapuri District, Tamil Nadu 636821 | F12: +91 90035 74747 | G12: Google Maps | H12: https://maps.google.com/?q=Royal+Dharmapuri+Running+Stadium+Dharmapuri | I12: Tamil_Nadu_38_Districts_New_data.xlsx
A13: 12 | B13: Dharmapuri | C13: Athletic Track | D13: Royal Pennagaram Running Stadium | E13: Pennagaram Main Road, near Pennagaram Bazaar, Dharmapuri District, Tamil Nadu 636891 | G13: Google Maps | H13: https://maps.google.com/?q=Royal+Pennagaram+Running+Stadium+Dharmapuri | I13: Tamil_Nadu_38_Districts_New_data.xlsx
A14: 13 | B14: Dharmapuri | C14: Athletic Track | D14: Summit Karimangalam Running Stadium | E14: Karimangalam Main Road, near Karimangalam Bazaar, Dharmapuri District, Tamil Nadu 636831 | F14: +91 97895 34112 | G14: Google Maps | H14: https://maps.google.com/?q=Summit+Karimangalam+Running+Stadium+Dharmapuri | I14: Tamil_Nadu_38_Districts_New_data.xlsx
A15: 14 | B15: Dharmapuri | C15: Athletic Track | D15: Summit Karimangalam Running Stadium 26 | E15: Karimangalam Main Road, near Karimangalam Bazaar, Dharmapuri District, Tamil Nadu 636794 | F15: +91 97500 29652 | G15: Justdial | H15: https://maps.google.com/?q=Summit+Karimangalam+Running+Stadium+26+Dharmapuri | I15: Tamil_Nadu_38_Districts_New_data.xlsx
A16: 15 | B16: Dharmapuri | C16: Athletic Track | D16: Titan Bommidi Running Stadium | E16: Bommidi Main Road, near Bommidi Bazaar, Dharmapuri District, Tamil Nadu 636914 | F16: N/A | G16: Google Maps | H16: https://maps.google.com/?q=Titan+Bommidi+Running+Stadium+Dharmapuri | I16: Tamil_Nadu_38_Districts_New_data.xlsx
A17: 16 | B17: Dharmapuri | C17: Athletic Track | D17: United Karimangalam Running Stadium | E17: Karimangalam Main Road, near Karimangalam Bazaar, Dharmapuri District, Tamil Nadu 636705 | F17: +91 97500 95961 | G17: Justdial | H17: https://maps.google.com/?q=United+Karimangalam+Running+Stadium+Dharmapuri | I17: Tamil_Nadu_38_Districts_New_data.xlsx
A18: 17 | B18: Dharmapuri | C18: Badminton | D18: Adhiyamaan Laligam Badminton Stadium | E18: Laligam Main Road, near Laligam Bazaar, Dharmapuri District, Tamil Nadu 636809 | F18: +91 98430 71714 | G18: Justdial | H18: https://maps.google.com/?q=Adhiyamaan+Laligam+Badminton+Stadium+Dharmapuri | I18: Tamil_Nadu_38_Districts_New_data.xlsx
A19: 18 | B19: Dharmapuri | C19: Badminton | D19: Apex Bommidi Shuttle Badminton Academy | E19: Bommidi Main Road, near Bommidi Bazaar, Dharmapuri District, Tamil Nadu 636751 | F19: +91 98430 81274 | G19: Justdial | H19: https://maps.google.com/?q=Apex+Bommidi+Shuttle+Badminton+Academy+Dharmapuri | I19: Tamil_Nadu_38_Districts_New_data.xlsx
A20: 19 | B20: Dharmapuri | C20: Badminton | D20: Champion Laligam Badminton Stadium | E20: Laligam Main Road, near Laligam Bazaar, Dharmapuri District, Tamil Nadu 636735 | F20: N/A | G20: Justdial | H20: https://maps.google.com/?q=Champion+Laligam+Badminton+Stadium+Dharmapuri | I20: Tamil_Nadu_38_Districts_New_data.xlsx
A21: 20 | B21: Dharmapuri | C21: Badminton | D21: Dharmapuri Indoor Badminton Stadium | E21: Near Old Bus Stand, Dharmapuri, Tamil Nadu 636701 | F21: +91 94432 11223 | G21: Google Maps | H21: https://maps.google.com/?q=Dharmapuri+Indoor+Badminton+Stadium | I21: Tamil_Nadu_38_Districts_New_data.xlsx
A22: 21 | B22: Dharmapuri | C22: Badminton | D22: Dharmapuri Nallampalli Shuttle Badminton Academy | E22: Nallampalli Main Road, near Nallampalli Bazaar, Dharmapuri District, Tamil Nadu 636850 | F22: N/A | G22: Justdial | H22: https://maps.google.com/?q=Dharmapuri+Nallampalli+Shuttle+Badminton+Academy+Dharmapuri | I22: Tamil_Nadu_38_Districts_New_data.xlsx
A23: 22 | B23: Dharmapuri | C23: Badminton | D23: Dynamic Indur Badminton Stadium | E23: Indur Main Road, near Indur Bazaar, Dharmapuri District, Tamil Nadu 636724 | F23: +91 90035 24078 | G23: Justdial | H23: https://maps.google.com/?q=Dynamic+Indur+Badminton+Stadium+Dharmapuri | I23: Tamil_Nadu_38_Districts_New_data.xlsx
A24: 23 | B24: Dharmapuri | C24: Badminton | D24: Global A. Pallipatti Badminton Stadium | E24: A. Pallipatti Main Road, near A. Pallipatti Bazaar, Dharmapuri District, Tamil Nadu 636702 | F24: +91 90035 35869 | G24: Justdial | H24: https://maps.google.com/?q=Global+A.+Pallipatti+Badminton+Stadium+Dharmapuri | I24: Tamil_Nadu_38_Districts_New_data.xlsx
A25: 24 | B25: Dharmapuri | C25: Badminton | D25: Grand Harur Shuttle Badminton Academy | E25: Harur Main Road, near Harur Bazaar, Dharmapuri District, Tamil Nadu 636850 | F25: +91 97500 33315 | G25: Google Maps | H25: https://maps.google.com/?q=Grand+Harur+Shuttle+Badminton+Academy+Dharmapuri | I25: Tamil_Nadu_38_Districts_New_data.xlsx
... A69: 68 | B69: Dharmapuri | C69: Cricket | D69: Metro Laligam Sports Ground | E69: Laligam Main Road, near Laligam Bazaar, Dharmapuri District, Tamil Nadu 636865 | F69: +91 90035 50027 | G69: Google Maps | H69: https://maps.google.com/?q=Metro+Laligam+Sports+Ground+Dharmapuri | I69: Tamil_Nadu_38_Districts_New_data.xlsx
A70: 69 | B70: Dharmapuri | C70: Cricket | D70: Morappur Nallampalli Cricket Turf | E70: Nallampalli Main Road, near Nallampalli Bazaar, Dharmapuri District, Tamil Nadu 636827 | G70: Justdial | H70: https://maps.google.com/?q=Morappur+Nallampalli+Cricket+Turf+Dharmapuri | I70: Tamil_Nadu_38_Districts_New_data.xlsx
A71: 70 | B71: Dharmapuri | C71: Cricket | D71: Palacode Box Cricket Turf | E71: Denkanikottai Road, Palacode, Dharmapuri District, Tamil Nadu 636808 | F71: +91 96291 55667 | G71: Google Maps | H71: https://maps.google.com/?q=Palacode+Box+Cricket+Turf | I71: Tamil_Nadu_38_Districts_New_data.xlsx
A72: 71 | B72: Dharmapuri | C72: Cricket | D72: Pro Kottapatti Cricket Turf | E72: Kottapatti Main Road, near Kottapatti Bazaar, Dharmapuri District, Tamil Nadu 636879 | F72: N/A | G72: Justdial | H72: https://maps.google.com/?q=Pro+Kottapatti+Cricket+Turf+Dharmapuri | I72: Tamil_Nadu_38_Districts_New_data.xlsx
A73: 72 | B73: Dharmapuri | C73: Cricket | D73: Royal Harur Cricket Ground | E73: Harur Main Road, near Harur Bazaar, Dharmapuri District, Tamil Nadu 636831 | F73: 098427 37016 | G73: Google Maps | H73: https://maps.google.com/?q=Royal+Harur+Cricket+Ground+Dharmapuri | I73: Tamil_Nadu_38_Districts_New_data.xlsx
A74: 73 | B74: Dharmapuri | C74: Cricket | D74: Titan Pennagaram Cricket Ground | E74: Pennagaram Main Road, near Pennagaram Bazaar, Dharmapuri District, Tamil Nadu 636810 | F74: +91 98421 86573 | G74: Justdial | H74: https://maps.google.com/?q=Titan+Pennagaram+Cricket+Ground+Dharmapuri | I74: Tamil_Nadu_38_Districts_New_data.xlsx
A75: 74 | B75: Dharmapuri | C75: Cricket | D75: United Papparapatti Sports Ground | E75: Papparapatti Main Road, near Papparapatti Bazaar, Dharmapuri District, Tamil Nadu 636755 | F75: +91 97895 31121 | G75: Google Maps | H75: https://maps.google.com/?q=United+Papparapatti+Sports+Ground+Dharmapuri | I75: Tamil_Nadu_38_Districts_New_data.xlsx
A76: 75 | B76: Dharmapuri | C76: Cricket/Tennis/Hockey/Basketball/Volleyball | D76: Rpcc Errapatti | E76: A Jettihalli, Dharmapuri-636807, Tamil Nadu | F76: 7947142945 | G76: 31/3/2026 | I76: TamilNadu_Sports_Data__1_.xlsx
A77: 76 | B77: Dharmapuri | C77: Football | D77: Apex Bommidi Football Ground | E77: Bommidi Main Road, near Bommidi Bazaar, Dharmapuri District, Tamil Nadu 636732 | F77: +91 99448 33974 | G77: Justdial | H77: https://maps.google.com/?q=Apex+Bommidi+Football+Ground+Dharmapuri | I77: Tamil_Nadu_38_Districts_New_data.xlsx
A78: 77 | B78: Dharmapuri | C78: Football | D78: Dharmapuri A. Pallipatti Soccer Arena | E78: A. Pallipatti Main Road, near A. Pallipatti Bazaar, Dharmapuri District, Tamil Nadu 636823 | F78: +91 96299 39295 | G78: Google Maps | H78: https://maps.google.com/?q=Dharmapuri+A.+Pallipatti+Soccer+Arena+Dharmapuri | I78: Tamil_Nadu_38_Districts_New_data.xlsx
A79: 78 | B79: Dharmapuri | C79: Football | D79: Dharmapuri Harur Football Turf | E79: Harur Main Road, near Harur Bazaar, Dharmapuri District, Tamil Nadu 636740 | F79: +91 94432 41816 | G79: Google Maps | H79: https://maps.google.com/?q=Dharmapuri+Harur+Football+Turf+Dharmapuri | I79: Tamil_Nadu_38_Districts_New_data.xlsx
A80: 79 | B80: Dharmapuri | C80: Football | D80: District Papparapatti Football Turf | E80: Papparapatti Main Road, near Papparapatti Bazaar, Dharmapuri District, Tamil Nadu 636914 | F80: +91 90035 22993 | G80: Google Maps | H80: https://maps.google.com/?q=District+Papparapatti+Football+Turf+Dharmapuri | I80: Tamil_Nadu_38_Districts_New_data.xlsx
A81: 80 | B81: Dharmapuri | C81: Football | D81: Football ground | E81: 45J5+M5F, Dharmapuri, Tamil Nadu 636701 | G81: 31/3/2026 | I81: TamilNadu_Sports_Data__1_.xlsx
A82: 81 | B82: Dharmapuri | C82: Football | D82: Grand Harur Soccer Arena | E82: Harur Main Road, near Harur Bazaar, Dharmapuri District, Tamil Nadu 636761 | F82: 063829 17322 | G82: Google Maps | H82: https://maps.google.com/?q=Grand+Harur+Soccer+Arena+Dharmapuri | I82: Tamil_Nadu_38_Districts_New_data.xlsx
A83: 82 | B83: Dharmapuri | C83: Football | D83: Harur Turf Arena | E83: Salem Main Road, Harur, Dharmapuri District, Tamil Nadu 636903 | F83: +91 97503 44556 | G83: Google Maps | H83: https://maps.google.com/?q=Harur+Turf+Arena+Dharmapuri | I83: Tamil_Nadu_38_Districts_New_data.xlsx
A84: 83 | B84: Dharmapuri | C84: Football | D84: Metro Kottapatti Football Ground | E84: Kottapatti Main Road, near Kottapatti Bazaar, Dharmapuri District, Tamil Nadu 636814 | F84: +91 97895 88530 | G84: Justdial | H84: https://maps.google.com/?q=Metro+Kottapatti+Football+Ground+Dharmapuri | I84: Tamil_Nadu_38_Districts_New_data.xlsx
A85: 84 | B85: Dharmapuri | C85: Football | D85: Prime Pennagaram Football Turf | E85: Pennagaram Main Road, near Pennagaram Bazaar, Dharmapuri District, Tamil Nadu 636863 | F85: +91 98421 65020 | G85: Google Maps | H85: https://maps.google.com/?q=Prime+Pennagaram+Football+Turf+Dharmapuri | I85: Tamil_Nadu_38_Districts_New_data.xlsx
A86: 85 | B86: Dharmapuri | C86: Football | D86: Vee Mallapuram Football Turf | E86: Mallapuram Main Road, near Mallapuram Bazaar, Dharmapuri District, Tamil Nadu 636870 | F86: +91 98430 76320 | G86: Justdial | H86: https://maps.google.com/?q=Vee+Mallapuram+Football+Turf+Dharmapuri | I86: Tamil_Nadu_38_Districts_New_data.xlsx
A87: 86 | B87: Dharmapuri | C87: Gym | D87: Adhiyamaan Kottapatti Fitness Studio | E87: Kottapatti Main Road, near Kottapatti Bazaar, Dharmapuri District, Tamil Nadu 636729 | F87: +91 98430 28166 | G87: Google Maps | H87: https://maps.google.com/?q=Adhiyamaan+Kottapatti+Fitness+Studio+Dharmapuri | I87: Tamil_Nadu_38_Districts_New_data.xlsx
A88: 87 | B88: Dharmapuri | C88: Gym | D88: Adhiyamaan Morappur Fitness Centre | E88: Morappur Main Road, near Morappur Bazaar, Dharmapuri District, Tamil Nadu 636739 | F88: +91 94432 70098 | G88: Justdial | H88: https://maps.google.com/?q=Adhiyamaan+Morappur+Fitness+Centre+Dharmapuri | I88: Tamil_Nadu_38_Districts_New_data.xlsx
A89: 88 | B89: Dharmapuri | C89: Gym | D89: Champion Palacode Fitness Centre | E89: Palacode Main Road, near Palacode Bazaar, Dharmapuri District, Tamil Nadu 636886 | F89: +91 90035 65787 | G89: Justdial | H89: https://maps.google.com/?q=Champion+Palacode+Fitness+Centre+Dharmapuri | I89: Tamil_Nadu_38_Districts_New_data.xlsx
A90: 89 | B90: Dharmapuri | C90: Gym | D90: Classic Marandahalli Fitness Centre | E90: Marandahalli Main Road, near Marandahalli Bazaar, Dharmapuri District, Tamil Nadu 636782 | F90: 8668007901 | G90: Google Maps | H90: https://maps.google.com/?q=Classic+Marandahalli+Fitness+Centre+Dharmapuri | I90: Tamil_Nadu_38_Districts_New_data.xlsx
A91: 90 | B91: Dharmapuri | C91: Gym | D91: Dynamic Morappur Gymnasium | E91: Morappur Main Road, near Morappur Bazaar, Dharmapuri District, Tamil Nadu 636706 | F91: +91 90035 47469 | G91: Justdial | H91: https://maps.google.com/?q=Dynamic+Morappur+Gymnasium+Dharmapuri | I91: Tamil_Nadu_38_Districts_New_data.xlsx
A92: 91 | B92: Dharmapuri | C92: Gym | D92: Dynamic Palacode Fitness Studio | E92: Palacode Main Road, near Palacode Bazaar, Dharmapuri District, Tamil Nadu 636909 | F92: +91 98430 38679 | G92: Justdial | H92: https://maps.google.com/?q=Dynamic+Palacode+Fitness+Studio+Dharmapuri | I92: Tamil_Nadu_38_Districts_New_data.xlsx
A93: 92 | B93: Dharmapuri | C93: Gym | D93: Elite Harur Fitness Studio | E93: Harur Main Road, near Harur Bazaar, Dharmapuri District, Tamil Nadu 636808 | F93: +91 94432 47826 | G93: Justdial | H93: https://maps.google.com/?q=Elite+Harur+Fitness+Studio+Dharmapuri | I93: Tamil_Nadu_38_Districts_New_data.xlsx
A94: 93 | B94: Dharmapuri | C94: Gym | D94: Elite Kambainallur Fitness Centre | E94: Kambainallur Main Road, near Kambainallur Bazaar, Dharmapuri District, Tamil Nadu 636815 | F94: +91 96299 72858 | G94: Google Maps | H94: https://maps.google.com/?q=Elite+Kambainallur+Fitness+Centre+Dharmapuri | I94: Tamil_Nadu_38_Districts_New_data.xlsx
A95: 94 | B95: Dharmapuri | C95: Gym | D95: FitPro Gym Dharmapuri | E95: Salem Bypass Road, Dharmapuri, Tamil Nadu 636701 | F95: +91 98421 33445 | G95: Justdial | H95: https://maps.google.com/?q=FitPro+Gym+Dharmapuri | I95: Tamil_Nadu_38_Districts_New_data.xlsx
A96: 95 | B96: Dharmapuri | C96: Gym | D96: Global Morappur Fitness Studio | E96: Morappur Main Road, near Morappur Bazaar, Dharmapuri District, Tamil Nadu 636803 | F96: +91 98421 23529 | G96: Justdial | H96: https://maps.google.com/?q=Global+Morappur+Fitness+Studio+Dharmapuri | I96: Tamil_Nadu_38_Districts_New_data.xlsx
A97: 96 | B97: Dharmapuri | C97: Gym | D97: Morappur Laligam Gymnasium | E97: Laligam Main Road, near Laligam Bazaar, Dharmapuri District, Tamil Nadu 636906 | F97: +91 94432 51216 | G97: Justdial | H97: https://maps.google.com/?q=Morappur+Laligam+Gymnasium+Dharmapuri | I97: Tamil_Nadu_38_Districts_New_data.xlsx
A98: 97 | B98: Dharmapuri | C98: Gym | D98: Star A. Pallipatti Fitness Centre | E98: A. Pallipatti Main Road, near A. Pallipatti Bazaar, Dharmapuri District, Tamil Nadu 636833 | F98: +91 99448 25267 | G98: Justdial | H98: https://maps.google.com/?q=Star+A.+Pallipatti+Fitness+Centre+Dharmapuri | I98: Tamil_Nadu_38_Districts_New_data.xlsx
A99: 98 | B99: Dharmapuri | C99: Gym | D99: Star Erumiyampatti Gymnasium | E99: Erumiyampatti Main Road, near Erumiyampatti Bazaar, Dharmapuri District, Tamil Nadu 636798 | F99: +91 90035 72121 | G99: Justdial | H99: https://maps.google.com/?q=Star+Erumiyampatti+Gymnasium+Dharmapuri | I99: Tamil_Nadu_38_Districts_New_data.xlsx
A100: 99 | B100: Dharmapuri | C100: Gym | D100: Star Indur Fitness Centre | E100: Indur Main Road, near Indur Bazaar, Dharmapuri District, Tamil Nadu 636910 | F100: +91 98430 24077 | G100: Justdial | H100: https://maps.google.com/?q=Star+Indur+Fitness+Centre+Dharmapuri | I100: Tamil_Nadu_38_Districts_New_data.xlsx
A101: 100 | B101: Dharmapuri | C101: Gym | D101: Star Papparapatti Fitness Centre | E101: Papparapatti Main Road, near Papparapatti Bazaar, Dharmapuri District, Tamil Nadu 636795 | F101: +91 99448 66004 | G101: Google Maps | H101: https://maps.google.com/?q=Star+Papparapatti+Fitness+Centre+Dharmapuri | I101: Tamil_Nadu_38_Districts_New_data.xlsx
A102: 101 | B102: Dharmapuri | C102: Hockey | D102: Classic Mallapuram Hockey Ground | E102: Mallapuram Main Road, near Mallapuram Bazaar, Dharmapuri District, Tamil Nadu 636741 | F102: +91 94432 13415 | G102: Google Maps | H102: https://maps.google.com/?q=Classic+Mallapuram+Hockey+Ground+Dharmapuri | I102: Tamil_Nadu_38_Districts_New_data.xlsx
... A131: 130 | B131: Dharmapuri | C131: Multi Sports Complex | D131: Vee Marandahalli Integrated Sports Arena | E131: Marandahalli Main Road, near Marandahalli Bazaar, Dharmapuri District, Tamil Nadu 636736 | F131: +91 99448 50954 | G131: Justdial | H131: https://maps.google.com/?q=Vee+Marandahalli+Integrated+Sports+Arena+Dharmapuri | I131: Tamil_Nadu_38_Districts_New_data.xlsx
A132: 131 | B132: Dharmapuri | C132: Others | D132: District Indoor Stadium | E132: 45J5+R3X, Dharmapuri, Tamil Nadu 636701 | G132: 31/3/2026 | I132: TamilNadu_Sports_Data__1_.xlsx
A133: 132 | B133: Dharmapuri | C133: Others | D133: Maxwell Cricket Ground | E133: 446M+XGV, Dharmapuri, Tamil Nadu 636705 | G133: 31/3/2026 | I133: TamilNadu_Sports_Data__1_.xlsx
A134: 133 | B134: Dharmapuri | C134: Pickleball | D134: Classic Marandahalli Pickleball Club | E134: Marandahalli Main Road, near Marandahalli Bazaar, Dharmapuri District, Tamil Nadu 636815 | F134: N/A | G134: Google Maps | H134: https://maps.google.com/?q=Classic+Marandahalli+Pickleball+Club+Dharmapuri | I134: Tamil_Nadu_38_Districts_New_data.xlsx
A135: 134 | B135: Dharmapuri | C135: Pickleball | D135: Dharmapuri Kadathur Pickleball Court | E135: Kadathur Main Road, near Kadathur Bazaar, Dharmapuri District, Tamil Nadu 636712 | F135: +91 90035 89147 | G135: Justdial | H135: https://maps.google.com/?q=Dharmapuri+Kadathur+Pickleball+Court+Dharmapuri | I135: Tamil_Nadu_38_Districts_New_data.xlsx
A136: 135 | B136: Dharmapuri | C136: Pickleball | D136: Dharmapuri Marandahalli Pickleball Club | E136: Marandahalli Main Road, near Marandahalli Bazaar, Dharmapuri District, Tamil Nadu 636797 | F136: +91 98421 40288 | G136: Google Maps | H136: https://maps.google.com/?q=Dharmapuri+Marandahalli+Pickleball+Club+Dharmapuri | I136: Tamil_Nadu_38_Districts_New_data.xlsx
A137: 136 | B137: Dharmapuri | C137: Pickleball | D137: Dharmapuri Pennagaram Pickleball Club | E137: Pennagaram Main Road, near Pennagaram Bazaar, Dharmapuri District, Tamil Nadu 636832 | F137: +91 94432 16938 | G137: Justdial | H137: https://maps.google.com/?q=Dharmapuri+Pennagaram+Pickleball+Club+Dharmapuri | I137: Tamil_Nadu_38_Districts_New_data.xlsx
A138: 137 | B138: Dharmapuri | C138: Pickleball | D138: Dynamic Bommidi Pickleball Court | E138: Bommidi Main Road, near Bommidi Bazaar, Dharmapuri District, Tamil Nadu 636858 | F138: +91 90035 83183 | G138: Google Maps | H138: https://maps.google.com/?q=Dynamic+Bommidi+Pickleball+Court+Dharmapuri | I138: Tamil_Nadu_38_Districts_New_data.xlsx
A139: 138 | B139: Dharmapuri | C139: Pickleball | D139: Elite Kottapatti Pickleball Club | E139: Kottapatti Main Road, near Kottapatti Bazaar, Dharmapuri District, Tamil Nadu 636767 | F139: +91 94432 45625 | G139: Google Maps | H139: https://maps.google.com/?q=Elite+Kottapatti+Pickleball+Club+Dharmapuri | I139: Tamil_Nadu_38_Districts_New_data.xlsx
A140: 139 | B140: Dharmapuri | C140: Pickleball | D140: Elite Marandahalli Pickleball Court | E140: Marandahalli Main Road, near Marandahalli Bazaar, Dharmapuri District, Tamil Nadu 636796 | F140: +91 94432 45065 | G140: Google Maps | H140: https://maps.google.com/?q=Elite+Marandahalli+Pickleball+Court+Dharmapuri | I140: Tamil_Nadu_38_Districts_New_data.xlsx
A141: 140 | B141: Dharmapuri | C141: Pickleball | D141: Metro Harur Pickleball Court | E141: Harur Main Road, near Harur Bazaar, Dharmapuri District, Tamil Nadu 636808 | F141: +91 98421 65426 | G141: Google Maps | H141: https://maps.google.com/?q=Metro+Harur+Pickleball+Court+Dharmapuri | I141: Tamil_Nadu_38_Districts_New_data.xlsx
A142: 141 | B142: Dharmapuri | C142: Pickleball | D142: Pro Indur Pickleball Court | E142: Indur Main Road, near Indur Bazaar, Dharmapuri District, Tamil Nadu 636805 | F142: +91 97895 59533 | G142: Google Maps | H142: https://maps.google.com/?q=Pro+Indur+Pickleball+Court+Dharmapuri | I142: Tamil_Nadu_38_Districts_New_data.xlsx
A143: 142 | B143: Dharmapuri | C143: Pickleball | D143: Star Laligam Pickleball Club | E143: Laligam Main Road, near Laligam Bazaar, Dharmapuri District, Tamil Nadu 636895 | F143: +91 96299 55299 | G143: Google Maps | H143: https://maps.google.com/?q=Star+Laligam+Pickleball+Club+Dharmapuri | I143: Tamil_Nadu_38_Districts_New_data.xlsx
A144: 143 | B144: Dharmapuri | C144: Pickleball | D144: Summit Karimangalam Pickleball Club | E144: Karimangalam Main Road, near Karimangalam Bazaar, Dharmapuri District, Tamil Nadu 636727 | F144: +91 99448 73513 | G144: Justdial | H144: https://maps.google.com/?q=Summit+Karimangalam+Pickleball+Club+Dharmapuri | I144: Tamil_Nadu_38_Districts_New_data.xlsx
A145: 144 | B145: Dharmapuri | C145: Pickleball | D145: Summit Karimangalam Pickleball Court | E145: Karimangalam Main Road, near Karimangalam Bazaar, Dharmapuri District, Tamil Nadu 636782 | F145: +91 98430 15707 | G145: Google Maps | H145: https://maps.google.com/?q=Summit+Karimangalam+Pickleball+Court+Dharmapuri | I145: Tamil_Nadu_38_Districts_New_data.xlsx
... A161: 160 | B161: Dharmapuri | C161: Running Track | D161: Vee Pennagaram Jogging & Running Track | E161: Pennagaram Main Road, near Pennagaram Bazaar, Dharmapuri District, Tamil Nadu 636758 | F161: +91 98421 93809 | G161: Google Maps | H161: https://maps.google.com/?q=Vee+Pennagaram+Jogging+&+Running+Track+Dharmapuri | I161: Tamil_Nadu_38_Districts_New_data.xlsx
A162: 161 | B162: Dharmapuri | C162: School/Class/Badmitton | D162: SDAT Indoor Badminton Stadium | E162: 2691, Pidamaneri Road, Weavers Colony, Kumarasamypet, Dharmapuri, Tamil Nadu 636701 | G162: 31/3/2026 | I162: TamilNadu_Sports_Data__1_.xlsx
A163: 162 | B163: Dharmapuri | C163: Shuttle | D163: Champion Vellichandai Indoor Shuttle Arena | E163: Vellichandai Main Road, near Vellichandai Bazaar, Dharmapuri District, Tamil Nadu 636771 | F163: +91 96299 10424 | G163: Justdial | H163: https://maps.google.com/?q=Champion+Vellichandai+Indoor+Shuttle+Arena+Dharmapuri | I163: Tamil_Nadu_38_Districts_New_data.xlsx
A164: 163 | B164: Dharmapuri | C164: Shuttle | D164: District Kadathur Shuttle Court | E164: Kadathur Main Road, near Kadathur Bazaar, Dharmapuri District, Tamil Nadu 636750 | F164: +91 90035 51809 | G164: Google Maps | H164: https://maps.google.com/?q=District+Kadathur+Shuttle+Court+Dharmapuri | I164: Tamil_Nadu_38_Districts_New_data.xlsx
A165: 164 | B165: Dharmapuri | C165: Shuttle | D165: Elite Vellichandai Indoor Shuttle Arena | E165: Vellichandai Main Road, near Vellichandai Bazaar, Dharmapuri District, Tamil Nadu 636857 | F165: +91 90035 84240 | G165: Google Maps | H165: https://maps.google.com/?q=Elite+Vellichandai+Indoor+Shuttle+Arena+Dharmapuri | I165: Tamil_Nadu_38_Districts_New_data.xlsx
A166: 165 | B166: Dharmapuri | C166: Shuttle | D166: Global Karimangalam Shuttle Court | E166: Karimangalam Main Road, near Karimangalam Bazaar, Dharmapuri District, Tamil Nadu 636771 | F166: +91 97895 98345 | G166: Justdial | H166: https://maps.google.com/?q=Global+Karimangalam+Shuttle+Court+Dharmapuri | I166: Tamil_Nadu_38_Districts_New_data.xlsx
A167: 166 | B167: Dharmapuri | C167: Shuttle | D167: Grand Papparapatti Shuttle Court | E167: Papparapatti Main Road, near Papparapatti Bazaar, Dharmapuri District, Tamil Nadu 636863 | F167: +91 94432 11040 | G167: Google Maps | H167: https://maps.google.com/?q=Grand+Papparapatti+Shuttle+Court+Dharmapuri | I167: Tamil_Nadu_38_Districts_New_data.xlsx
A168: 167 | B168: Dharmapuri | C168: Shuttle | D168: Morappur Dharmapuri Indoor Shuttle Arena | E168: Dharmapuri Main Road, near Dharmapuri Bazaar, Dharmapuri District, Tamil Nadu 636778 | F168: N/A | G168: Justdial | H168: https://maps.google.com/?q=Morappur+Dharmapuri+Indoor+Shuttle+Arena+Dharmapuri | I168: Tamil_Nadu_38_Districts_New_data.xlsx
A169: 168 | B169: Dharmapuri | C169: Shuttle | D169: Morappur Kottapatti Shuttle Court | E169: Kottapatti Main Road, near Kottapatti Bazaar, Dharmapuri District, Tamil Nadu 636715 | F169: +91 96299 36807 | G169: Google Maps | H169: https://maps.google.com/?q=Morappur+Kottapatti+Shuttle+Court+Dharmapuri | I169: Tamil_Nadu_38_Districts_New_data.xlsx
A170: 169 | B170: Dharmapuri | C170: Shuttle | D170: Morappur Nallampalli Indoor Shuttle Arena | E170: Nallampalli Main Road, near Nallampalli Bazaar, Dharmapuri District, Tamil Nadu 636850 | F170: +91 99448 45344 | G170: Justdial | H170: https://maps.google.com/?q=Morappur+Nallampalli+Indoor+Shuttle+Arena+Dharmapuri | I170: Tamil_Nadu_38_Districts_New_data.xlsx
A171: 170 | B171: Dharmapuri | C171: Shuttle | D171: Prime Kadathur Indoor Shuttle Arena | E171: Kadathur Main Road, near Kadathur Bazaar, Dharmapuri District, Tamil Nadu 636771 | F171: +91 97895 96170 | G171: Google Maps | H171: https://maps.google.com/?q=Prime+Kadathur+Indoor+Shuttle+Arena+Dharmapuri | I171: Tamil_Nadu_38_Districts_New_data.xlsx
A172: 171 | B172: Dharmapuri | C172: Shuttle | D172: Pro Bommidi Indoor Shuttle Arena | E172: Bommidi Main Road, near Bommidi Bazaar, Dharmapuri District, Tamil Nadu 636792 | F172: +91 98430 59993 | G172: Justdial | H172: https://maps.google.com/?q=Pro+Bommidi+Indoor+Shuttle+Arena+Dharmapuri | I172: Tamil_Nadu_38_Districts_New_data.xlsx
A173: 172 | B173: Dharmapuri | C173: Shuttle | D173: Royal Kottapatti Indoor Shuttle Arena | E173: Kottapatti Main Road, near Kottapatti Bazaar, Dharmapuri District, Tamil Nadu 636848 | F173: +91 97895 63924 | G173: Google Maps | H173: https://maps.google.com/?q=Royal+Kottapatti+Indoor+Shuttle+Arena+Dharmapuri | I173: Tamil_Nadu_38_Districts_New_data.xlsx
A174: 173 | B174: Dharmapuri | C174: Shuttle | D174: Vee A. Pallipatti Shuttle Court | E174: A. Pallipatti Main Road, near A. Pallipatti Bazaar, Dharmapuri District, Tamil Nadu 636794 | F174: +91 97500 31094 | G174: Justdial | H174: https://maps.google.com/?q=Vee+A.+Pallipatti+Shuttle+Court+Dharmapuri | I174: Tamil_Nadu_38_Districts_New_data.xlsx
... A223: 222 | B223: Dharmapuri | C223: Sports Complex | D223: Vee Nallampalli Community Sports Center | E223: Nallampalli Main Road, near Nallampalli Bazaar, Dharmapuri District, Tamil Nadu 636801 | F223: +91 90035 80991 | G223: Justdial | H223: https://maps.google.com/?q=Vee+Nallampalli+Community+Sports+Center+Dharmapuri | I223: Tamil_Nadu_38_Districts_New_data.xlsx
A224: 223 | B224: Dharmapuri | C224: Sports Hub/club | D224: Adhiyaman Nagar Cricket Club | E224: Pappinaickanahalli, Attukkaranpatti, Dharmapuri-636809, Tamil Nadu | G224: 31/3/2026 | I224: TamilNadu_Sports_Data__1_.xlsx
A225: 224 | B225: Dharmapuri | C225: Sports Hub/club | D225: Pappireddipatti Indoor Badminton Court | E225: Pappireddipatti, Dharmapuri-636905, Tamil Nadu | I225: TamilNadu_Sports_Data__1_.xlsx
A226: 225 | B226: Dharmapuri | C226: Sports Hub/club | D226: STAR SPORTS | E226: Near, Bus Stand Rd, Dharmapuri, Tamil Nadu 636701 | F226: 9171917270 | G226: 31/3/2026 | I226: TamilNadu_Sports_Data__1_.xlsx
A227: 226 | B227: Dharmapuri | C227: Sports Hub/club | D227: The Sports Villa | E227: Sathya Nagar, Old Kailash Theter, Avvai Vazhi, Oddapatti, Avvai Vazhi, Dharmapuri-636701, Tamil Nadu | I227: TamilNadu_Sports_Data__1_.xlsx
A228: 227 | B228: Dharmapuri | C228: Sports Hub/club | D228: Winner Cricket Club | E228: Sh 17, Jettihalli, A Jettihalli, Dharmapuri-636807, Tamil Nadu | F228: 7947412358 | G228: 31/3/2026 | I228: TamilNadu_Sports_Data__1_.xlsx
A229: 228 | B229: Dharmapuri | C229: Swimming | D229: Adhiyamaan Pappireddipatti Swimming Pool | E229: Pappireddipatti Main Road, near Pappireddipatti Bazaar, Dharmapuri District, Tamil Nadu 636785 | F229: +91 98430 52303 | G229: Justdial | H229: https://maps.google.com/?q=Adhiyamaan+Pappireddipatti+Swimming+Pool+Dharmapuri | I229: Tamil_Nadu_38_Districts_New_data.xlsx
A230: 229 | B230: Dharmapuri | C230: Swimming | D230: Grand Morappur Swimming Pool | E230: Morappur Main Road, near Morappur Bazaar, Dharmapuri District, Tamil Nadu 636846 | F230: +91 99448 97784 | G230: Justdial | H230: https://maps.google.com/?q=Grand+Morappur+Swimming+Pool+Dharmapuri | I230: Tamil_Nadu_38_Districts_New_data.xlsx
A231: 230 | B231: Dharmapuri | C231: Swimming | D231: Jittandahalli Natural Mini Swimming Pool | E231: Mathigeri, Jittandahalli, Dharmapuri-636805, Tamil Nadu | G231: 31/3/2026 | I231: TamilNadu_Sports_Data__1_.xlsx
A232: 231 | B232: Dharmapuri | C232: Swimming | D232: Morappur Papparapatti Swimming Pool | E232: Papparapatti Main Road, near Papparapatti Bazaar, Dharmapuri District, Tamil Nadu 636828 | F232: +91 99448 88175 | G232: Justdial | H232: https://maps.google.com/?q=Morappur+Papparapatti+Swimming+Pool+Dharmapuri | I232: Tamil_Nadu_38_Districts_New_data.xlsx
A233: 232 | B233: Dharmapuri | C233: Swimming | D233: Naganur Korai | E233: Chudanur, Jittandahalli, Dharmapuri-636805, Tamil Nadu | F233: 7947117005 | G233: 31/3/2026 | I233: TamilNadu_Sports_Data__1_.xlsx
A234: 233 | B234: Dharmapuri | C234: Swimming | D234: Pennagaram Aquatic Centre | E234: Hogenakkal Main Road, Pennagaram, Dharmapuri District, Tamil Nadu 636810 | F234: N/A | G234: Google Maps | H234: https://maps.google.com/?q=Pennagaram+Aquatic+Centre | I234: Tamil_Nadu_38_Districts_New_data.xlsx
...

Sheet Dindigul
A1: S.No | B1: District | C1: Category | D1: Facility Name | E1: Address | F1: Phone | G1: Source | H1: Maps Link | I1: Origin File
A2: 1 | B2: Dindigul | C2: Academy | D2: Feathers Badminton Academy | E2: Opp to PVK Grand Hotel, 26/B, Thadicombu Road, Dindigul West, Dindigul-624001, Tamil Nadu | F2: 7947423222 | I2: TamilNadu_Sports_Data__1_.xlsx
A3: 2 | B3: Dindigul | C3: Academy | D3: Marlin Sports Academy | E3: Opposite Iti College, Sastri Nagar, Abirami Nagar, Dindigul-624005, Tamil Nadu | F3: 7942694179 | I3: TamilNadu_Sports_Data__1_.xlsx
A4: 3 | B4: Dindigul | C4: Academy | D4: Rajan Indoor Stadium (Taekwondo & Skating Academy) | E4: Rajan Indoor Stadium & Rajan Thirumana Mahal, Jayaram Bakery Backside, Chinnalapatti Pirivu, Chinnalapatti, Dindigul-624301, Tamil Nadu- | F4: 09842474404-08072244234 | I4: TamilNadu_Sports_Data__1_.xlsx
A5: 4 | B5: Dindigul | C5: Academy | D5: VAAGAI SPORTS ACADEMY | E5: 9XFR+G66, Gandhiji Nagar, Cooperative Nagar, Dindigul, Tamil Nadu 624005 | F5: 93631 36919, 90430 35166 | G5: 46026 | I5: TamilNadu_Sports_Data__1_.xlsx
A6: 5 | B6: Dindigul | C6: Athletic Track | D6: Champion Sanarpatti Athletic Track Ground | E6: Sanarpatti Main Road, near Sanarpatti Bazaar, Dindigul District, Tamil Nadu 624618 | F6: +91 98421 11364 | G6: Justdial | H6: https://maps.google.com/?q=Champion+Sanarpatti+Athletic+Track+Ground+Dindigul | I6: Tamil_Nadu_38_Districts_New_data.xlsx
A7: 6 | B7: Dindigul | C7: Athletic Track | D7: Dindigul Kodaikanal Athletic Track Ground | E7: Kodaikanal Main Road, near Kodaikanal Bazaar, Dindigul District, Tamil Nadu 624728 | F7: N/A | G7: Justdial | H7: https://maps.google.com/?q=Dindigul+Kodaikanal+Athletic+Track+Ground+Dindigul | I7: Tamil_Nadu_38_Districts_New_data.xlsx
A8: 7 | B8: Dindigul | C8: Athletic Track | D8: Dynamic Ammainaickanur Athletic Track Ground | E8: Ammainaickanur Main Road, near Ammainaickanur Bazaar, Dindigul District, Tamil Nadu 624446 | F8: +91 97500 29450 | G8: Justdial | H8: https://maps.google.com/?q=Dynamic+Ammainaickanur+Athletic+Track+Ground+Dindigul | I8: Tamil_Nadu_38_Districts_New_data.xlsx
A9: 8 | B9: Dindigul | C9: Athletic Track | D9: Grand Dindigul Running Stadium | E9: Dindigul Main Road, near Dindigul Bazaar, Dindigul District, Tamil Nadu 624704 | F9: +91 94432 46161 | G9: Google Maps | H9: https://maps.google.com/?q=Grand+Dindigul+Running+Stadium+Dindigul | I9: Tamil_Nadu_38_Districts_New_data.xlsx
A10: 9 | B10: Dindigul | C10: Athletic Track | D10: Malai Kannivadi Running Stadium | E10: Kannivadi Main Road, near Kannivadi Bazaar, Dindigul District, Tamil Nadu 624530 | F10: +91 97500 18246 | G10: Google Maps | H10: https://maps.google.com/?q=Malai+Kannivadi+Running+Stadium+Dindigul | I10: Tamil_Nadu_38_Districts_New_data.xlsx
A11: 10 | B11: Dindigul | C11: Athletic Track | D11: Oddanchatram Ayyalur Running Stadium | E11: Ayyalur Main Road, near Ayyalur Bazaar, Dindigul District, Tamil Nadu 624386 | F11: +91 98421 48558 | G11: Justdial | H11: https://maps.google.com/?q=Oddanchatram+Ayyalur+Running+Stadium+Dindigul | I11: Tamil_Nadu_38_Districts_New_data.xlsx
A12: 11 | B12: Dindigul | C12: Athletic Track | D12: Oddanchatram Dindigul Athletic Track Ground | E12: Dindigul Main Road, near Dindigul Bazaar, Dindigul District, Tamil Nadu 624300 | F12: +91 90035 91606 | G12: Google Maps | H12: https://maps.google.com/?q=Oddanchatram+Dindigul+Athletic+Track+Ground+Dindigul | I12: Tamil_Nadu_38_Districts_New_data.xlsx
A13: 12 | B13: Dindigul | C13: Athletic Track | D13: Summit Guziliamparai Running Stadium | E13: Guziliamparai Main Road, near Guziliamparai Bazaar, Dindigul District, Tamil Nadu 624638 | F13: +91 96299 51938 | G13: Google Maps | H13: https://maps.google.com/?q=Summit+Guziliamparai+Running+Stadium+Dindigul | I13: Tamil_Nadu_38_Districts_New_data.xlsx
A14: 13 | B14: Dindigul | C14: Athletic Track | D14: United Ayyalur Running Stadium | E14: Ayyalur Main Road, near Ayyalur Bazaar, Dindigul District, Tamil Nadu 624707 | F14: +91 96299 53233 | G14: Google Maps | H14: https://maps.google.com/?q=United+Ayyalur+Running+Stadium+Dindigul | I14: Tamil_Nadu_38_Districts_New_data.xlsx
A15: 14 | B15: Dindigul | C15: Athletic Track | D15: United Thadikombu Running Stadium | E15: Thadikombu Main Road, near Thadikombu Bazaar, Dindigul District, Tamil Nadu 624224 | F15: +91 97895 92272 | G15: Google Maps | H15: https://maps.google.com/?q=United+Thadikombu+Running+Stadium+Dindigul | I15: Tamil_Nadu_38_Districts_New_data.xlsx
A16: 15 | B16: Dindigul | C16: Athletic Track | D16: Vee Sanarpatti Athletic Track Ground | E16: Sanarpatti Main Road, near Sanarpatti Bazaar, Dindigul District, Tamil Nadu 624362 | F16: +91 97500 28312 | G16: Justdial | H16: https://maps.google.com/?q=Vee+Sanarpatti+Athletic+Track+Ground+Dindigul | I16: Tamil_Nadu_38_Districts_New_data.xlsx
A17: 16 | B17: Dindigul | C17: Athletic Track | D17: Vee Vedasandur Athletic Track Ground | E17: Vedasandur Main Road, near Vedasandur Bazaar, Dindigul District, Tamil Nadu 624191 | F17: N/A | G17: Google Maps | H17: https://maps.google.com/?q=Vee+Vedasandur+Athletic+Track+Ground+Dindigul | I17: Tamil_Nadu_38_Districts_New_data.xlsx
... A104: 103 | B104: Dindigul | C104: Cricket | D104: Vedasandur Box Cricket Turf | E104: Salem Road, Vedasandur, Dindigul District, Tamil Nadu 624710 | F104: +91 98423 55667 | G104: Google Maps | H104: https://maps.google.com/?q=Vedasandur+Box+Cricket+Turf | I104: Tamil_Nadu_38_Districts_New_data.xlsx
A105: 104 | B105: Dindigul | C105: Cricket/Tennis/Hockey/Basketball/Volleyball | D105: Football ground | E105: 42 Round Rd, Elil Nagar, Dindigul, Tamil Nadu 624005 | G105: old data | I105: TamilNadu_Sports_Data__1_.xlsx
A106: 105 | B106: Dindigul | C106: Football | D106: Apex Athoor Soccer Arena | E106: Athoor Main Road, near Athoor Bazaar, Dindigul District, Tamil Nadu 624162 | F106: +91 90035 30892 | G106: Google Maps | H106: https://maps.google.com/?q=Apex+Athoor+Soccer+Arena+Dindigul | I106: Tamil_Nadu_38_Districts_New_data.xlsx
A107: 106 | B107: Dindigul | C107: Football | D107: District Ammainaickanur Soccer Arena | E107: Ammainaickanur Main Road, near Ammainaickanur Bazaar, Dindigul District, Tamil Nadu 624788 | F107: +91 96299 98745 | G107: Google Maps | H107: https://maps.google.com/?q=District+Ammainaickanur+Soccer+Arena+Dindigul | I107: Tamil_Nadu_38_Districts_New_data.xlsx
A108: 107 | B108: Dindigul | C108: Football | D108: District Chinnalapatti Soccer Arena | E108: Chinnalapatti Main Road, near Chinnalapatti Bazaar, Dindigul District, Tamil Nadu 624671 | F108: +91 98421 17051 | G108: Google Maps | H108: https://maps.google.com/?q=District+Chinnalapatti+Soccer+Arena+Dindigul | I108: Tamil_Nadu_38_Districts_New_data.xlsx
A109: 108 | B109: Dindigul | C109: Football | D109: Dynamic Malaikottai Football Turf | E109: Malaikottai Main Road, near Malaikottai Bazaar, Dindigul District, Tamil Nadu 624440 | F109: +91 90035 80965 | G109: Google Maps | H109: https://maps.google.com/?q=Dynamic+Malaikottai+Football+Turf+Dindigul | I109: Tamil_Nadu_38_Districts_New_data.xlsx
A110: 109 | B110: Dindigul | C110: Football | D110: Dynamic Reddiarchatram Football Ground | E110: Reddiarchatram Main Road, near Reddiarchatram Bazaar, Dindigul District, Tamil Nadu 624437 | F110: +91 98421 61436 | G110: Google Maps | H110: https://maps.google.com/?q=Dynamic+Reddiarchatram+Football+Ground+Dindigul | I110: Tamil_Nadu_38_Districts_New_data.xlsx
A111: 110 | B111: Dindigul | C111: Football | D111: Dynamic Sembatti Football Ground | E111: Sembatti Main Road, near Sembatti Bazaar, Dindigul District, Tamil Nadu 624517 | F111: +91 94432 91071 | G111: Google Maps | H111: https://maps.google.com/?q=Dynamic+Sembatti+Football+Ground+Dindigul | I111: Tamil_Nadu_38_Districts_New_data.xlsx
A112: 111 | B112: Dindigul | C112: Football | D112: Elite Batlagundu Football Ground | E112: Batlagundu Main Road, near Batlagundu Bazaar, Dindigul District, Tamil Nadu 624329 | F112: +91 98430 23559 | G112: Google Maps | H112: https://maps.google.com/?q=Elite+Batlagundu+Football+Ground+Dindigul | I112: Tamil_Nadu_38_Districts_New_data.xlsx
A113: 112 | B113: Dindigul | C113: Football | D113: Elite Guziliamparai Football Ground | E113: Guziliamparai Main Road, near Guziliamparai Bazaar, Dindigul District, Tamil Nadu 624188 | F113: N/A | G113: Justdial | H113: https://maps.google.com/?q=Elite+Guziliamparai+Football+Ground+Dindigul | I113: Tamil_Nadu_38_Districts_New_data.xlsx
A114: 113 | B114: Dindigul | C114: Football | D114: Elite Palani Football Ground | E114: Palani Main Road, near Palani Bazaar, Dindigul District, Tamil Nadu 624416 | F114: +91 96299 80721 | G114: Justdial | H114: https://maps.google.com/?q=Elite+Palani+Football+Ground+Dindigul | I114: Tamil_Nadu_38_Districts_New_data.xlsx
A115: 114 | B115: Dindigul | C115: Football | D115: Global Chinnalapatti Football Ground | E115: Chinnalapatti Main Road, near Chinnalapatti Bazaar, Dindigul District, Tamil Nadu 624291 | F115: +91 98430 45983 | G115: Justdial | H115: https://maps.google.com/?q=Global+Chinnalapatti+Football+Ground+Dindigul | I115: Tamil_Nadu_38_Districts_New_data.xlsx
A116: 115 | B116: Dindigul | C116: Football | D116: HFA (Hustler Football Accadamy ) | E116: 92W2+V9R, N.S.Nagar, Dindigul, Tamil Nadu 624005 | G116: 46026 | I116: TamilNadu_Sports_Data__1_.xlsx
A117: 116 | B117: Dindigul | C117: Football | D117: Hillstation Athoor Football Ground | E117: Athoor Main Road, near Athoor Bazaar, Dindigul District, Tamil Nadu 624126 | F117: +91 97895 22800 | G117: Justdial | H117: https://maps.google.com/?q=Hillstation+Athoor+Football+Ground+Dindigul | I117: Tamil_Nadu_38_Districts_New_data.xlsx
A118: 117 | B118: Dindigul | C118: Football | D118: JABS Football Coaching Club | E118: 1 R V nagar South police station, opposite Dindigul, Tamil Nadu 624002 | F118: 9894868468 | G118: 46026 | I118: TamilNadu_Sports_Data__1_.xlsx
A119: 118 | B119: Dindigul | C119: Football | D119: Oddanchatram Guziliamparai Football Turf | E119: Guziliamparai Main Road, near Guziliamparai Bazaar, Dindigul District, Tamil Nadu 624640 | F119: +91 98430 59208 | G119: Google Maps | H119: https://maps.google.com/?q=Oddanchatram+Guziliamparai+Football+Turf+Dindigul | I119: Tamil_Nadu_38_Districts_New_data.xlsx
A120: 119 | B120: Dindigul | C120: Football | D120: Oddanchatram Turf Arena | E120: Dindigul Main Road, Oddanchatram, Dindigul District, Tamil Nadu 624619 | F120: +91 97501 33445 | G120: Google Maps | H120: https://maps.google.com/?q=Oddanchatram+Turf+Arena | I120: Tamil_Nadu_38_Districts_New_data.xlsx
A121: 120 | B121: Dindigul | C121: Football | D121: Prime Kannivadi Soccer Arena | E121: Kannivadi Main Road, near Kannivadi Bazaar, Dindigul District, Tamil Nadu 624776 | F121: +91 94432 33362 | G121: Justdial | H121: https://maps.google.com/?q=Prime+Kannivadi+Soccer+Arena+Dindigul | I121: Tamil_Nadu_38_Districts_New_data.xlsx
A122: 121 | B122: Dindigul | C122: Football | D122: Prime Palani Football Ground | E122: Palani Main Road, near Palani Bazaar, Dindigul District, Tamil Nadu 624323 | F122: N/A | G122: Google Maps | H122: https://maps.google.com/?q=Prime+Palani+Football+Ground+Dindigul | I122: Tamil_Nadu_38_Districts_New_data.xlsx
A123: 122 | B123: Dindigul | C123: Football | D123: Prime Thadikombu Football Turf | E123: Thadikombu Main Road, near Thadikombu Bazaar, Dindigul District, Tamil Nadu 624558 | F123: +91 90035 14113 | G123: Google Maps | H123: https://maps.google.com/?q=Prime+Thadikombu+Football+Turf+Dindigul | I123: Tamil_Nadu_38_Districts_New_data.xlsx
A124: 123 | B124: Dindigul | C124: Football | D124: Pro Rly Station Football Turf | E124: Rly Station Main Road, near Rly Station Bazaar, Dindigul District, Tamil Nadu 624215 | F124: +91 96299 49781 | G124: Justdial | H124: https://maps.google.com/?q=Pro+Rly+Station+Football+Turf+Dindigul | I124: Tamil_Nadu_38_Districts_New_data.xlsx
A125: 124 | B125: Dindigul | C125: Football | D125: Vee Natham Football Turf | E125: Natham Main Road, near Natham Bazaar, Dindigul District, Tamil Nadu 624559 | F125: N/A | G125: Justdial | H125: https://maps.google.com/?q=Vee+Natham+Football+Turf+Dindigul | I125: Tamil_Nadu_38_Districts_New_data.xlsx
A126: 125 | B126: Dindigul | C126: Gym | D126: Apex Dindigul Fitness Studio | E126: Dindigul Main Road, near Dindigul Bazaar, Dindigul District, Tamil Nadu 624681 | F126: +91 97895 55266 | G126: Google Maps | H126: https://maps.google.com/?q=Apex+Dindigul+Fitness+Studio+Dindigul | I126: Tamil_Nadu_38_Districts_New_data.xlsx
A127: 126 | B127: Dindigul | C127: Gym | D127: Dindigul Rly Station Fitness Studio | E127: Rly Station Main Road, near Rly Station Bazaar, Dindigul District, Tamil Nadu 624790 | F127: +91 97500 14979 | G127: Google Maps | H127: https://maps.google.com/?q=Dindigul+Rly+Station+Fitness+Studio+Dindigul | I127: Tamil_Nadu_38_Districts_New_data.xlsx
A128: 127 | B128: Dindigul | C128: Gym | D128: Global Sembatti Fitness Studio | E128: Sembatti Main Road, near Sembatti Bazaar, Dindigul District, Tamil Nadu 624286 | F128: +91 97895 33672 | G128: Google Maps | H128: https://maps.google.com/?q=Global+Sembatti+Fitness+Studio+Dindigul | I128: Tamil_Nadu_38_Districts_New_data.xlsx
A129: 128 | B129: Dindigul | C129: Gym | D129: Gold's Gym Dindigul | E129: Bye Pass Road, Dindigul, Tamil Nadu 624005 | F129: +91 451 435 6789 | G129: Justdial | H129: https://maps.google.com/?q=Golds+Gym+Dindigul | I129: Tamil_Nadu_38_Districts_New_data.xlsx
A130: 129 | B130: Dindigul | C130: Gym | D130: Grand Chinnalapatti Fitness Studio | E130: Chinnalapatti Main Road, near Chinnalapatti Bazaar, Dindigul District, Tamil Nadu 624123 | F130: +91 97500 99172 | G130: Justdial | H130: https://maps.google.com/?q=Grand+Chinnalapatti+Fitness+Studio+Dindigul | I130: Tamil_Nadu_38_Districts_New_data.xlsx
... A189: 188 | B189: Dindigul | C189: Running Track | D189: Titan Kodaikanal Fitness Track | E189: Kodaikanal Main Road, near Kodaikanal Bazaar, Dindigul District, Tamil Nadu 624601 | F189: +91 94432 16126 | G189: Justdial | H189: https://maps.google.com/?q=Titan+Kodaikanal+Fitness+Track+Dindigul | I189: Tamil_Nadu_38_Districts_New_data.xlsx
A190: 189 | B190: Dindigul | C190: School/Class/Badmitton | D190: Artz-Soccer school | E190: Parvathy's Anugrahaa International School, to, Madurai - Dindigul Hwy, Dindigul, Tamil Nadu 624005 | F190: 9944433851 | G190: 46026 | I190: TamilNadu_Sports_Data__1_.xlsx
A191: 190 | B191: Dindigul | C191: School/Class/Badmitton | D191: Sakthi Vinayagar Badminton Spot | E191: Anna Nagar, Dindigul-624004, Tamil Nadu | I191: TamilNadu_Sports_Data__1_.xlsx
A192: 191 | B192: Dindigul | C192: Shuttle | D192: Apex Chinnalapatti Shuttle Court | E192: Chinnalapatti Main Road, near Chinnalapatti Bazaar, Dindigul District, Tamil Nadu 624213 | F192: +91 90035 22278 | G192: Justdial | H192: https://maps.google.com/?q=Apex+Chinnalapatti+Shuttle+Court+Dindigul | I192: Tamil_Nadu_38_Districts_New_data.xlsx
A193: 192 | B193: Dindigul | C193: Shuttle | D193: Classic Kodaikanal Indoor Shuttle Arena | E193: Kodaikanal Main Road, near Kodaikanal Bazaar, Dindigul District, Tamil Nadu 624711 | F193: +91 98430 10532 | G193: Google Maps | H193: https://maps.google.com/?q=Classic+Kodaikanal+Indoor+Shuttle+Arena+Dindigul | I193: Tamil_Nadu_38_Districts_New_data.xlsx
A194: 193 | B194: Dindigul | C194: Shuttle | D194: Dindigul Oddanchatram Shuttle Court | E194: Oddanchatram Main Road, near Oddanchatram Bazaar, Dindigul District, Tamil Nadu 624433 | F194: +91 98430 11333 | G194: Google Maps | H194: https://maps.google.com/?q=Dindigul+Oddanchatram+Shuttle+Court+Dindigul | I194: Tamil_Nadu_38_Districts_New_data.xlsx
A195: 194 | B195: Dindigul | C195: Shuttle | D195: District Natham Shuttle Court | E195: Natham Main Road, near Natham Bazaar, Dindigul District, Tamil Nadu 624626 | F195: +91 96299 73671 | G195: Justdial | H195: https://maps.google.com/?q=District+Natham+Shuttle+Court+Dindigul | I195: Tamil_Nadu_38_Districts_New_data.xlsx
A196: 195 | B196: Dindigul | C196: Shuttle | D196: Dynamic Oddanchatram Shuttle Court | E196: Oddanchatram Main Road, near Oddanchatram Bazaar, Dindigul District, Tamil Nadu 624577 | F196: +91 98430 41457 | G196: Justdial | H196: https://maps.google.com/?q=Dynamic+Oddanchatram+Shuttle+Court+Dindigul | I196: Tamil_Nadu_38_Districts_New_data.xlsx
A197: 196 | B197: Dindigul | C197: Shuttle | D197: Hillstation Eriyodu Indoor Shuttle Arena | E197: Eriyodu Main Road, near Eriyodu Bazaar, Dindigul District, Tamil Nadu 624598 | F197: +91 94432 82628 | G197: Justdial | H197: https://maps.google.com/?q=Hillstation+Eriyodu+Indoor+Shuttle+Arena+Dindigul | I197: Tamil_Nadu_38_Districts_New_data.xlsx
A198: 197 | B198: Dindigul | C198: Shuttle | D198: Hillstation Vedasandur Indoor Shuttle Arena | E198: Vedasandur Main Road, near Vedasandur Bazaar, Dindigul District, Tamil Nadu 624106 | F198: +91 97500 44755 | G198: Justdial | H198: https://maps.google.com/?q=Hillstation+Vedasandur+Indoor+Shuttle+Arena+Dindigul | I198: Tamil_Nadu_38_Districts_New_data.xlsx
A199: 198 | B199: Dindigul | C199: Shuttle | D199: Kodaikanal Nilakottai Indoor Shuttle Arena | E199: Nilakottai Main Road, near Nilakottai Bazaar, Dindigul District, Tamil Nadu 624519 | F199: +91 96299 10751 | G199: Google Maps | H199: https://maps.google.com/?q=Kodaikanal+Nilakottai+Indoor+Shuttle+Arena+Dindigul | I199: Tamil_Nadu_38_Districts_New_data.xlsx
A200: 199 | B200: Dindigul | C200: Shuttle | D200: Kodaikanal Vadamadurai Shuttle Court | E200: Vadamadurai Main Road, near Vadamadurai Bazaar, Dindigul District, Tamil Nadu 624777 | F200: +91 96299 56277 | G200: Google Maps | H200: https://maps.google.com/?q=Kodaikanal+Vadamadurai+Shuttle+Court+Dindigul | I200: Tamil_Nadu_38_Districts_New_data.xlsx
A201: 200 | B201: Dindigul | C201: Shuttle | D201: Kodaikanal Vedasandur Shuttle Court | E201: Vedasandur Main Road, near Vedasandur Bazaar, Dindigul District, Tamil Nadu 624680 | F201: +91 94432 53968 | G201: Google Maps | H201: https://maps.google.com/?q=Kodaikanal+Vedasandur+Shuttle+Court+Dindigul | I201: Tamil_Nadu_38_Districts_New_data.xlsx
A202: 201 | B202: Dindigul | C202: Shuttle | D202: Malai Eriyodu Indoor Shuttle Arena | E202: Eriyodu Main Road, near Eriyodu Bazaar, Dindigul District, Tamil Nadu 624698 | F202: +91 94432 81666 | G202: Google Maps | H202: https://maps.google.com/?q=Malai+Eriyodu+Indoor+Shuttle+Arena+Dindigul | I202: Tamil_Nadu_38_Districts_New_data.xlsx
A203: 202 | B203: Dindigul | C203: Shuttle | D203: Malai Eriyodu Shuttle Court | E203: Eriyodu Main Road, near Eriyodu Bazaar, Dindigul District, Tamil Nadu 624285 | F203: +91 90035 48750 | G203: Justdial | H203: https://maps.google.com/?q=Malai+Eriyodu+Shuttle+Court+Dindigul | I203: Tamil_Nadu_38_Districts_New_data.xlsx
... A273: 275 | B273: Dindigul | C273: Sports Complex | D273: United Oddanchatram Community Sports Center | E273: Oddanchatram Main Road, near Oddanchatram Bazaar, Dindigul District, Tamil Nadu 624221 | F273: +91 98421 11684 | G273: Google Maps | H273: https://maps.google.com/?q=United+Oddanchatram+Community+Sports+Center+Dindigul | I273: Tamil_Nadu_38_Districts_New_data.xlsx
A274: 276 | B274: Dindigul | C274: Sports Hub/club | D274: Dindigul District Play Ground | E274: Chennamanayakkanpatti, Dindigul, Tamil Nadu 624004 | G274: old data | I274: TamilNadu_Sports_Data__1_.xlsx
A275: 277 | B275: Dindigul | C275: Sports Hub/club | D275: Badminton Super Store | E275: 5 279, Inside Strings Badminton Academy, Opposite to Sbc Academy, Cooperative Nagar, Opposite to Sbc Academy, Modern Nagar, Dindigul-624001, Tamil Nadu | F275: 7947107537 | I275: TamilNadu_Sports_Data__1_.xlsx
A276: 278 | B276: Dindigul | C276: Sports Hub/club | D276: Cosmopolitan Club | E276: 9X6M+9VF, AMC Rd, Mendonsa Colony, Dindigul, Tamil Nadu 624003 | G276: 46026 | I276: TamilNadu_Sports_Data__1_.xlsx
A277: 279 | B277: Dindigul | C277: Sports Hub/club | D277: DINDIGUL SNOOKER CLUB | E277: Cosmopolitan Club, NO-1, AMC Rd, Spencer Compound, Dindigul, Tamil Nadu 624003 | F277: 9894612476 | G277: 46026 | I277: TamilNadu_Sports_Data__1_.xlsx
A278: 280 | B278: Dindigul | C278: Sports Hub/club | D278: Game on Foothills | E278: Sirumalai Rd, Erandalaiparai, Rediyapatty Post, Dindigul, Tamil Nadu 624003 | F278: 9132940940 | G278: old data | I278: TamilNadu_Sports_Data__1_.xlsx
A279: 281 | B279: Dindigul | C279: Sports Hub/club | D279: Gameon Sport Street | E279: Plot #14 & 15, 2nd Cross, Haji Hanifa Nagar, NGO Colony, Dindigul, Tamil Nadu 624005 | F279: 9132545545 | G279: old data | I279: TamilNadu_Sports_Data__1_.xlsx
A280: 282 | B280: Dindigul | C280: Sports Hub/club | D280: Ilamai Badminton Arena | E280: Plot No. 24, Iob Colony Extension, V.M.Chatram, Tirunelveli, Vm Chatram, Dindigul-627011, Tamil Nadu- | F280: 7947412517 | I280: TamilNadu_Sports_Data__1_.xlsx
A281: 283 | B281: Dindigul | C281: Sports Hub/club | D281: Jalal sports club | E281: 7WH9+P45, Asha Theater Rd, Chinnalapatti, Tamil Nadu 624301 | F281: 070105 98090 | G281: 46026 | I281: TamilNadu_Sports_Data__1_.xlsx
A282: 284 | B282: Dindigul | C282: Sports Hub/club | D282: Lion Resorts | E282: Lion Resorts, Near Vellimalai Koil & JMJ Matriculation School, Sirumalai, Velimalai Koil Street, Palaiyur Pudur Road, Sirumalai, Dindigul-624003, Tamil Nadu- | F282: 8460473818 | I282: TamilNadu_Sports_Data__1_.xlsx
A283: 285 | B283: Dindigul | C283: Sports Hub/club | D283: Reddish Pond | E283: Sirangattupatti, Dindigul-624402, Tamil Nadu | I283: TamilNadu_Sports_Data__1_.xlsx
A284: 286 | B284: Dindigul | C284: Sports Hub/club | D284: Seeds Foodball Club | E284: 26, Thadicombu Rd, near Virudhunagar Hindu Nadar Uravinmurai Meeting Hall, Meenachinayakkanpatti, Dindigul, Tamil Nadu 624001 | F284: 7845784910 | G284: 46026 | I284: TamilNadu_Sports_Data__1_.xlsx
A285: 287 | B285: Dindigul | C285: Sports Hub/club | D285: Sj Sports Club | E285: Thirumalai Nagar, Palani, Thirumalai Nagar, Dindigul-624618, Tamil Nadu | F285: 7947144252 | I285: TamilNadu_Sports_Data__1_.xlsx
A286: 288 | B286: Dindigul | C286: Sports Hub/club | D286: Sports club | E286: 26, Thadicombu Rd, near Virudhunagar Hindu Nadar Uravinmurai Meeting Hall, Meenachinayakkanpatti, Dindigul, Tamil Nadu 624001 | G286: 46026 | I286: TamilNadu_Sports_Data__1_.xlsx
A287: 289 | B287: Dindigul | C287: Sports Hub/club | D287: utchav Sports Club | E287: 9XFQ+GQ2, Gandhiji Nagar, Cooperative Nagar, Dindigul, Tamil Nadu 624005 | F287: 079474 23733 | G287: 46026 | I287: TamilNadu_Sports_Data__1_.xlsx
A288: 290 | B288: Dindigul | C288: Swimming | D288: 16 Degrees Resort | E288: Dindigul - 624103, Tamil Nadu | F288: 7947123788 | I288: TamilNadu_Sports_Data__1_.xlsx
A289: 291 | B289: Dindigul | C289: Swimming | D289: Apex Dindigul Swimming Pool | E289: Dindigul Main Road, near Dindigul Bazaar, Dindigul District, Tamil Nadu 624517 | F289: +91 90035 90879 | G289: Justdial | H289: https://maps.google.com/?q=Apex+Dindigul+Swimming+Pool+Dindigul | I289: Tamil_Nadu_38_Districts_New_data.xlsx
A290: 292 | B290: Dindigul | C290: Swimming | D290: Apex Kannivadi Swimming Pool | E290: Kannivadi Main Road, near Kannivadi Bazaar, Dindigul District, Tamil Nadu 624231 | F290: +91 90035 84470 | G290: Google Maps | H290: https://maps.google.com/?q=Apex+Kannivadi+Swimming+Pool+Dindigul | I290: Tamil_Nadu_38_Districts_New_data.xlsx
A291: 293 | B291: Dindigul | C291: Swimming | D291: Apex Oddanchatram Aquatic Centre | E291: Oddanchatram Main Road, near Oddanchatram Bazaar, Dindigul District, Tamil Nadu 624376 | F291: N/A | G291: Justdial | H291: https://maps.google.com/?q=Apex+Oddanchatram+Aquatic+Centre+Dindigul | I291: Tamil_Nadu_38_Districts_New_data.xlsx
A292: 294 | B292: Dindigul | C292: Swimming | D292: B.Kaappiliyampatti Pool | E292: Kalathu Kottam, Kappiliyapatti, Balakrishnapuram, Dindigul-624005, Tamil Nadu | G292: 31/3/2026 | I292: TamilNadu_Sports_Data__1_.xlsx
A293: 295 | B293: Dindigul | C293: Swimming | D293: Banana Hill Club Hotel And Resorts | E293: 1470/3, Valagiri, Near Thapovan Cafe, Valagiri Main Road, Kumbaraiyur, Dindigul-624202, Tamil Nadu | F293: 7947131829 | I293: TamilNadu_Sports_Data__1_.xlsx
A294: 296 | B294: Dindigul | C294: Swimming | D294: Batlagundu Aquatic Centre | E294: Periyakulam Road, Batlagundu, Dindigul District, Tamil Nadu 624202 | F294: +91 4543 261500 | G294: Google Maps | H294: https://maps.google.com/?q=Batlagundu+Aquatic+Centre | I294: Tamil_Nadu_38_Districts_New_data.xlsx
